Workbook

Sheet Companies
A1: No. | B1: Company
A2: 1 | B2: Reliance Industries | C2: PetroChemical
A3: 2 | B3: Deepak Nitrite | C3: PetroChemical
A4: 3 | B4: Linde India | C4: PetroChemical
A5: 4 | B5: SRF Ltd | C5: PetroChemical
A6: 5 | B6: Gujarat Fluorochemicals | C6: PetroChemical
A7: 6 | B7: NTPC | C7: Power
A8: 7 | B8: Tata Power | C8: Power
A9: 8 | B9: Adani Green | C9: Power
A10: 9 | B10: Power Grid | C10: Power
A11: 10 | B11: Indian Oil | C11: Power
A12: 11 | B12: Hindustan Zinc | C12: Mining
A13: 12 | B13: NMDC | C13: Mining
... A16: 15 | B16: MOIL | C16: Mining

Sheet Raw_Financials
A1: Company | B1: Year | C1: Revenue | D1: Net_Profit | E1: Total_Assets | F1: Total_Liabilities | G1: Current_Assets | H1: Current_Liabilities | I1: PPE(Net PPE) | J1: CapEx | K1: Depreciation | L1: Interest_Expense | M1: EBITDA | N1: Operating_Cash_Flow | O1: Net_Debt | P1: Goodwill | Q1: Intangibles
A2: Reliance Industries | B2: 2020 | C2: 43727.01 | D2: 11605.71 | E2: 184799.09 | F2: 98879.26 | G2: 26240.75 | H2: 19679.84 | I2: 27904.18 | J2: 13661.76 | K2: 7707.81 | L2: 6040.36 | M2: 10411.69 | N2: 36747.75 | O2: 66622.13 | P2: 5698.71 | Q2: 4090.95
A3: Reliance Industries | B3: 2021 | C3: 34170.23 | D3: 6433.94 | E3: 153713.46 | F3: 83875.05 | G3: 31649.17 | H3: 33355.59 | I3: 31974.69 | J3: 7921.45 | K3: 6064.53 | L3: 4780.35 | M3: 25703.52 | N3: 17491.84 | O3: 50711.72 | P3: 8739.32 | Q3: 3278.7
A4: Reliance Industries | B4: 2022 | C4: 55377.24 | D4: 5364.19 | E4: 84757.74 | F4: 130399.7 | G4: 58625.28 | H4: 39251.92 | I4: 40230.69 | J4: 5976.72 | K4: 8289.63 | L4: 4700.76 | M4: 12440.76 | N4: 24879.42 | O4: 26719.43 | P4: 11274.56 | Q4: 4552.68
A5: Reliance Industries | B5: 2023 | C5: 58126.11 | D5: 6493.69 | E5: 153010.2 | F5: 94203.93 | G5: 27394.18 | H5: 44087.54 | I5: 63756.64 | J5: 14394.99 | K5: 9763.79 | L5: 5489.5 | M5: 28437.48 | N5: 14712.31 | O5: 34799.14 | P5: 4361.82 | Q5: 4951.98
A6: Reliance Industries | B6: 2024 | C6: 44433.86 | D6: 6170.79 | E6: 199310.63 | F6: 77107.8 | G6: 31237.38 | H6: 31280.88 | I6: 32046.21 | J6: 13021.97 | K6: 4021.85 | L6: 7434.43 | M6: 25444.9 | N6: 17467.89 | O6: 25276.11 | P6: 10523.69 | Q6: 7241.14
A7: Deepak Nitrite | B7: 2020 | C7: 61450.36 | D7: 10170.16 | E7: 86106.7 | F7: 77261.92 | G7: 24634.76 | H7: 40893.1 | I7: 56164.91 | J7: 8308.98 | K7: 3944.91 | L7: 4054.91 | M7: 16503.67 | N7: 30740.15 | O7: 56877.87 | P7: 11097.7 | Q7: 5833.29
A8: Deepak Nitrite | B8: 2021 | C8: 30979.71 | D8: 9705.96 | E8: 189117.76 | F8: 95514.95 | G8: 50838.69 | H8: 29813.87 | I8: 51136.64 | J8: 9275.41 | K8: 3677.93 | L8: 3039.46 | M8: 10628.58 | N8: 28410.26 | O8: 40717.8 | P8: 8068.57 | Q8: 8445.4
A9: Deepak Nitrite | B9: 2022 | C9: 37464.61 | D9: 7283.06 | E9: 188332.67 | F9: 65591.83 | G9: 23079.2 | H9: 23692.54 | I9: 33061.06 | J9: 14296.98 | K9: 9156.84 | L9: 5667.02 | M9: 27429.21 | N9: 32591.8 | O9: 34328.5 | P9: 11140.47 | Q9: 6236.05
A10: Deepak Nitrite | B10: 2023 | C10: 65372.01 | D10: 11168.73 | E10: 122700.52 | F10: 54904.67 | G10: 29117.41 | H10: 27813.23 | I10: 65900.74 | J10: 13607.31 | K10: 3548.66 | L10: 5053.74 | M10: 18348.22 | N10: 18052.7 | O10: 30993.27 | P10: 6700.92 | Q10: 8657.46
A11: Deepak Nitrite | B11: 2024 | C11: 41160.15 | D11: 8150.32 | E11: 180452.84 | F11: 77726.66 | G11: 58871.28 | H11: 43873.42 | I11: 37589.11 | J11: 9972.49 | K11: 5606.15 | L11: 3924.2 | M11: 10737.74 | N11: 27739.11 | O11: 50133.95 | P11: 4411.83 | Q11: 4671.88
A12: Linde India | B12: 2020 | C12: 70413.29 | D12: 5916.5 | E12: 96734.23 | F12: 89050.75 | G12: 59426.02 | H12: 22261.66 | I12: 58606.78 | J12: 12616.2 | K12: 5163.46 | L12: 6141.08 | M12: 17355.66 | N12: 28307.65 | O12: 56676.49 | P12: 8286.2 | Q12: 3541.74
A13: Linde India | B13: 2021 | C13: 66765.12 | D13: 6566.24 | E13: 102977.78 | F13: 48669.76 | G13: 43635.72 | H13: 35326.93 | I13: 25829.39 | J13: 10120.93 | K13: 5085.47 | L13: 5725.86 | M13: 13487.33 | N13: 29773.44 | O13: 44336.77 | P13: 11493.84 | Q13: 3825.13
... A76: MOIL | B76: 2024 | C76: 65791.66 | D76: 5795.52 | E76: 108572.64 | F76: 93327.7 | G76: 43717.6 | H76: 32402.59 | I76: 29574.34 | J76: 13774.61 | K76: 5359.2 | L76: 3147.57 | M76: 27774.96 | N76: 36391.29 | O76: 68106.38 | P76: 10476.13 | Q76: 6931.45

Sheet Raw_ESG
A1: Company | B1: Year | C1: ESG_CapEx | D1: Green_Assets | E1: Scope1_Emissions_tCO2e | F1: Scope2_Emissions_tCO2e | G1: ESG_Score | H1: Number_of_Sustainability_Projects
A2: Reliance Industries | B2: 2020 | C2: 4372.7 | D2: 24580.14 | E2: 140826.59 | F2: 37199.48 | G2: 42.58 | H2: 8
A3: Reliance Industries | B3: 2021 | C3: 7253.57 | D3: 25425.41 | E3: 73956.19 | F3: 73650.53 | G3: 66.57 | H3: 13
A4: Reliance Industries | B4: 2022 | C4: 6159.97 | D4: 11480.89 | E4: 64489.49 | F4: 44654.89 | G4: 67.03 | H4: 10
A5: Reliance Industries | B5: 2023 | C5: 5493.29 | D5: 17169.31 | E5: 98945.28 | F5: 69602.33 | G5: 71.87 | H5: 10
A6: Reliance Industries | B6: 2024 | C6: 3280.09 | D6: 12317.38 | E6: 148565.05 | F6: 56556.93 | G6: 76.3 | H6: 10
A7: Deepak Nitrite | B7: 2020 | C7: 3279.97 | D7: 27262.07 | E7: 74205.53 | F7: 64740.57 | G7: 88.79 | H7: 14
A8: Deepak Nitrite | B8: 2021 | C8: 2790.42 | D8: 22465.96 | E8: 117213.55 | F8: 50131.85 | G8: 65.82 | H8: 2
A9: Deepak Nitrite | B9: 2022 | C9: 6830.88 | D9: 16617.96 | E9: 126161.96 | F9: 53845.19 | G9: 56.15 | H9: 3
A10: Deepak Nitrite | B10: 2023 | C10: 5505.58 | D10: 11271.17 | E10: 73763.75 | F10: 49625.88 | G10: 79.76 | H10: 9
A11: Deepak Nitrite | B11: 2024 | C11: 6040.36 | D11: 16219.65 | E11: 122821.63 | F11: 34762.15 | G11: 53.54 | H11: 7
A12: Linde India | B12: 2020 | C12: 2602.92 | D12: 16503.67 | E12: 86778.31 | F12: 61122.61 | G12: 61.95 | H12: 4
A13: Linde India | B13: 2021 | C13: 7349.55 | D13: 24592.12 | E13: 113230.58 | F13: 39038.62 | G13: 43.92 | H13: 10
... A76: MOIL | B76: 2024 | C76: 6034.29 | D76: 15572.93 | E76: 76520.24 | F76: 29267.37 | G76: 43.56 | H76: 12

Sheet Calculated_Metrics
A1: Company | B1: Year | C1: ROA (NetProfit/TotalAssets) | D1: Asset_Turnover (Revenue/TotalAssets) | E1: Working_Capital (CurrentAssets-CurrentLiabilities) | F1: Working_Cap_Turnover (Revenue/WorkingCapital) | G1: Net_Debt/EBITDA | H1: Interest_Coverage (EBITDA/InterestExpense) | I1: FCF (OperatingCashFlow - CapEx) | J1: EBITDA_Margin (EBITDA/Revenue) | K1: ESG_CapEx_pct (ESG_CapEx/CapEx) | L1: Green_Assets_pct (Green_Assets/TotalAssets) | M1: Scope1+2_Emissions | N1: ESG_Score
A2: Reliance Industries | B2: 2020 | C2: {=IF(OR(IFERROR(INDEX(Raw_Financials!$E$2:$E$76, MATCH(1, (Raw_Financials!$A$2:$A$76="Reliance Industries")*(Raw_Financials!$B$2:$B$76="2020"),0)+1),"")="",IFERROR(INDEX(Raw_Financials!$D$2:$D$76, MATCH(1, (Raw_Financials!$A$2:$A$76="Reliance Industries")*(Raw_Financials!$B$2:$B$76="2020"),0)+1),"")=""),"",(IFERROR(INDEX(Raw_Financials!$D$2:$D$76, MATCH(1, (Raw_Financials!$A$2:$A$76="Reliance Industries")*(Raw_Financials!$B$2:$B$76="2020"),0)+1),""))/(IFERROR(INDEX(Raw_Financials!$E$2:$E$76, MATCH(1, (Raw_Financials!$A$2:$A$76="Reliance Industries")*(Raw_Financials!$B$2:$B$76="2020"),0)+1),"")))} -> 0.041856712 | D2: {=IF(OR(IFERROR(INDEX(Raw_Financials!$E$2:$E$76, MATCH(1, (Raw_Financials!$A$2:$A$76="Reliance Industries")*(Raw_Financials!$B$2:$B$76="2020"),0)+1),"")="",IFERROR(INDEX(Raw_Financials!$C$2:$C$76, MATCH(1, (Raw_Financials!$A$2:$A$76="Reliance Industries")*(Raw_Financials!$B$2:$B$76="2020"),0)+1),"")=""),"",(IFERROR(INDEX(Raw_Financials!$C$2:$C$76, MATCH(1, (Raw_Financials!$A$2:$A$76="Reliance Industries")*(Raw_Financials!$B$2:$B$76="2020"),0)+1),""))/(IFERROR(INDEX(Raw_Financials!$E$2:$E$76, MATCH(1, (Raw_Financials!$A$2:$A$76="Reliance Industries")*(Raw_Financials!$B$2:$B$76="2020"),0)+1),"")))} -> 0.22229823 | E2: {=IF(OR(IFERROR(INDEX(Raw_Financials!$G$2:$G$76, MATCH(1, (Raw_Financials!$A$2:$A$76="Reliance Industries")*(Raw_Financials!$B$2:$B$76="2020"),0)+1),"")="",IFERROR(INDEX(Raw_Financials!$H$2:$H$76, MATCH(1, (Raw_Financials!$A$2:$A$76="Reliance Industries")*(Raw_Financials!$B$2:$B$76="2020"),0)+1),"")=""),"",(IFERROR(INDEX(Raw_Financials!$G$2:$G$76, MATCH(1, (Raw_Financials!$A$2:$A$76="Reliance Industries")*(Raw_Financials!$B$2:$B$76="2020"),0)+1),""))-(IFERROR(INDEX(Raw_Financials!$H$2:$H$76, MATCH(1, (Raw_Financials!$A$2:$A$76="Reliance Industries")*(Raw_Financials!$B$2:$B$76="2020"),0)+1),"")))} -> -1706.42 | F2: {=IF(OR(IFERROR(INDEX(Raw_Financials!$C$2:$C$76, MATCH(1, (Raw_Financials!$A$2:$A$76="Reliance Industries")*(Raw_Financials!$B$2:$B$76="2020"),0)+1),"")="",IF(OR(IFERROR(INDEX(Raw_Financials!$G$2:$G$76, MATCH(1, (Raw_Financials!$A$2:$A$76="Reliance Industries")*(Raw_Financials!$B$2:$B$76="2020"),0)+1),"")="",IFERROR(INDEX(Raw_Financials!$H$2:$H$76, MATCH(1, (Raw_Financials!$A$2:$A$76="Reliance Industries")*(Raw_Financials!$B$2:$B$76="2020"),0)+1),"")=""),"",(IFERROR(INDEX(Raw_Financials!$G$2:$G$76, MATCH(1, (Raw_Financials!$A$2:$A$76="Reliance Industries")*(Raw_Financials!$B$2:$B$76="2020"),0)+1),""))-(IFERROR(INDEX(Raw_Financials!$H$2:$H$76, MATCH(1, (Raw_Financials!$A$2:$A$76="Reliance Industries")*(Raw_Financials!$B$2:$B$76="2020"),0)+1),"")))=""),"",(IFERROR(INDEX(Raw_Financials!$C$2:$C$76, MATCH(1, (Raw_Financials!$A$2:$A$76="Reliance Industries")*(Raw_Financials!$B$2:$B$76="2020"),0)+1),""))/(IF(OR(IFERROR(INDEX(Raw_Financials!$G$2:$G$76, MATCH(1, (Raw_Financials!$A$2:$A$76="Reliance Industries")*(Raw_Financials!$B$2:$B$76="2020"),0)+1),"")="",IFERROR(INDEX(Raw_Financials!$H$2:$H$76, MATCH(1, (Raw_Financials!$A$2:$A$76="Reliance Industries")*(Raw_Financials!$B$2:$B$76="2020"),0)+1),"")=""),"",(IFERROR(INDEX(Raw_Financials!$G$2:$G$76, MATCH(1, (Raw_Financials!$A$2:$A$76="Reliance Industries")*(Raw_Financials!$B$2:$B$76="2020"),0)+1),""))-(IFERROR(INDEX(Raw_Financials!$H$2:$H$76, MATCH(1, (Raw_Financials!$A$2:$A$76="Reliance Industries")*(Raw_Financials!$B$2:$B$76="2020"),0)+1),"")))))} -> -20.024513 | G2: {=IF(OR(IFERROR(INDEX(Raw_Financials!$O$2:$O$76, MATCH(1, (Raw_Financials!$A$2:$A$76="Reliance Industries")*(Raw_Financials!$B$2:$B$76="2020"),0)+1),"")="",IFERROR(INDEX(Raw_Financials!$M$2:$M$76, MATCH(1, (Raw_Financials!$A$2:$A$76="Reliance Industries")*(Raw_Financials!$B$2:$B$76="2020"),0)+1),"")=""),"",(IFERROR(INDEX(Raw_Financials!$O$2:$O$76, MATCH(1, (Raw_Financials!$A$2:$A$76="Reliance Industries")*(Raw_Financials!$B$2:$B$76="2020"),0)+1),""))/(IFERROR(INDEX(Raw_Financials!$M$2:$M$76, MATCH(1, (Raw_Financials!$A$2:$A$76="Reliance Industries")*(Raw_Financials!$B$2:$B$76="2020"),0)+1),"")))} -> 1.9729485 | H2: {=IF(OR(IFERROR(INDEX(Raw_Financials!$M$2:$M$76, MATCH(1, (Raw_Financials!$A$2:$A$76="Reliance Industries")*(Raw_Financials!$B$2:$B$76="2020"),0)+1),"")="",IFERROR(INDEX(Raw_Financials!$L$2:$L$76, MATCH(1, (Raw_Financials!$A$2:$A$76="Reliance Industries")*(Raw_Financials!$B$2:$B$76="2020"),0)+1),"")=""),"",(IFERROR(INDEX(Raw_Financials!$M$2:$M$76, MATCH(1, (Raw_Financials!$A$2:$A$76="Reliance Industries")*(Raw_Financials!$B$2:$B$76="2020"),0)+1),""))/(IFERROR(INDEX(Raw_Financials!$L$2:$L$76, MATCH(1, (Raw_Financials!$A$2:$A$76="Reliance Industries")*(Raw_Financials!$B$2:$B$76="2020"),0)+1),"")))} -> 5.3769117 | I2: {=IF(OR(IFERROR(INDEX(Raw_Financials!$N$2:$N$76, MATCH(1, (Raw_Financials!$A$2:$A$76="Reliance Industries")*(Raw_Financials!$B$2:$B$76="2020"),0)+1),"")="",IFERROR(INDEX(Raw_Financials!$J$2:$J$76, MATCH(1, (Raw_Financials!$A$2:$A$76="Reliance Industries")*(Raw_Financials!$B$2:$B$76="2020"),0)+1),"")=""),"",(IFERROR(INDEX(Raw_Financials!$N$2:$N$76, MATCH(1, (Raw_Financials!$A$2:$A$76="Reliance Industries")*(Raw_Financials!$B$2:$B$76="2020"),0)+1),""))-(IFERROR(INDEX(Raw_Financials!$J$2:$J$76, MATCH(1, (Raw_Financials!$A$2:$A$76="Reliance Industries")*(Raw_Financials!$B$2:$B$76="2020"),0)+1),"")))} -> 9570.39 | J2: {=IF(OR(IFERROR(INDEX(Raw_Financials!$M$2:$M$76, MATCH(1, (Raw_Financials!$A$2:$A$76="Reliance Industries")*(Raw_Financials!$B$2:$B$76="2020"),0)+1),"")="",IFERROR(INDEX(Raw_Financials!$C$2:$C$76, MATCH(1, (Raw_Financials!$A$2:$A$76="Reliance Industries")*(Raw_Financials!$B$2:$B$76="2020"),0)+1),"")=""),"",(IFERROR(INDEX(Raw_Financials!$M$2:$M$76, MATCH(1, (Raw_Financials!$A$2:$A$76="Reliance Industries")*(Raw_Financials!$B$2:$B$76="2020"),0)+1),""))/(IFERROR(INDEX(Raw_Financials!$C$2:$C$76, MATCH(1, (Raw_Financials!$A$2:$A$76="Reliance Industries")*(Raw_Financials!$B$2:$B$76="2020"),0)+1),"")))} -> 0.7522197 | K2: {=IF(OR(IFERROR(INDEX(Raw_ESG!$C$2:$C$76, MATCH(1, (Raw_ESG!$A$2:$A$76="Reliance Industries")*(Raw_ESG!$B$2:$B$76="2020"),0)+1),"")="",IFERROR(INDEX(Raw_Financials!$J$2:$J$76, MATCH(1, (Raw_Financials!$A$2:$A$76="Reliance Industries")*(Raw_Financials!$B$2:$B$76="2020"),0)+1),"")=""),"",(IFERROR(INDEX(Raw_ESG!$C$2:$C$76, MATCH(1, (Raw_ESG!$A$2:$A$76="Reliance Industries")*(Raw_ESG!$B$2:$B$76="2020"),0)+1),""))/(IFERROR(INDEX(Raw_Financials!$J$2:$J$76, MATCH(1, (Raw_Financials!$A$2:$A$76="Reliance Industries")*(Raw_Financials!$B$2:$B$76="2020"),0)+1),"")))} -> 0.91568715 | L2: {=IF(OR(IFERROR(INDEX(Raw_ESG!$D$2:$D$76, MATCH(1, (Raw_ESG!$A$2:$A$76="Reliance Industries")*(Raw_ESG!$B$2:$B$76="2020"),0)+1),"")="",IFERROR(INDEX(Raw_Financials!$E$2:$E$76, MATCH(1, (Raw_Financials!$A$2:$A$76="Reliance Industries")*(Raw_Financials!$B$2:$B$76="2020"),0)+1),"")=""),"",(IFERROR(INDEX(Raw_ESG!$D$2:$D$76, MATCH(1, (Raw_ESG!$A$2:$A$76="Reliance Industries")*(Raw_ESG!$B$2:$B$76="2020"),0)+1),""))/(IFERROR(INDEX(Raw_Financials!$E$2:$E$76, MATCH(1, (Raw_Financials!$A$2:$A$76="Reliance Industries")*(Raw_Financials!$B$2:$B$76="2020"),0)+1),"")))} -> 0.16540783 | M2: {=IF(OR(IFERROR(INDEX(Raw_ESG!$E$2:$E$76, MATCH(1, (Raw_ESG!$A$2:$A$76="Reliance Industries")*(Raw_ESG!$B$2:$B$76="2020"),0)+1),"")="",IFERROR(INDEX(Raw_ESG!$F$2:$F$76, MATCH(1, (Raw_ESG!$A$2:$A$76="Reliance Industries")*(Raw_ESG!$B$2:$B$76="2020"),0)+1),"")=""),"",(IFERROR(INDEX(Raw_ESG!$E$2:$E$76, MATCH(1, (Raw_ESG!$A$2:$A$76="Reliance Industries")*(Raw_ESG!$B$2:$B$76="2020"),0)+1),""))+(IFERROR(INDEX(Raw_ESG!$F$2:$F$76, MATCH(1, (Raw_ESG!$A$2:$A$76="Reliance Industries")*(Raw_ESG!$B$2:$B$76="2020"),0)+1),"")))} -> 147606.72 | N2: {=IFERROR(INDEX(Raw_ESG!$G$2:$G$76, MATCH(1, (Raw_ESG!$A$2:$A$76="Reliance Industries")*(Raw_ESG!$B$2:$B$76="2020"),0)+1),"")} -> 66.57
A3: Reliance Industries | B3: 2021 | C3: {=IF(OR(IFERROR(INDEX(Raw_Financials!$E$2:$E$76, MATCH(1, (Raw_Financials!$A$2:$A$76="Reliance Industries")*(Raw_Financials!$B$2:$B$76="2021"),0)+1),"")="",IFERROR(INDEX(Raw_Financials!$D$2:$D$76, MATCH(1, (Raw_Financials!$A$2:$A$76="Reliance Industries")*(Raw_Financials!$B$2:$B$76="2021"),0)+1),"")=""),"",(IFERROR(INDEX(Raw_Financials!$D$2:$D$76, MATCH(1, (Raw_Financials!$A$2:$A$76="Reliance Industries")*(Raw_Financials!$B$2:$B$76="2021"),0)+1),""))/(IFERROR(INDEX(Raw_Financials!$E$2:$E$76, MATCH(1, (Raw_Financials!$A$2:$A$76="Reliance Industries")*(Raw_Financials!$B$2:$B$76="2021"),0)+1),"")))} -> 0.063288497 | D3: {=IF(OR(IFERROR(INDEX(Raw_Financials!$E$2:$E$76, MATCH(1, (Raw_Financials!$A$2:$A$76="Reliance Industries")*(Raw_Financials!$B$2:$B$76="2021"),0)+1),"")="",IFERROR(INDEX(Raw_Financials!$C$2:$C$76, MATCH(1, (Raw_Financials!$A$2:$A$76="Reliance Industries")*(Raw_Financials!$B$2:$B$76="2021"),0)+1),"")=""),"",(IFERROR(INDEX(Raw_Financials!$C$2:$C$76, MATCH(1, (Raw_Financials!$A$2:$A$76="Reliance Industries")*(Raw_Financials!$B$2:$B$76="2021"),0)+1),""))/(IFERROR(INDEX(Raw_Financials!$E$2:$E$76, MATCH(1, (Raw_Financials!$A$2:$A$76="Reliance Industries")*(Raw_Financials!$B$2:$B$76="2021"),0)+1),"")))} -> 0.65335909 | E3: {=IF(OR(IFERROR(INDEX(Raw_Financials!$G$2:$G$76, MATCH(1, (Raw_Financials!$A$2:$A$76="Reliance Industries")*(Raw_Financials!$B$2:$B$76="2021"),0)+1),"")="",IFERROR(INDEX(Raw_Financials!$H$2:$H$76, MATCH(1, (Raw_Financials!$A$2:$A$76="Reliance Industries")*(Raw_Financials!$B$2:$B$76="2021"),0)+1),"")=""),"",(IFERROR(INDEX(Raw_Financials!$G$2:$G$76, MATCH(1, (Raw_Financials!$A$2:$A$76="Reliance Industries")*(Raw_Financials!$B$2:$B$76="2021"),0)+1),""))-(IFERROR(INDEX(Raw_Financials!$H$2:$H$76, MATCH(1, (Raw_Financials!$A$2:$A$76="Reliance Industries")*(Raw_Financials!$B$2:$B$76="2021"),0)+1),"")))} -> 19373.36 | F3: {=IF(OR(IFERROR(INDEX(Raw_Financials!$C$2:$C$76, MATCH(1, (Raw_Financials!$A$2:$A$76="Reliance Industries")*(Raw_Financials!$B$2:$B$76="2021"),0)+1),"")="",IF(OR(IFERROR(INDEX(Raw_Financials!$G$2:$G$76, MATCH(1, (Raw_Financials!$A$2:$A$76="Reliance Industries")*(Raw_Financials!$B$2:$B$76="2021"),0)+1),"")="",IFERROR(INDEX(Raw_Financials!$H$2:$H$76, MATCH(1, (Raw_Financials!$A$2:$A$76="Reliance Industries")*(Raw_Financials!$B$2:$B$76="2021"),0)+1),"")=""),"",(IFERROR(INDEX(Raw_Financials!$G$2:$G$76, MATCH(1, (Raw_Financials!$A$2:$A$76="Reliance Industries")*(Raw_Financials!$B$2:$B$76="2021"),0)+1),""))-(IFERROR(INDEX(Raw_Financials!$H$2:$H$76, MATCH(1, (Raw_Financials!$A$2:$A$76="Reliance Industries")*(Raw_Financials!$B$2:$B$76="2021"),0)+1),"")))=""),"",(IFERROR(INDEX(Raw_Financials!$C$2:$C$76, MATCH(1, (Raw_Financials!$A$2:$A$76="Reliance Industries")*(Raw_Financials!$B$2:$B$76="2021"),0)+1),""))/(IF(OR(IFERROR(INDEX(Raw_Financials!$G$2:$G$76, MATCH(1, (Raw_Financials!$A$2:$A$76="Reliance Industries")*(Raw_Financials!$B$2:$B$76="2021"),0)+1),"")="",IFERROR(INDEX(Raw_Financials!$H$2:$H$76, MATCH(1, (Raw_Financials!$A$2:$A$76="Reliance Industries")*(Raw_Financials!$B$2:$B$76="2021"),0)+1),"")=""),"",(IFERROR(INDEX(Raw_Financials!$G$2:$G$76, MATCH(1, (Raw_Financials!$A$2:$A$76="Reliance Industries")*(Raw_Financials!$B$2:$B$76="2021"),0)+1),""))-(IFERROR(INDEX(Raw_Financials!$H$2:$H$76, MATCH(1, (Raw_Financials!$A$2:$A$76="Reliance Industries")*(Raw_Financials!$B$2:$B$76="2021"),0)+1),"")))))} -> 2.8584221 | G3: {=IF(OR(IFERROR(INDEX(Raw_Financials!$O$2:$O$76, MATCH(1, (Raw_Financials!$A$2:$A$76="Reliance Industries")*(Raw_Financials!$B$2:$B$76="2021"),0)+1),"")="",IFERROR(INDEX(Raw_Financials!$M$2:$M$76, MATCH(1, (Raw_Financials!$A$2:$A$76="Reliance Industries")*(Raw_Financials!$B$2:$B$76="2021"),0)+1),"")=""),"",(IFERROR(INDEX(Raw_Financials!$O$2:$O$76, MATCH(1, (Raw_Financials!$A$2:$A$76="Reliance Industries")*(Raw_Financials!$B$2:$B$76="2021"),0)+1),""))/(IFERROR(INDEX(Raw_Financials!$M$2:$M$76, MATCH(1, (Raw_Financials!$A$2:$A$76="Reliance Industries")*(Raw_Financials!$B$2:$B$76="2021"),0)+1),"")))} -> 2.1477329 | H3: {=IF(OR(IFERROR(INDEX(Raw_Financials!$M$2:$M$76, MATCH(1, (Raw_Financials!$A$2:$A$76="Reliance Industries")*(Raw_Financials!$B$2:$B$76="2021"),0)+1),"")="",IFERROR(INDEX(Raw_Financials!$L$2:$L$76, MATCH(1, (Raw_Financials!$A$2:$A$76="Reliance Industries")*(Raw_Financials!$B$2:$B$76="2021"),0)+1),"")=""),"",(IFERROR(INDEX(Raw_Financials!$M$2:$M$76, MATCH(1, (Raw_Financials!$A$2:$A$76="Reliance Industries")*(Raw_Financials!$B$2:$B$76="2021"),0)+1),""))/(IFERROR(INDEX(Raw_Financials!$L$2:$L$76, MATCH(1, (Raw_Financials!$A$2:$A$76="Reliance Industries")*(Raw_Financials!$B$2:$B$76="2021"),0)+1),"")))} -> 2.6465423 | I3: {=IF(OR(IFERROR(INDEX(Raw_Financials!$N$2:$N$76, MATCH(1, (Raw_Financials!$A$2:$A$76="Reliance Industries")*(Raw_Financials!$B$2:$B$76="2021"),0)+1),"")="",IFERROR(INDEX(Raw_Financials!$J$2:$J$76, MATCH(1, (Raw_Financials!$A$2:$A$76="Reliance Industries")*(Raw_Financials!$B$2:$B$76="2021"),0)+1),"")=""),"",(IFERROR(INDEX(Raw_Financials!$N$2:$N$76, MATCH(1, (Raw_Financials!$A$2:$A$76="Reliance Industries")*(Raw_Financials!$B$2:$B$76="2021"),0)+1),""))-(IFERROR(INDEX(Raw_Financials!$J$2:$J$76, MATCH(1, (Raw_Financials!$A$2:$A$76="Reliance Industries")*(Raw_Financials!$B$2:$B$76="2021"),0)+1),"")))} -> 18902.7 | J3: {=IF(OR(IFERROR(INDEX(Raw_Financials!$M$2:$M$76, MATCH(1, (Raw_Financials!$A$2:$A$76="Reliance Industries")*(Raw_Financials!$B$2:$B$76="2021"),0)+1),"")="",IFERROR(INDEX(Raw_Financials!$C$2:$C$76, MATCH(1, (Raw_Financials!$A$2:$A$76="Reliance Industries")*(Raw_Financials!$B$2:$B$76="2021"),0)+1),"")=""),"",(IFERROR(INDEX(Raw_Financials!$M$2:$M$76, MATCH(1, (Raw_Financials!$A$2:$A$76="Reliance Industries")*(Raw_Financials!$B$2:$B$76="2021"),0)+1),""))/(IFERROR(INDEX(Raw_Financials!$C$2:$C$76, MATCH(1, (Raw_Financials!$A$2:$A$76="Reliance Industries")*(Raw_Financials!$B$2:$B$76="2021"),0)+1),"")))} -> 0.22465475 | K3: {=IF(OR(IFERROR(INDEX(Raw_ESG!$C$2:$C$76, MATCH(1, (Raw_ESG!$A$2:$A$76="Reliance Industries")*(Raw_ESG!$B$2:$B$76="2021"),0)+1),"")="",IFERROR(INDEX(Raw_Financials!$J$2:$J$76, MATCH(1, (Raw_Financials!$A$2:$A$76="Reliance Industries")*(Raw_Financials!$B$2:$B$76="2021"),0)+1),"")=""),"",(IFERROR(INDEX(Raw_ESG!$C$2:$C$76, MATCH(1, (Raw_ESG!$A$2:$A$76="Reliance Industries")*(Raw_ESG!$B$2:$B$76="2021"),0)+1),""))/(IFERROR(INDEX(Raw_Financials!$J$2:$J$76, MATCH(1, (Raw_Financials!$A$2:$A$76="Reliance Industries")*(Raw_Financials!$B$2:$B$76="2021"),0)+1),"")))} -> 1.0306606 | L3: {=IF(OR(IFERROR(INDEX(Raw_ESG!$D$2:$D$76, MATCH(1, (Raw_ESG!$A$2:$A$76="Reliance Industries")*(Raw_ESG!$B$2:$B$76="2021"),0)+1),"")="",IFERROR(INDEX(Raw_Financials!$E$2:$E$76, MATCH(1, (Raw_Financials!$A$2:$A$76="Reliance Industries")*(Raw_Financials!$B$2:$B$76="2021"),0)+1),"")=""),"",(IFERROR(INDEX(Raw_ESG!$D$2:$D$76, MATCH(1, (Raw_ESG!$A$2:$A$76="Reliance Industries")*(Raw_ESG!$B$2:$B$76="2021"),0)+1),""))/(IFERROR(INDEX(Raw_Financials!$E$2:$E$76, MATCH(1, (Raw_Financials!$A$2:$A$76="Reliance Industries")*(Raw_Financials!$B$2:$B$76="2021"),0)+1),"")))} -> 0.13545536 | M3: {=IF(OR(IFERROR(INDEX(Raw_ESG!$E$2:$E$76, MATCH(1, (Raw_ESG!$A$2:$A$76="Reliance Industries")*(Raw_ESG!$B$2:$B$76="2021"),0)+1),"")="",IFERROR(INDEX(Raw_ESG!$F$2:$F$76, MATCH(1, (Raw_ESG!$A$2:$A$76="Reliance Industries")*(Raw_ESG!$B$2:$B$76="2021"),0)+1),"")=""),"",(IFERROR(INDEX(Raw_ESG!$E$2:$E$76, MATCH(1, (Raw_ESG!$A$2:$A$76="Reliance Industries")*(Raw_ESG!$B$2:$B$76="2021"),0)+1),""))+(IFERROR(INDEX(Raw_ESG!$F$2:$F$76, MATCH(1, (Raw_ESG!$A$2:$A$76="Reliance Industries")*(Raw_ESG!$B$2:$B$76="2021"),0)+1),"")))} -> 109144.38 | N3: {=IFERROR(INDEX(Raw_ESG!$G$2:$G$76, MATCH(1, (Raw_ESG!$A$2:$A$76="Reliance Industries")*(Raw_ESG!$B$2:$B$76="2021"),0)+1),"")} -> 67.03
A4: Reliance Industries | B4: 2022 | C4: {=IF(OR(IFERROR(INDEX(Raw_Financials!$E$2:$E$76, MATCH(1, (Raw_Financials!$A$2:$A$76="Reliance Industries")*(Raw_Financials!$B$2:$B$76="2022"),0)+1),"")="",IFERROR(INDEX(Raw_Financials!$D$2:$D$76, MATCH(1, (Raw_Financials!$A$2:$A$76="Reliance Industries")*(Raw_Financials!$B$2:$B$76="2022"),0)+1),"")=""),"",(IFERROR(INDEX(Raw_Financials!$D$2:$D$76, MATCH(1, (Raw_Financials!$A$2:$A$76="Reliance Industries")*(Raw_Financials!$B$2:$B$76="2022"),0)+1),""))/(IFERROR(INDEX(Raw_Financials!$E$2:$E$76, MATCH(1, (Raw_Financials!$A$2:$A$76="Reliance Industries")*(Raw_Financials!$B$2:$B$76="2022"),0)+1),"")))} -> 0.042439589 | D4: {=IF(OR(IFERROR(INDEX(Raw_Financials!$E$2:$E$76, MATCH(1, (Raw_Financials!$A$2:$A$76="Reliance Industries")*(Raw_Financials!$B$2:$B$76="2022"),0)+1),"")="",IFERROR(INDEX(Raw_Financials!$C$2:$C$76, MATCH(1, (Raw_Financials!$A$2:$A$76="Reliance Industries")*(Raw_Financials!$B$2:$B$76="2022"),0)+1),"")=""),"",(IFERROR(INDEX(Raw_Financials!$C$2:$C$76, MATCH(1, (Raw_Financials!$A$2:$A$76="Reliance Industries")*(Raw_Financials!$B$2:$B$76="2022"),0)+1),""))/(IFERROR(INDEX(Raw_Financials!$E$2:$E$76, MATCH(1, (Raw_Financials!$A$2:$A$76="Reliance Industries")*(Raw_Financials!$B$2:$B$76="2022"),0)+1),"")))} -> 0.37988389 | E4: {=IF(OR(IFERROR(INDEX(Raw_Financials!$G$2:$G$76, MATCH(1, (Raw_Financials!$A$2:$A$76="Reliance Industries")*(Raw_Financials!$B$2:$B$76="2022"),0)+1),"")="",IFERROR(INDEX(Raw_Financials!$H$2:$H$76, MATCH(1, (Raw_Financials!$A$2:$A$76="Reliance Industries")*(Raw_Financials!$B$2:$B$76="2022"),0)+1),"")=""),"",(IFERROR(INDEX(Raw_Financials!$G$2:$G$76, MATCH(1, (Raw_Financials!$A$2:$A$76="Reliance Industries")*(Raw_Financials!$B$2:$B$76="2022"),0)+1),""))-(IFERROR(INDEX(Raw_Financials!$H$2:$H$76, MATCH(1, (Raw_Financials!$A$2:$A$76="Reliance Industries")*(Raw_Financials!$B$2:$B$76="2022"),0)+1),"")))} -> -16693.36 | F4: {=IF(OR(IFERROR(INDEX(Raw_Financials!$C$2:$C$76, MATCH(1, (Raw_Financials!$A$2:$A$76="Reliance Industries")*(Raw_Financials!$B$2:$B$76="2022"),0)+1),"")="",IF(OR(IFERROR(INDEX(Raw_Financials!$G$2:$G$76, MATCH(1, (Raw_Financials!$A$2:$A$76="Reliance Industries")*(Raw_Financials!$B$2:$B$76="2022"),0)+1),"")="",IFERROR(INDEX(Raw_Financials!$H$2:$H$76, MATCH(1, (Raw_Financials!$A$2:$A$76="Reliance Industries")*(Raw_Financials!$B$2:$B$76="2022"),0)+1),"")=""),"",(IFERROR(INDEX(Raw_Financials!$G$2:$G$76, MATCH(1, (Raw_Financials!$A$2:$A$76="Reliance Industries")*(Raw_Financials!$B$2:$B$76="2022"),0)+1),""))-(IFERROR(INDEX(Raw_Financials!$H$2:$H$76, MATCH(1, (Raw_Financials!$A$2:$A$76="Reliance Industries")*(Raw_Financials!$B$2:$B$76="2022"),0)+1),"")))=""),"",(IFERROR(INDEX(Raw_Financials!$C$2:$C$76, MATCH(1, (Raw_Financials!$A$2:$A$76="Reliance Industries")*(Raw_Financials!$B$2:$B$76="2022"),0)+1),""))/(IF(OR(IFERROR(INDEX(Raw_Financials!$G$2:$G$76, MATCH(1, (Raw_Financials!$A$2:$A$76="Reliance Industries")*(Raw_Financials!$B$2:$B$76="2022"),0)+1),"")="",IFERROR(INDEX(Raw_Financials!$H$2:$H$76, MATCH(1, (Raw_Financials!$A$2:$A$76="Reliance Industries")*(Raw_Financials!$B$2:$B$76="2022"),0)+1),"")=""),"",(IFERROR(INDEX(Raw_Financials!$G$2:$G$76, MATCH(1, (Raw_Financials!$A$2:$A$76="Reliance Industries")*(Raw_Financials!$B$2:$B$76="2022"),0)+1),""))-(IFERROR(INDEX(Raw_Financials!$H$2:$H$76, MATCH(1, (Raw_Financials!$A$2:$A$76="Reliance Industries")*(Raw_Financials!$B$2:$B$76="2022"),0)+1),"")))))} -> -3.4819898 | G4: {=IF(OR(IFERROR(INDEX(Raw_Financials!$O$2:$O$76, MATCH(1, (Raw_Financials!$A$2:$A$76="Reliance Industries")*(Raw_Financials!$B$2:$B$76="2022"),0)+1),"")="",IFERROR(INDEX(Raw_Financials!$M$2:$M$76, MATCH(1, (Raw_Financials!$A$2:$A$76="Reliance Industries")*(Raw_Financials!$B$2:$B$76="2022"),0)+1),"")=""),"",(IFERROR(INDEX(Raw_Financials!$O$2:$O$76, MATCH(1, (Raw_Financials!$A$2:$A$76="Reliance Industries")*(Raw_Financials!$B$2:$B$76="2022"),0)+1),""))/(IFERROR(INDEX(Raw_Financials!$M$2:$M$76, MATCH(1, (Raw_Financials!$A$2:$A$76="Reliance Industries")*(Raw_Financials!$B$2:$B$76="2022"),0)+1),"")))} -> 1.2237069 | H4: {=IF(OR(IFERROR(INDEX(Raw_Financials!$M$2:$M$76, MATCH(1, (Raw_Financials!$A$2:$A$76="Reliance Industries")*(Raw_Financials!$B$2:$B$76="2022"),0)+1),"")="",IFERROR(INDEX(Raw_Financials!$L$2:$L$76, MATCH(1, (Raw_Financials!$A$2:$A$76="Reliance Industries")*(Raw_Financials!$B$2:$B$76="2022"),0)+1),"")=""),"",(IFERROR(INDEX(Raw_Financials!$M$2:$M$76, MATCH(1, (Raw_Financials!$A$2:$A$76="Reliance Industries")*(Raw_Financials!$B$2:$B$76="2022"),0)+1),""))/(IFERROR(INDEX(Raw_Financials!$L$2:$L$76, MATCH(1, (Raw_Financials!$A$2:$A$76="Reliance Industries")*(Raw_Financials!$B$2:$B$76="2022"),0)+1),"")))} -> 5.1803407 | I4: {=IF(OR(IFERROR(INDEX(Raw_Financials!$N$2:$N$76, MATCH(1, (Raw_Financials!$A$2:$A$76="Reliance Industries")*(Raw_Financials!$B$2:$B$76="2022"),0)+1),"")="",IFERROR(INDEX(Raw_Financials!$J$2:$J$76, MATCH(1, (Raw_Financials!$A$2:$A$76="Reliance Industries")*(Raw_Financials!$B$2:$B$76="2022"),0)+1),"")=""),"",(IFERROR(INDEX(Raw_Financials!$N$2:$N$76, MATCH(1, (Raw_Financials!$A$2:$A$76="Reliance Industries")*(Raw_Financials!$B$2:$B$76="2022"),0)+1),""))-(IFERROR(INDEX(Raw_Financials!$J$2:$J$76, MATCH(1, (Raw_Financials!$A$2:$A$76="Reliance Industries")*(Raw_Financials!$B$2:$B$76="2022"),0)+1),"")))} -> 317.32 | J4: {=IF(OR(IFERROR(INDEX(Raw_Financials!$M$2:$M$76, MATCH(1, (Raw_Financials!$A$2:$A$76="Reliance Industries")*(Raw_Financials!$B$2:$B$76="2022"),0)+1),"")="",IFERROR(INDEX(Raw_Financials!$C$2:$C$76, MATCH(1, (Raw_Financials!$A$2:$A$76="Reliance Industries")*(Raw_Financials!$B$2:$B$76="2022"),0)+1),"")=""),"",(IFERROR(INDEX(Raw_Financials!$M$2:$M$76, MATCH(1, (Raw_Financials!$A$2:$A$76="Reliance Industries")*(Raw_Financials!$B$2:$B$76="2022"),0)+1),""))/(IFERROR(INDEX(Raw_Financials!$C$2:$C$76, MATCH(1, (Raw_Financials!$A$2:$A$76="Reliance Industries")*(Raw_Financials!$B$2:$B$76="2022"),0)+1),"")))} -> 0.48923762 | K4: {=IF(OR(IFERROR(INDEX(Raw_ESG!$C$2:$C$76, MATCH(1, (Raw_ESG!$A$2:$A$76="Reliance Industries")*(Raw_ESG!$B$2:$B$76="2022"),0)+1),"")="",IFERROR(INDEX(Raw_Financials!$J$2:$J$76, MATCH(1, (Raw_Financials!$A$2:$A$76="Reliance Industries")*(Raw_Financials!$B$2:$B$76="2022"),0)+1),"")=""),"",(IFERROR(INDEX(Raw_ESG!$C$2:$C$76, MATCH(1, (Raw_ESG!$A$2:$A$76="Reliance Industries")*(Raw_ESG!$B$2:$B$76="2022"),0)+1),""))/(IFERROR(INDEX(Raw_Financials!$J$2:$J$76, MATCH(1, (Raw_Financials!$A$2:$A$76="Reliance Industries")*(Raw_Financials!$B$2:$B$76="2022"),0)+1),"")))} -> 0.38161124 | L4: {=IF(OR(IFERROR(INDEX(Raw_ESG!$D$2:$D$76, MATCH(1, (Raw_ESG!$A$2:$A$76="Reliance Industries")*(Raw_ESG!$B$2:$B$76="2022"),0)+1),"")="",IFERROR(INDEX(Raw_Financials!$E$2:$E$76, MATCH(1, (Raw_Financials!$A$2:$A$76="Reliance Industries")*(Raw_Financials!$B$2:$B$76="2022"),0)+1),"")=""),"",(IFERROR(INDEX(Raw_ESG!$D$2:$D$76, MATCH(1, (Raw_ESG!$A$2:$A$76="Reliance Industries")*(Raw_ESG!$B$2:$B$76="2022"),0)+1),""))/(IFERROR(INDEX(Raw_Financials!$E$2:$E$76, MATCH(1, (Raw_Financials!$A$2:$A$76="Reliance Industries")*(Raw_Financials!$B$2:$B$76="2022"),0)+1),"")))} -> 0.11221023 | M4: {=IF(OR(IFERROR(INDEX(Raw_ESG!$E$2:$E$76, MATCH(1, (Raw_ESG!$A$2:$A$76="Reliance Industries")*(Raw_ESG!$B$2:$B$76="2022"),0)+1),"")="",IFERROR(INDEX(Raw_ESG!$F$2:$F$76, MATCH(1, (Raw_ESG!$A$2:$A$76="Reliance Industries")*(Raw_ESG!$B$2:$B$76="2022"),0)+1),"")=""),"",(IFERROR(INDEX(Raw_ESG!$E$2:$E$76, MATCH(1, (Raw_ESG!$A$2:$A$76="Reliance Industries")*(Raw_ESG!$B$2:$B$76="2022"),0)+1),""))+(IFERROR(INDEX(Raw_ESG!$F$2:$F$76, MATCH(1, (Raw_ESG!$A$2:$A$76="Reliance Industries")*(Raw_ESG!$B$2:$B$76="2022"),0)+1),"")))} -> 168547.61 | N4: {=IFERROR(INDEX(Raw_ESG!$G$2:$G$76, MATCH(1, (Raw_ESG!$A$2:$A$76="Reliance Industries")*(Raw_ESG!$B$2:$B$76="2022"),0)+1),"")} -> 71.87
A5: Reliance Industries | B5: 2023 | C5: {=IF(OR(IFERROR(INDEX(Raw_Financials!$E$2:$E$76, MATCH(1, (Raw_Financials!$A$2:$A$76="Reliance Industries")*(Raw_Financials!$B$2:$B$76="2023"),0)+1),"")="",IFERROR(INDEX(Raw_Financials!$D$2:$D$76, MATCH(1, (Raw_Financials!$A$2:$A$76="Reliance Industries")*(Raw_Financials!$B$2:$B$76="2023"),0)+1),"")=""),"",(IFERROR(INDEX(Raw_Financials!$D$2:$D$76, MATCH(1, (Raw_Financials!$A$2:$A$76="Reliance Industries")*(Raw_Financials!$B$2:$B$76="2023"),0)+1),""))/(IFERROR(INDEX(Raw_Financials!$E$2:$E$76, MATCH(1, (Raw_Financials!$A$2:$A$76="Reliance Industries")*(Raw_Financials!$B$2:$B$76="2023"),0)+1),"")))} -> 0.030960667 | D5: {=IF(OR(IFERROR(INDEX(Raw_Financials!$E$2:$E$76, MATCH(1, (Raw_Financials!$A$2:$A$76="Reliance Industries")*(Raw_Financials!$B$2:$B$76="2023"),0)+1),"")="",IFERROR(INDEX(Raw_Financials!$C$2:$C$76, MATCH(1, (Raw_Financials!$A$2:$A$76="Reliance Industries")*(Raw_Financials!$B$2:$B$76="2023"),0)+1),"")=""),"",(IFERROR(INDEX(Raw_Financials!$C$2:$C$76, MATCH(1, (Raw_Financials!$A$2:$A$76="Reliance Industries")*(Raw_Financials!$B$2:$B$76="2023"),0)+1),""))/(IFERROR(INDEX(Raw_Financials!$E$2:$E$76, MATCH(1, (Raw_Financials!$A$2:$A$76="Reliance Industries")*(Raw_Financials!$B$2:$B$76="2023"),0)+1),"")))} -> 0.22293773 | E5: {=IF(OR(IFERROR(INDEX(Raw_Financials!$G$2:$G$76, MATCH(1, (Raw_Financials!$A$2:$A$76="Reliance Industries")*(Raw_Financials!$B$2:$B$76="2023"),0)+1),"")="",IFERROR(INDEX(Raw_Financials!$H$2:$H$76, MATCH(1, (Raw_Financials!$A$2:$A$76="Reliance Industries")*(Raw_Financials!$B$2:$B$76="2023"),0)+1),"")=""),"",(IFERROR(INDEX(Raw_Financials!$G$2:$G$76, MATCH(1, (Raw_Financials!$A$2:$A$76="Reliance Industries")*(Raw_Financials!$B$2:$B$76="2023"),0)+1),""))-(IFERROR(INDEX(Raw_Financials!$H$2:$H$76, MATCH(1, (Raw_Financials!$A$2:$A$76="Reliance Industries")*(Raw_Financials!$B$2:$B$76="2023"),0)+1),"")))} -> -43.5 | F5: {=IF(OR(IFERROR(INDEX(Raw_Financials!$C$2:$C$76, MATCH(1, (Raw_Financials!$A$2:$A$76="Reliance Industries")*(Raw_Financials!$B$2:$B$76="2023"),0)+1),"")="",IF(OR(IFERROR(INDEX(Raw_Financials!$G$2:$G$76, MATCH(1, (Raw_Financials!$A$2:$A$76="Reliance Industries")*(Raw_Financials!$B$2:$B$76="2023"),0)+1),"")="",IFERROR(INDEX(Raw_Financials!$H$2:$H$76, MATCH(1, (Raw_Financials!$A$2:$A$76="Reliance Industries")*(Raw_Financials!$B$2:$B$76="2023"),0)+1),"")=""),"",(IFERROR(INDEX(Raw_Financials!$G$2:$G$76, MATCH(1, (Raw_Financials!$A$2:$A$76="Reliance Industries")*(Raw_Financials!$B$2:$B$76="2023"),0)+1),""))-(IFERROR(INDEX(Raw_Financials!$H$2:$H$76, MATCH(1, (Raw_Financials!$A$2:$A$76="Reliance Industries")*(Raw_Financials!$B$2:$B$76="2023"),0)+1),"")))=""),"",(IFERROR(INDEX(Raw_Financials!$C$2:$C$76, MATCH(1, (Raw_Financials!$A$2:$A$76="Reliance Industries")*(Raw_Financials!$B$2:$B$76="2023"),0)+1),""))/(IF(OR(IFERROR(INDEX(Raw_Financials!$G$2:$G$76, MATCH(1, (Raw_Financials!$A$2:$A$76="Reliance Industries")*(Raw_Financials!$B$2:$B$76="2023"),0)+1),"")="",IFERROR(INDEX(Raw_Financials!$H$2:$H$76, MATCH(1, (Raw_Financials!$A$2:$A$76="Reliance Industries")*(Raw_Financials!$B$2:$B$76="2023"),0)+1),"")=""),"",(IFERROR(INDEX(Raw_Financials!$G$2:$G$76, MATCH(1, (Raw_Financials!$A$2:$A$76="Reliance Industries")*(Raw_Financials!$B$2:$B$76="2023"),0)+1),""))-(IFERROR(INDEX(Raw_Financials!$H$2:$H$76, MATCH(1, (Raw_Financials!$A$2:$A$76="Reliance Industries")*(Raw_Financials!$B$2:$B$76="2023"),0)+1),"")))))} -> -1021.468 | G5: {=IF(OR(IFERROR(INDEX(Raw_Financials!$O$2:$O$76, MATCH(1, (Raw_Financials!$A$2:$A$76="Reliance Industries")*(Raw_Financials!$B$2:$B$76="2023"),0)+1),"")="",IFERROR(INDEX(Raw_Financials!$M$2:$M$76, MATCH(1, (Raw_Financials!$A$2:$A$76="Reliance Industries")*(Raw_Financials!$B$2:$B$76="2023"),0)+1),"")=""),"",(IFERROR(INDEX(Raw_Financials!$O$2:$O$76, MATCH(1, (Raw_Financials!$A$2:$A$76="Reliance Industries")*(Raw_Financials!$B$2:$B$76="2023"),0)+1),""))/(IFERROR(INDEX(Raw_Financials!$M$2:$M$76, MATCH(1, (Raw_Financials!$A$2:$A$76="Reliance Industries")*(Raw_Financials!$B$2:$B$76="2023"),0)+1),"")))} -> 0.99336645 | H5: {=IF(OR(IFERROR(INDEX(Raw_Financials!$M$2:$M$76, MATCH(1, (Raw_Financials!$A$2:$A$76="Reliance Industries")*(Raw_Financials!$B$2:$B$76="2023"),0)+1),"")="",IFERROR(INDEX(Raw_Financials!$L$2:$L$76, MATCH(1, (Raw_Financials!$A$2:$A$76="Reliance Industries")*(Raw_Financials!$B$2:$B$76="2023"),0)+1),"")=""),"",(IFERROR(INDEX(Raw_Financials!$M$2:$M$76, MATCH(1, (Raw_Financials!$A$2:$A$76="Reliance Industries")*(Raw_Financials!$B$2:$B$76="2023"),0)+1),""))/(IFERROR(INDEX(Raw_Financials!$L$2:$L$76, MATCH(1, (Raw_Financials!$A$2:$A$76="Reliance Industries")*(Raw_Financials!$B$2:$B$76="2023"),0)+1),"")))} -> 3.4225758 | I5: {=IF(OR(IFERROR(INDEX(Raw_Financials!$N$2:$N$76, MATCH(1, (Raw_Financials!$A$2:$A$76="Reliance Industries")*(Raw_Financials!$B$2:$B$76="2023"),0)+1),"")="",IFERROR(INDEX(Raw_Financials!$J$2:$J$76, MATCH(1, (Raw_Financials!$A$2:$A$76="Reliance Industries")*(Raw_Financials!$B$2:$B$76="2023"),0)+1),"")=""),"",(IFERROR(INDEX(Raw_Financials!$N$2:$N$76, MATCH(1, (Raw_Financials!$A$2:$A$76="Reliance Industries")*(Raw_Financials!$B$2:$B$76="2023"),0)+1),""))-(IFERROR(INDEX(Raw_Financials!$J$2:$J$76, MATCH(1, (Raw_Financials!$A$2:$A$76="Reliance Industries")*(Raw_Financials!$B$2:$B$76="2023"),0)+1),"")))} -> 4445.92 | J5: {=IF(OR(IFERROR(INDEX(Raw_Financials!$M$2:$M$76, MATCH(1, (Raw_Financials!$A$2:$A$76="Reliance Industries")*(Raw_Financials!$B$2:$B$76="2023"),0)+1),"")="",IFERROR(INDEX(Raw_Financials!$C$2:$C$76, MATCH(1, (Raw_Financials!$A$2:$A$76="Reliance Industries")*(Raw_Financials!$B$2:$B$76="2023"),0)+1),"")=""),"",(IFERROR(INDEX(Raw_Financials!$M$2:$M$76, MATCH(1, (Raw_Financials!$A$2:$A$76="Reliance Industries")*(Raw_Financials!$B$2:$B$76="2023"),0)+1),""))/(IFERROR(INDEX(Raw_Financials!$C$2:$C$76, MATCH(1, (Raw_Financials!$A$2:$A$76="Reliance Industries")*(Raw_Financials!$B$2:$B$76="2023"),0)+1),"")))} -> 0.57264663 | K5: {=IF(OR(IFERROR(INDEX(Raw_ESG!$C$2:$C$76, MATCH(1, (Raw_ESG!$A$2:$A$76="Reliance Industries")*(Raw_ESG!$B$2:$B$76="2023"),0)+1),"")="",IFERROR(INDEX(Raw_Financials!$J$2:$J$76, MATCH(1, (Raw_Financials!$A$2:$A$76="Reliance Industries")*(Raw_Financials!$B$2:$B$76="2023"),0)+1),"")=""),"",(IFERROR(INDEX(Raw_ESG!$C$2:$C$76, MATCH(1, (Raw_ESG!$A$2:$A$76="Reliance Industries")*(Raw_ESG!$B$2:$B$76="2023"),0)+1),""))/(IFERROR(INDEX(Raw_Financials!$J$2:$J$76, MATCH(1, (Raw_Financials!$A$2:$A$76="Reliance Industries")*(Raw_Financials!$B$2:$B$76="2023"),0)+1),"")))} -> 0.25188892 | L5: {=IF(OR(IFERROR(INDEX(Raw_ESG!$D$2:$D$76, MATCH(1, (Raw_ESG!$A$2:$A$76="Reliance Industries")*(Raw_ESG!$B$2:$B$76="2023"),0)+1),"")="",IFERROR(INDEX(Raw_Financials!$E$2:$E$76, MATCH(1, (Raw_Financials!$A$2:$A$76="Reliance Industries")*(Raw_Financials!$B$2:$B$76="2023"),0)+1),"")=""),"",(IFERROR(INDEX(Raw_ESG!$D$2:$D$76, MATCH(1, (Raw_ESG!$A$2:$A$76="Reliance Industries")*(Raw_ESG!$B$2:$B$76="2023"),0)+1),""))/(IFERROR(INDEX(Raw_Financials!$E$2:$E$76, MATCH(1, (Raw_Financials!$A$2:$A$76="Reliance Industries")*(Raw_Financials!$B$2:$B$76="2023"),0)+1),"")))} -> 0.061799915 | M5: {=IF(OR(IFERROR(INDEX(Raw_ESG!$E$2:$E$76, MATCH(1, (Raw_ESG!$A$2:$A$76="Reliance Industries")*(Raw_ESG!$B$2:$B$76="2023"),0)+1),"")="",IFERROR(INDEX(Raw_ESG!$F$2:$F$76, MATCH(1, (Raw_ESG!$A$2:$A$76="Reliance Industries")*(Raw_ESG!$B$2:$B$76="2023"),0)+1),"")=""),"",(IFERROR(INDEX(Raw_ESG!$E$2:$E$76, MATCH(1, (Raw_ESG!$A$2:$A$76="Reliance Industries")*(Raw_ESG!$B$2:$B$76="2023"),0)+1),""))+(IFERROR(INDEX(Raw_ESG!$F$2:$F$76, MATCH(1, (Raw_ESG!$A$2:$A$76="Reliance Industries")*(Raw_ESG!$B$2:$B$76="2023"),0)+1),"")))} -> 205121.98 | N5: {=IFERROR(INDEX(Raw_ESG!$G$2:$G$76, MATCH(1, (Raw_ESG!$A$2:$A$76="Reliance Industries")*(Raw_ESG!$B$2:$B$76="2023"),0)+1),"")} -> 76.3
A6: Reliance Industries | B6: 2024 | C6: {=IF(OR(IFERROR(INDEX(Raw_Financials!$E$2:$E$76, MATCH(1, (Raw_Financials!$A$2:$A$76="Reliance Industries")*(Raw_Financials!$B$2:$B$76="2024"),0)+1),"")="",IFERROR(INDEX(Raw_Financials!$D$2:$D$76, MATCH(1, (Raw_Financials!$A$2:$A$76="Reliance Industries")*(Raw_Financials!$B$2:$B$76="2024"),0)+1),"")=""),"",(IFERROR(INDEX(Raw_Financials!$D$2:$D$76, MATCH(1, (Raw_Financials!$A$2:$A$76="Reliance Industries")*(Raw_Financials!$B$2:$B$76="2024"),0)+1),""))/(IFERROR(INDEX(Raw_Financials!$E$2:$E$76, MATCH(1, (Raw_Financials!$A$2:$A$76="Reliance Industries")*(Raw_Financials!$B$2:$B$76="2024"),0)+1),"")))} -> 0.11811113 | D6: {=IF(OR(IFERROR(INDEX(Raw_Financials!$E$2:$E$76, MATCH(1, (Raw_Financials!$A$2:$A$76="Reliance Industries")*(Raw_Financials!$B$2:$B$76="2024"),0)+1),"")="",IFERROR(INDEX(Raw_Financials!$C$2:$C$76, MATCH(1, (Raw_Financials!$A$2:$A$76="Reliance Industries")*(Raw_Financials!$B$2:$B$76="2024"),0)+1),"")=""),"",(IFERROR(INDEX(Raw_Financials!$C$2:$C$76, MATCH(1, (Raw_Financials!$A$2:$A$76="Reliance Industries")*(Raw_Financials!$B$2:$B$76="2024"),0)+1),""))/(IFERROR(INDEX(Raw_Financials!$E$2:$E$76, MATCH(1, (Raw_Financials!$A$2:$A$76="Reliance Industries")*(Raw_Financials!$B$2:$B$76="2024"),0)+1),"")))} -> 0.71365364 | E6: {=IF(OR(IFERROR(INDEX(Raw_Financials!$G$2:$G$76, MATCH(1, (Raw_Financials!$A$2:$A$76="Reliance Industries")*(Raw_Financials!$B$2:$B$76="2024"),0)+1),"")="",IFERROR(INDEX(Raw_Financials!$H$2:$H$76, MATCH(1, (Raw_Financials!$A$2:$A$76="Reliance Industries")*(Raw_Financials!$B$2:$B$76="2024"),0)+1),"")=""),"",(IFERROR(INDEX(Raw_Financials!$G$2:$G$76, MATCH(1, (Raw_Financials!$A$2:$A$76="Reliance Industries")*(Raw_Financials!$B$2:$B$76="2024"),0)+1),""))-(IFERROR(INDEX(Raw_Financials!$H$2:$H$76, MATCH(1, (Raw_Financials!$A$2:$A$76="Reliance Industries")*(Raw_Financials!$B$2:$B$76="2024"),0)+1),"")))} -> -16258.34 | F6: {=IF(OR(IFERROR(INDEX(Raw_Financials!$C$2:$C$76, MATCH(1, (Raw_Financials!$A$2:$A$76="Reliance Industries")*(Raw_Financials!$B$2:$B$76="2024"),0)+1),"")="",IF(OR(IFERROR(INDEX(Raw_Financials!$G$2:$G$76, MATCH(1, (Raw_Financials!$A$2:$A$76="Reliance Industries")*(Raw_Financials!$B$2:$B$76="2024"),0)+1),"")="",IFERROR(INDEX(Raw_Financials!$H$2:$H$76, MATCH(1, (Raw_Financials!$A$2:$A$76="Reliance Industries")*(Raw_Financials!$B$2:$B$76="2024"),0)+1),"")=""),"",(IFERROR(INDEX(Raw_Financials!$G$2:$G$76, MATCH(1, (Raw_Financials!$A$2:$A$76="Reliance Industries")*(Raw_Financials!$B$2:$B$76="2024"),0)+1),""))-(IFERROR(INDEX(Raw_Financials!$H$2:$H$76, MATCH(1, (Raw_Financials!$A$2:$A$76="Reliance Industries")*(Raw_Financials!$B$2:$B$76="2024"),0)+1),"")))=""),"",(IFERROR(INDEX(Raw_Financials!$C$2:$C$76, MATCH(1, (Raw_Financials!$A$2:$A$76="Reliance Industries")*(Raw_Financials!$B$2:$B$76="2024"),0)+1),""))/(IF(OR(IFERROR(INDEX(Raw_Financials!$G$2:$G$76, MATCH(1, (Raw_Financials!$A$2:$A$76="Reliance Industries")*(Raw_Financials!$B$2:$B$76="2024"),0)+1),"")="",IFERROR(INDEX(Raw_Financials!$H$2:$H$76, MATCH(1, (Raw_Financials!$A$2:$A$76="Reliance Industries")*(Raw_Financials!$B$2:$B$76="2024"),0)+1),"")=""),"",(IFERROR(INDEX(Raw_Financials!$G$2:$G$76, MATCH(1, (Raw_Financials!$A$2:$A$76="Reliance Industries")*(Raw_Financials!$B$2:$B$76="2024"),0)+1),""))-(IFERROR(INDEX(Raw_Financials!$H$2:$H$76, MATCH(1, (Raw_Financials!$A$2:$A$76="Reliance Industries")*(Raw_Financials!$B$2:$B$76="2024"),0)+1),"")))))} -> -3.7796208 | G6: {=IF(OR(IFERROR(INDEX(Raw_Financials!$O$2:$O$76, MATCH(1, (Raw_Financials!$A$2:$A$76="Reliance Industries")*(Raw_Financials!$B$2:$B$76="2024"),0)+1),"")="",IFERROR(INDEX(Raw_Financials!$M$2:$M$76, MATCH(1, (Raw_Financials!$A$2:$A$76="Reliance Industries")*(Raw_Financials!$B$2:$B$76="2024"),0)+1),"")=""),"",(IFERROR(INDEX(Raw_Financials!$O$2:$O$76, MATCH(1, (Raw_Financials!$A$2:$A$76="Reliance Industries")*(Raw_Financials!$B$2:$B$76="2024"),0)+1),""))/(IFERROR(INDEX(Raw_Financials!$M$2:$M$76, MATCH(1, (Raw_Financials!$A$2:$A$76="Reliance Industries")*(Raw_Financials!$B$2:$B$76="2024"),0)+1),"")))} -> 3.4463771 | H6: {=IF(OR(IFERROR(INDEX(Raw_Financials!$M$2:$M$76, MATCH(1, (Raw_Financials!$A$2:$A$76="Reliance Industries")*(Raw_Financials!$B$2:$B$76="2024"),0)+1),"")="",IFERROR(INDEX(Raw_Financials!$L$2:$L$76, MATCH(1, (Raw_Financials!$A$2:$A$76="Reliance Industries")*(Raw_Financials!$B$2:$B$76="2024"),0)+1),"")=""),"",(IFERROR(INDEX(Raw_Financials!$M$2:$M$76, MATCH(1, (Raw_Financials!$A$2:$A$76="Reliance Industries")*(Raw_Financials!$B$2:$B$76="2024"),0)+1),""))/(IFERROR(INDEX(Raw_Financials!$L$2:$L$76, MATCH(1, (Raw_Financials!$A$2:$A$76="Reliance Industries")*(Raw_Financials!$B$2:$B$76="2024"),0)+1),"")))} -> 4.0700459 | I6: {=IF(OR(IFERROR(INDEX(Raw_Financials!$N$2:$N$76, MATCH(1, (Raw_Financials!$A$2:$A$76="Reliance Industries")*(Raw_Financials!$B$2:$B$76="2024"),0)+1),"")="",IFERROR(INDEX(Raw_Financials!$J$2:$J$76, MATCH(1, (Raw_Financials!$A$2:$A$76="Reliance Industries")*(Raw_Financials!$B$2:$B$76="2024"),0)+1),"")=""),"",(IFERROR(INDEX(Raw_Financials!$N$2:$N$76, MATCH(1, (Raw_Financials!$A$2:$A$76="Reliance Industries")*(Raw_Financials!$B$2:$B$76="2024"),0)+1),""))-(IFERROR(INDEX(Raw_Financials!$J$2:$J$76, MATCH(1, (Raw_Financials!$A$2:$A$76="Reliance Industries")*(Raw_Financials!$B$2:$B$76="2024"),0)+1),"")))} -> 22431.17 | J6: {=IF(OR(IFERROR(INDEX(Raw_Financials!$M$2:$M$76, MATCH(1, (Raw_Financials!$A$2:$A$76="Reliance Industries")*(Raw_Financials!$B$2:$B$76="2024"),0)+1),"")="",IFERROR(INDEX(Raw_Financials!$C$2:$C$76, MATCH(1, (Raw_Financials!$A$2:$A$76="Reliance Industries")*(Raw_Financials!$B$2:$B$76="2024"),0)+1),"")=""),"",(IFERROR(INDEX(Raw_Financials!$M$2:$M$76, MATCH(1, (Raw_Financials!$A$2:$A$76="Reliance Industries")*(Raw_Financials!$B$2:$B$76="2024"),0)+1),""))/(IFERROR(INDEX(Raw_Financials!$C$2:$C$76, MATCH(1, (Raw_Financials!$A$2:$A$76="Reliance Industries")*(Raw_Financials!$B$2:$B$76="2024"),0)+1),"")))} -> 0.26856913 | K6: {=IF(OR(IFERROR(INDEX(Raw_ESG!$C$2:$C$76, MATCH(1, (Raw_ESG!$A$2:$A$76="Reliance Industries")*(Raw_ESG!$B$2:$B$76="2024"),0)+1),"")="",IFERROR(INDEX(Raw_Financials!$J$2:$J$76, MATCH(1, (Raw_Financials!$A$2:$A$76="Reliance Industries")*(Raw_Financials!$B$2:$B$76="2024"),0)+1),"")=""),"",(IFERROR(INDEX(Raw_ESG!$C$2:$C$76, MATCH(1, (Raw_ESG!$A$2:$A$76="Reliance Industries")*(Raw_ESG!$B$2:$B$76="2024"),0)+1),""))/(IFERROR(INDEX(Raw_Financials!$J$2:$J$76, MATCH(1, (Raw_Financials!$A$2:$A$76="Reliance Industries")*(Raw_Financials!$B$2:$B$76="2024"),0)+1),"")))} -> 0.39475002 | L6: {=IF(OR(IFERROR(INDEX(Raw_ESG!$D$2:$D$76, MATCH(1, (Raw_ESG!$A$2:$A$76="Reliance Industries")*(Raw_ESG!$B$2:$B$76="2024"),0)+1),"")="",IFERROR(INDEX(Raw_Financials!$E$2:$E$76, MATCH(1, (Raw_Financials!$A$2:$A$76="Reliance Industries")*(Raw_Financials!$B$2:$B$76="2024"),0)+1),"")=""),"",(IFERROR(INDEX(Raw_ESG!$D$2:$D$76, MATCH(1, (Raw_ESG!$A$2:$A$76="Reliance Industries")*(Raw_ESG!$B$2:$B$76="2024"),0)+1),""))/(IFERROR(INDEX(Raw_Financials!$E$2:$E$76, MATCH(1, (Raw_Financials!$A$2:$A$76="Reliance Industries")*(Raw_Financials!$B$2:$B$76="2024"),0)+1),"")))} -> 0.316608 | M6: {=IF(OR(IFERROR(INDEX(Raw_ESG!$E$2:$E$76, MATCH(1, (Raw_ESG!$A$2:$A$76="Reliance Industries")*(Raw_ESG!$B$2:$B$76="2024"),0)+1),"")="",IFERROR(INDEX(Raw_ESG!$F$2:$F$76, MATCH(1, (Raw_ESG!$A$2:$A$76="Reliance Industries")*(Raw_ESG!$B$2:$B$76="2024"),0)+1),"")=""),"",(IFERROR(INDEX(Raw_ESG!$E$2:$E$76, MATCH(1, (Raw_ESG!$A$2:$A$76="Reliance Industries")*(Raw_ESG!$B$2:$B$76="2024"),0)+1),""))+(IFERROR(INDEX(Raw_ESG!$F$2:$F$76, MATCH(1, (Raw_ESG!$A$2:$A$76="Reliance Industries")*(Raw_ESG!$B$2:$B$76="2024"),0)+1),"")))} -> 138946.1 | N6: {=IFERROR(INDEX(Raw_ESG!$G$2:$G$76, MATCH(1, (Raw_ESG!$A$2:$A$76="Reliance Industries")*(Raw_ESG!$B$2:$B$76="2024"),0)+1),"")} -> 88.79
A7: Deepak Nitrite | B7: 2020 | C7: {=IF(OR(IFERROR(INDEX(Raw_Financials!$E$2:$E$76, MATCH(1, (Raw_Financials!$A$2:$A$76="Deepak Nitrite")*(Raw_Financials!$B$2:$B$76="2020"),0)+1),"")="",IFERROR(INDEX(Raw_Financials!$D$2:$D$76, MATCH(1, (Raw_Financials!$A$2:$A$76="Deepak Nitrite")*(Raw_Financials!$B$2:$B$76="2020"),0)+1),"")=""),"",(IFERROR(INDEX(Raw_Financials!$D$2:$D$76, MATCH(1, (Raw_Financials!$A$2:$A$76="Deepak Nitrite")*(Raw_Financials!$B$2:$B$76="2020"),0)+1),""))/(IFERROR(INDEX(Raw_Financials!$E$2:$E$76, MATCH(1, (Raw_Financials!$A$2:$A$76="Deepak Nitrite")*(Raw_Financials!$B$2:$B$76="2020"),0)+1),"")))} -> 0.051322308 | D7: {=IF(OR(IFERROR(INDEX(Raw_Financials!$E$2:$E$76, MATCH(1, (Raw_Financials!$A$2:$A$76="Deepak Nitrite")*(Raw_Financials!$B$2:$B$76="2020"),0)+1),"")="",IFERROR(INDEX(Raw_Financials!$C$2:$C$76, MATCH(1, (Raw_Financials!$A$2:$A$76="Deepak Nitrite")*(Raw_Financials!$B$2:$B$76="2020"),0)+1),"")=""),"",(IFERROR(INDEX(Raw_Financials!$C$2:$C$76, MATCH(1, (Raw_Financials!$A$2:$A$76="Deepak Nitrite")*(Raw_Financials!$B$2:$B$76="2020"),0)+1),""))/(IFERROR(INDEX(Raw_Financials!$E$2:$E$76, MATCH(1, (Raw_Financials!$A$2:$A$76="Deepak Nitrite")*(Raw_Financials!$B$2:$B$76="2020"),0)+1),"")))} -> 0.16381174 | E7: {=IF(OR(IFERROR(INDEX(Raw_Financials!$G$2:$G$76, MATCH(1, (Raw_Financials!$A$2:$A$76="Deepak Nitrite")*(Raw_Financials!$B$2:$B$76="2020"),0)+1),"")="",IFERROR(INDEX(Raw_Financials!$H$2:$H$76, MATCH(1, (Raw_Financials!$A$2:$A$76="Deepak Nitrite")*(Raw_Financials!$B$2:$B$76="2020"),0)+1),"")=""),"",(IFERROR(INDEX(Raw_Financials!$G$2:$G$76, MATCH(1, (Raw_Financials!$A$2:$A$76="Deepak Nitrite")*(Raw_Financials!$B$2:$B$76="2020"),0)+1),""))-(IFERROR(INDEX(Raw_Financials!$H$2:$H$76, MATCH(1, (Raw_Financials!$A$2:$A$76="Deepak Nitrite")*(Raw_Financials!$B$2:$B$76="2020"),0)+1),"")))} -> 21024.82 | F7: {=IF(OR(IFERROR(INDEX(Raw_Financials!$C$2:$C$76, MATCH(1, (Raw_Financials!$A$2:$A$76="Deepak Nitrite")*(Raw_Financials!$B$2:$B$76="2020"),0)+1),"")="",IF(OR(IFERROR(INDEX(Raw_Financials!$G$2:$G$76, MATCH(1, (Raw_Financials!$A$2:$A$76="Deepak Nitrite")*(Raw_Financials!$B$2:$B$76="2020"),0)+1),"")="",IFERROR(INDEX(Raw_Financials!$H$2:$H$76, MATCH(1, (Raw_Financials!$A$2:$A$76="Deepak Nitrite")*(Raw_Financials!$B$2:$B$76="2020"),0)+1),"")=""),"",(IFERROR(INDEX(Raw_Financials!$G$2:$G$76, MATCH(1, (Raw_Financials!$A$2:$A$76="Deepak Nitrite")*(Raw_Financials!$B$2:$B$76="2020"),0)+1),""))-(IFERROR(INDEX(Raw_Financials!$H$2:$H$76, MATCH(1, (Raw_Financials!$A$2:$A$76="Deepak Nitrite")*(Raw_Financials!$B$2:$B$76="2020"),0)+1),"")))=""),"",(IFERROR(INDEX(Raw_Financials!$C$2:$C$76, MATCH(1, (Raw_Financials!$A$2:$A$76="Deepak Nitrite")*(Raw_Financials!$B$2:$B$76="2020"),0)+1),""))/(IF(OR(IFERROR(INDEX(Raw_Financials!$G$2:$G$76, MATCH(1, (Raw_Financials!$A$2:$A$76="Deepak Nitrite")*(Raw_Financials!$B$2:$B$76="2020"),0)+1),"")="",IFERROR(INDEX(Raw_Financials!$H$2:$H$76, MATCH(1, (Raw_Financials!$A$2:$A$76="Deepak Nitrite")*(Raw_Financials!$B$2:$B$76="2020"),0)+1),"")=""),"",(IFERROR(INDEX(Raw_Financials!$G$2:$G$76, MATCH(1, (Raw_Financials!$A$2:$A$76="Deepak Nitrite")*(Raw_Financials!$B$2:$B$76="2020"),0)+1),""))-(IFERROR(INDEX(Raw_Financials!$H$2:$H$76, MATCH(1, (Raw_Financials!$A$2:$A$76="Deepak Nitrite")*(Raw_Financials!$B$2:$B$76="2020"),0)+1),"")))))} -> 1.4734828 | G7: {=IF(OR(IFERROR(INDEX(Raw_Financials!$O$2:$O$76, MATCH(1, (Raw_Financials!$A$2:$A$76="Deepak Nitrite")*(Raw_Financials!$B$2:$B$76="2020"),0)+1),"")="",IFERROR(INDEX(Raw_Financials!$M$2:$M$76, MATCH(1, (Raw_Financials!$A$2:$A$76="Deepak Nitrite")*(Raw_Financials!$B$2:$B$76="2020"),0)+1),"")=""),"",(IFERROR(INDEX(Raw_Financials!$O$2:$O$76, MATCH(1, (Raw_Financials!$A$2:$A$76="Deepak Nitrite")*(Raw_Financials!$B$2:$B$76="2020"),0)+1),""))/(IFERROR(INDEX(Raw_Financials!$M$2:$M$76, MATCH(1, (Raw_Financials!$A$2:$A$76="Deepak Nitrite")*(Raw_Financials!$B$2:$B$76="2020"),0)+1),"")))} -> 3.8309727 | H7: {=IF(OR(IFERROR(INDEX(Raw_Financials!$M$2:$M$76, MATCH(1, (Raw_Financials!$A$2:$A$76="Deepak Nitrite")*(Raw_Financials!$B$2:$B$76="2020"),0)+1),"")="",IFERROR(INDEX(Raw_Financials!$L$2:$L$76, MATCH(1, (Raw_Financials!$A$2:$A$76="Deepak Nitrite")*(Raw_Financials!$B$2:$B$76="2020"),0)+1),"")=""),"",(IFERROR(INDEX(Raw_Financials!$M$2:$M$76, MATCH(1, (Raw_Financials!$A$2:$A$76="Deepak Nitrite")*(Raw_Financials!$B$2:$B$76="2020"),0)+1),""))/(IFERROR(INDEX(Raw_Financials!$L$2:$L$76, MATCH(1, (Raw_Financials!$A$2:$A$76="Deepak Nitrite")*(Raw_Financials!$B$2:$B$76="2020"),0)+1),"")))} -> 3.4968646 | I7: {=IF(OR(IFERROR(INDEX(Raw_Financials!$N$2:$N$76, MATCH(1, (Raw_Financials!$A$2:$A$76="Deepak Nitrite")*(Raw_Financials!$B$2:$B$76="2020"),0)+1),"")="",IFERROR(INDEX(Raw_Financials!$J$2:$J$76, MATCH(1, (Raw_Financials!$A$2:$A$76="Deepak Nitrite")*(Raw_Financials!$B$2:$B$76="2020"),0)+1),"")=""),"",(IFERROR(INDEX(Raw_Financials!$N$2:$N$76, MATCH(1, (Raw_Financials!$A$2:$A$76="Deepak Nitrite")*(Raw_Financials!$B$2:$B$76="2020"),0)+1),""))-(IFERROR(INDEX(Raw_Financials!$J$2:$J$76, MATCH(1, (Raw_Financials!$A$2:$A$76="Deepak Nitrite")*(Raw_Financials!$B$2:$B$76="2020"),0)+1),"")))} -> 19134.85 | J7: {=IF(OR(IFERROR(INDEX(Raw_Financials!$M$2:$M$76, MATCH(1, (Raw_Financials!$A$2:$A$76="Deepak Nitrite")*(Raw_Financials!$B$2:$B$76="2020"),0)+1),"")="",IFERROR(INDEX(Raw_Financials!$C$2:$C$76, MATCH(1, (Raw_Financials!$A$2:$A$76="Deepak Nitrite")*(Raw_Financials!$B$2:$B$76="2020"),0)+1),"")=""),"",(IFERROR(INDEX(Raw_Financials!$M$2:$M$76, MATCH(1, (Raw_Financials!$A$2:$A$76="Deepak Nitrite")*(Raw_Financials!$B$2:$B$76="2020"),0)+1),""))/(IFERROR(INDEX(Raw_Financials!$C$2:$C$76, MATCH(1, (Raw_Financials!$A$2:$A$76="Deepak Nitrite")*(Raw_Financials!$B$2:$B$76="2020"),0)+1),"")))} -> 0.34308197 | K7: {=IF(OR(IFERROR(INDEX(Raw_ESG!$C$2:$C$76, MATCH(1, (Raw_ESG!$A$2:$A$76="Deepak Nitrite")*(Raw_ESG!$B$2:$B$76="2020"),0)+1),"")="",IFERROR(INDEX(Raw_Financials!$J$2:$J$76, MATCH(1, (Raw_Financials!$A$2:$A$76="Deepak Nitrite")*(Raw_Financials!$B$2:$B$76="2020"),0)+1),"")=""),"",(IFERROR(INDEX(Raw_ESG!$C$2:$C$76, MATCH(1, (Raw_ESG!$A$2:$A$76="Deepak Nitrite")*(Raw_ESG!$B$2:$B$76="2020"),0)+1),""))/(IFERROR(INDEX(Raw_Financials!$J$2:$J$76, MATCH(1, (Raw_Financials!$A$2:$A$76="Deepak Nitrite")*(Raw_Financials!$B$2:$B$76="2020"),0)+1),"")))} -> 0.30084061 | L7: {=IF(OR(IFERROR(INDEX(Raw_ESG!$D$2:$D$76, MATCH(1, (Raw_ESG!$A$2:$A$76="Deepak Nitrite")*(Raw_ESG!$B$2:$B$76="2020"),0)+1),"")="",IFERROR(INDEX(Raw_Financials!$E$2:$E$76, MATCH(1, (Raw_Financials!$A$2:$A$76="Deepak Nitrite")*(Raw_Financials!$B$2:$B$76="2020"),0)+1),"")=""),"",(IFERROR(INDEX(Raw_ESG!$D$2:$D$76, MATCH(1, (Raw_ESG!$A$2:$A$76="Deepak Nitrite")*(Raw_ESG!$B$2:$B$76="2020"),0)+1),""))/(IFERROR(INDEX(Raw_Financials!$E$2:$E$76, MATCH(1, (Raw_Financials!$A$2:$A$76="Deepak Nitrite")*(Raw_Financials!$B$2:$B$76="2020"),0)+1),"")))} -> 0.1187935 | M7: {=IF(OR(IFERROR(INDEX(Raw_ESG!$E$2:$E$76, MATCH(1, (Raw_ESG!$A$2:$A$76="Deepak Nitrite")*(Raw_ESG!$B$2:$B$76="2020"),0)+1),"")="",IFERROR(INDEX(Raw_ESG!$F$2:$F$76, MATCH(1, (Raw_ESG!$A$2:$A$76="Deepak Nitrite")*(Raw_ESG!$B$2:$B$76="2020"),0)+1),"")=""),"",(IFERROR(INDEX(Raw_ESG!$E$2:$E$76, MATCH(1, (Raw_ESG!$A$2:$A$76="Deepak Nitrite")*(Raw_ESG!$B$2:$B$76="2020"),0)+1),""))+(IFERROR(INDEX(Raw_ESG!$F$2:$F$76, MATCH(1, (Raw_ESG!$A$2:$A$76="Deepak Nitrite")*(Raw_ESG!$B$2:$B$76="2020"),0)+1),"")))} -> 167345.4 | N7: {=IFERROR(INDEX(Raw_ESG!$G$2:$G$76, MATCH(1, (Raw_ESG!$A$2:$A$76="Deepak Nitrite")*(Raw_ESG!$B$2:$B$76="2020"),0)+1),"")} -> 65.82
A8: Deepak Nitrite | B8: 2021 | C8: {=IF(OR(IFERROR(INDEX(Raw_Financials!$E$2:$E$76, MATCH(1, (Raw_Financials!$A$2:$A$76="Deepak Nitrite")*(Raw_Financials!$B$2:$B$76="2021"),0)+1),"")="",IFERROR(INDEX(Raw_Financials!$D$2:$D$76, MATCH(1, (Raw_Financials!$A$2:$A$76="Deepak Nitrite")*(Raw_Financials!$B$2:$B$76="2021"),0)+1),"")=""),"",(IFERROR(INDEX(Raw_Financials!$D$2:$D$76, MATCH(1, (Raw_Financials!$A$2:$A$76="Deepak Nitrite")*(Raw_Financials!$B$2:$B$76="2021"),0)+1),""))/(IFERROR(INDEX(Raw_Financials!$E$2:$E$76, MATCH(1, (Raw_Financials!$A$2:$A$76="Deepak Nitrite")*(Raw_Financials!$B$2:$B$76="2021"),0)+1),"")))} -> 0.038671251 | D8: {=IF(OR(IFERROR(INDEX(Raw_Financials!$E$2:$E$76, MATCH(1, (Raw_Financials!$A$2:$A$76="Deepak Nitrite")*(Raw_Financials!$B$2:$B$76="2021"),0)+1),"")="",IFERROR(INDEX(Raw_Financials!$C$2:$C$76, MATCH(1, (Raw_Financials!$A$2:$A$76="Deepak Nitrite")*(Raw_Financials!$B$2:$B$76="2021"),0)+1),"")=""),"",(IFERROR(INDEX(Raw_Financials!$C$2:$C$76, MATCH(1, (Raw_Financials!$A$2:$A$76="Deepak Nitrite")*(Raw_Financials!$B$2:$B$76="2021"),0)+1),""))/(IFERROR(INDEX(Raw_Financials!$E$2:$E$76, MATCH(1, (Raw_Financials!$A$2:$A$76="Deepak Nitrite")*(Raw_Financials!$B$2:$B$76="2021"),0)+1),"")))} -> 0.19892783 | E8: {=IF(OR(IFERROR(INDEX(Raw_Financials!$G$2:$G$76, MATCH(1, (Raw_Financials!$A$2:$A$76="Deepak Nitrite")*(Raw_Financials!$B$2:$B$76="2021"),0)+1),"")="",IFERROR(INDEX(Raw_Financials!$H$2:$H$76, MATCH(1, (Raw_Financials!$A$2:$A$76="Deepak Nitrite")*(Raw_Financials!$B$2:$B$76="2021"),0)+1),"")=""),"",(IFERROR(INDEX(Raw_Financials!$G$2:$G$76, MATCH(1, (Raw_Financials!$A$2:$A$76="Deepak Nitrite")*(Raw_Financials!$B$2:$B$76="2021"),0)+1),""))-(IFERROR(INDEX(Raw_Financials!$H$2:$H$76, MATCH(1, (Raw_Financials!$A$2:$A$76="Deepak Nitrite")*(Raw_Financials!$B$2:$B$76="2021"),0)+1),"")))} -> -613.34 | F8: {=IF(OR(IFERROR(INDEX(Raw_Financials!$C$2:$C$76, MATCH(1, (Raw_Financials!$A$2:$A$76="Deepak Nitrite")*(Raw_Financials!$B$2:$B$76="2021"),0)+1),"")="",IF(OR(IFERROR(INDEX(Raw_Financials!$G$2:$G$76, MATCH(1, (Raw_Financials!$A$2:$A$76="Deepak Nitrite")*(Raw_Financials!$B$2:$B$76="2021"),0)+1),"")="",IFERROR(INDEX(Raw_Financials!$H$2:$H$76, MATCH(1, (Raw_Financials!$A$2:$A$76="Deepak Nitrite")*(Raw_Financials!$B$2:$B$76="2021"),0)+1),"")=""),"",(IFERROR(INDEX(Raw_Financials!$G$2:$G$76, MATCH(1, (Raw_Financials!$A$2:$A$76="Deepak Nitrite")*(Raw_Financials!$B$2:$B$76="2021"),0)+1),""))-(IFERROR(INDEX(Raw_Financials!$H$2:$H$76, MATCH(1, (Raw_Financials!$A$2:$A$76="Deepak Nitrite")*(Raw_Financials!$B$2:$B$76="2021"),0)+1),"")))=""),"",(IFERROR(INDEX(Raw_Financials!$C$2:$C$76, MATCH(1, (Raw_Financials!$A$2:$A$76="Deepak Nitrite")*(Raw_Financials!$B$2:$B$76="2021"),0)+1),""))/(IF(OR(IFERROR(INDEX(Raw_Financials!$G$2:$G$76, MATCH(1, (Raw_Financials!$A$2:$A$76="Deepak Nitrite")*(Raw_Financials!$B$2:$B$76="2021"),0)+1),"")="",IFERROR(INDEX(Raw_Financials!$H$2:$H$76, MATCH(1, (Raw_Financials!$A$2:$A$76="Deepak Nitrite")*(Raw_Financials!$B$2:$B$76="2021"),0)+1),"")=""),"",(IFERROR(INDEX(Raw_Financials!$G$2:$G$76, MATCH(1, (Raw_Financials!$A$2:$A$76="Deepak Nitrite")*(Raw_Financials!$B$2:$B$76="2021"),0)+1),""))-(IFERROR(INDEX(Raw_Financials!$H$2:$H$76, MATCH(1, (Raw_Financials!$A$2:$A$76="Deepak Nitrite")*(Raw_Financials!$B$2:$B$76="2021"),0)+1),"")))))} -> -61.082939 | G8: {=IF(OR(IFERROR(INDEX(Raw_Financials!$O$2:$O$76, MATCH(1, (Raw_Financials!$A$2:$A$76="Deepak Nitrite")*(Raw_Financials!$B$2:$B$76="2021"),0)+1),"")="",IFERROR(INDEX(Raw_Financials!$M$2:$M$76, MATCH(1, (Raw_Financials!$A$2:$A$76="Deepak Nitrite")*(Raw_Financials!$B$2:$B$76="2021"),0)+1),"")=""),"",(IFERROR(INDEX(Raw_Financials!$O$2:$O$76, MATCH(1, (Raw_Financials!$A$2:$A$76="Deepak Nitrite")*(Raw_Financials!$B$2:$B$76="2021"),0)+1),""))/(IFERROR(INDEX(Raw_Financials!$M$2:$M$76, MATCH(1, (Raw_Financials!$A$2:$A$76="Deepak Nitrite")*(Raw_Financials!$B$2:$B$76="2021"),0)+1),"")))} -> 1.2515308 | H8: {=IF(OR(IFERROR(INDEX(Raw_Financials!$M$2:$M$76, MATCH(1, (Raw_Financials!$A$2:$A$76="Deepak Nitrite")*(Raw_Financials!$B$2:$B$76="2021"),0)+1),"")="",IFERROR(INDEX(Raw_Financials!$L$2:$L$76, MATCH(1, (Raw_Financials!$A$2:$A$76="Deepak Nitrite")*(Raw_Financials!$B$2:$B$76="2021"),0)+1),"")=""),"",(IFERROR(INDEX(Raw_Financials!$M$2:$M$76, MATCH(1, (Raw_Financials!$A$2:$A$76="Deepak Nitrite")*(Raw_Financials!$B$2:$B$76="2021"),0)+1),""))/(IFERROR(INDEX(Raw_Financials!$L$2:$L$76, MATCH(1, (Raw_Financials!$A$2:$A$76="Deepak Nitrite")*(Raw_Financials!$B$2:$B$76="2021"),0)+1),"")))} -> 4.840147 | I8: {=IF(OR(IFERROR(INDEX(Raw_Financials!$N$2:$N$76, MATCH(1, (Raw_Financials!$A$2:$A$76="Deepak Nitrite")*(Raw_Financials!$B$2:$B$76="2021"),0)+1),"")="",IFERROR(INDEX(Raw_Financials!$J$2:$J$76, MATCH(1, (Raw_Financials!$A$2:$A$76="Deepak Nitrite")*(Raw_Financials!$B$2:$B$76="2021"),0)+1),"")=""),"",(IFERROR(INDEX(Raw_Financials!$N$2:$N$76, MATCH(1, (Raw_Financials!$A$2:$A$76="Deepak Nitrite")*(Raw_Financials!$B$2:$B$76="2021"),0)+1),""))-(IFERROR(INDEX(Raw_Financials!$J$2:$J$76, MATCH(1, (Raw_Financials!$A$2:$A$76="Deepak Nitrite")*(Raw_Financials!$B$2:$B$76="2021"),0)+1),"")))} -> 18294.82 | J8: {=IF(OR(IFERROR(INDEX(Raw_Financials!$M$2:$M$76, MATCH(1, (Raw_Financials!$A$2:$A$76="Deepak Nitrite")*(Raw_Financials!$B$2:$B$76="2021"),0)+1),"")="",IFERROR(INDEX(Raw_Financials!$C$2:$C$76, MATCH(1, (Raw_Financials!$A$2:$A$76="Deepak Nitrite")*(Raw_Financials!$B$2:$B$76="2021"),0)+1),"")=""),"",(IFERROR(INDEX(Raw_Financials!$M$2:$M$76, MATCH(1, (Raw_Financials!$A$2:$A$76="Deepak Nitrite")*(Raw_Financials!$B$2:$B$76="2021"),0)+1),""))/(IFERROR(INDEX(Raw_Financials!$C$2:$C$76, MATCH(1, (Raw_Financials!$A$2:$A$76="Deepak Nitrite")*(Raw_Financials!$B$2:$B$76="2021"),0)+1),"")))} -> 0.73213654 | K8: {=IF(OR(IFERROR(INDEX(Raw_ESG!$C$2:$C$76, MATCH(1, (Raw_ESG!$A$2:$A$76="Deepak Nitrite")*(Raw_ESG!$B$2:$B$76="2021"),0)+1),"")="",IFERROR(INDEX(Raw_Financials!$J$2:$J$76, MATCH(1, (Raw_Financials!$A$2:$A$76="Deepak Nitrite")*(Raw_Financials!$B$2:$B$76="2021"),0)+1),"")=""),"",(IFERROR(INDEX(Raw_ESG!$C$2:$C$76, MATCH(1, (Raw_ESG!$A$2:$A$76="Deepak Nitrite")*(Raw_ESG!$B$2:$B$76="2021"),0)+1),""))/(IFERROR(INDEX(Raw_Financials!$J$2:$J$76, MATCH(1, (Raw_Financials!$A$2:$A$76="Deepak Nitrite")*(Raw_Financials!$B$2:$B$76="2021"),0)+1),"")))} -> 0.47778482 | L8: {=IF(OR(IFERROR(INDEX(Raw_ESG!$D$2:$D$76, MATCH(1, (Raw_ESG!$A$2:$A$76="Deepak Nitrite")*(Raw_ESG!$B$2:$B$76="2021"),0)+1),"")="",IFERROR(INDEX(Raw_Financials!$E$2:$E$76, MATCH(1, (Raw_Financials!$A$2:$A$76="Deepak Nitrite")*(Raw_Financials!$B$2:$B$76="2021"),0)+1),"")=""),"",(IFERROR(INDEX(Raw_ESG!$D$2:$D$76, MATCH(1, (Raw_ESG!$A$2:$A$76="Deepak Nitrite")*(Raw_ESG!$B$2:$B$76="2021"),0)+1),""))/(IFERROR(INDEX(Raw_Financials!$E$2:$E$76, MATCH(1, (Raw_Financials!$A$2:$A$76="Deepak Nitrite")*(Raw_Financials!$B$2:$B$76="2021"),0)+1),"")))} -> 0.088237267 | M8: {=IF(OR(IFERROR(INDEX(Raw_ESG!$E$2:$E$76, MATCH(1, (Raw_ESG!$A$2:$A$76="Deepak Nitrite")*(Raw_ESG!$B$2:$B$76="2021"),0)+1),"")="",IFERROR(INDEX(Raw_ESG!$F$2:$F$76, MATCH(1, (Raw_ESG!$A$2:$A$76="Deepak Nitrite")*(Raw_ESG!$B$2:$B$76="2021"),0)+1),"")=""),"",(IFERROR(INDEX(Raw_ESG!$E$2:$E$76, MATCH(1, (Raw_ESG!$A$2:$A$76="Deepak Nitrite")*(Raw_ESG!$B$2:$B$76="2021"),0)+1),""))+(IFERROR(INDEX(Raw_ESG!$F$2:$F$76, MATCH(1, (Raw_ESG!$A$2:$A$76="Deepak Nitrite")*(Raw_ESG!$B$2:$B$76="2021"),0)+1),"")))} -> 180007.15 | N8: {=IFERROR(INDEX(Raw_ESG!$G$2:$G$76, MATCH(1, (Raw_ESG!$A$2:$A$76="Deepak Nitrite")*(Raw_ESG!$B$2:$B$76="2021"),0)+1),"")} -> 56.15
A9: Deepak Nitrite | B9: 2022 | C9: {=IF(OR(IFERROR(INDEX(Raw_Financials!$E$2:$E$76, MATCH(1, (Raw_Financials!$A$2:$A$76="Deepak Nitrite")*(Raw_Financials!$B$2:$B$76="2022"),0)+1),"")="",IFERROR(INDEX(Raw_Financials!$D$2:$D$76, MATCH(1, (Raw_Financials!$A$2:$A$76="Deepak Nitrite")*(Raw_Financials!$B$2:$B$76="2022"),0)+1),"")=""),"",(IFERROR(INDEX(Raw_Financials!$D$2:$D$76, MATCH(1, (Raw_Financials!$A$2:$A$76="Deepak Nitrite")*(Raw_Financials!$B$2:$B$76="2022"),0)+1),""))/(IFERROR(INDEX(Raw_Financials!$E$2:$E$76, MATCH(1, (Raw_Financials!$A$2:$A$76="Deepak Nitrite")*(Raw_Financials!$B$2:$B$76="2022"),0)+1),"")))} -> 0.091024309 | D9: {=IF(OR(IFERROR(INDEX(Raw_Financials!$E$2:$E$76, MATCH(1, (Raw_Financials!$A$2:$A$76="Deepak Nitrite")*(Raw_Financials!$B$2:$B$76="2022"),0)+1),"")="",IFERROR(INDEX(Raw_Financials!$C$2:$C$76, MATCH(1, (Raw_Financials!$A$2:$A$76="Deepak Nitrite")*(Raw_Financials!$B$2:$B$76="2022"),0)+1),"")=""),"",(IFERROR(INDEX(Raw_Financials!$C$2:$C$76, MATCH(1, (Raw_Financials!$A$2:$A$76="Deepak Nitrite")*(Raw_Financials!$B$2:$B$76="2022"),0)+1),""))/(IFERROR(INDEX(Raw_Financials!$E$2:$E$76, MATCH(1, (Raw_Financials!$A$2:$A$76="Deepak Nitrite")*(Raw_Financials!$B$2:$B$76="2022"),0)+1),"")))} -> 0.53277696 | E9: {=IF(OR(IFERROR(INDEX(Raw_Financials!$G$2:$G$76, MATCH(1, (Raw_Financials!$A$2:$A$76="Deepak Nitrite")*(Raw_Financials!$B$2:$B$76="2022"),0)+1),"")="",IFERROR(INDEX(Raw_Financials!$H$2:$H$76, MATCH(1, (Raw_Financials!$A$2:$A$76="Deepak Nitrite")*(Raw_Financials!$B$2:$B$76="2022"),0)+1),"")=""),"",(IFERROR(INDEX(Raw_Financials!$G$2:$G$76, MATCH(1, (Raw_Financials!$A$2:$A$76="Deepak Nitrite")*(Raw_Financials!$B$2:$B$76="2022"),0)+1),""))-(IFERROR(INDEX(Raw_Financials!$H$2:$H$76, MATCH(1, (Raw_Financials!$A$2:$A$76="Deepak Nitrite")*(Raw_Financials!$B$2:$B$76="2022"),0)+1),"")))} -> 1304.18 | F9: {=IF(OR(IFERROR(INDEX(Raw_Financials!$C$2:$C$76, MATCH(1, (Raw_Financials!$A$2:$A$76="Deepak Nitrite")*(Raw_Financials!$B$2:$B$76="2022"),0)+1),"")="",IF(OR(IFERROR(INDEX(Raw_Financials!$G$2:$G$76, MATCH(1, (Raw_Financials!$A$2:$A$76="Deepak Nitrite")*(Raw_Financials!$B$2:$B$76="2022"),0)+1),"")="",IFERROR(INDEX(Raw_Financials!$H$2:$H$76, MATCH(1, (Raw_Financials!$A$2:$A$76="Deepak Nitrite")*(Raw_Financials!$B$2:$B$76="2022"),0)+1),"")=""),"",(IFERROR(INDEX(Raw_Financials!$G$2:$G$76, MATCH(1, (Raw_Financials!$A$2:$A$76="Deepak Nitrite")*(Raw_Financials!$B$2:$B$76="2022"),0)+1),""))-(IFERROR(INDEX(Raw_Financials!$H$2:$H$76, MATCH(1, (Raw_Financials!$A$2:$A$76="Deepak Nitrite")*(Raw_Financials!$B$2:$B$76="2022"),0)+1),"")))=""),"",(IFERROR(INDEX(Raw_Financials!$C$2:$C$76, MATCH(1, (Raw_Financials!$A$2:$A$76="Deepak Nitrite")*(Raw_Financials!$B$2:$B$76="2022"),0)+1),""))/(IF(OR(IFERROR(INDEX(Raw_Financials!$G$2:$G$76, MATCH(1, (Raw_Financials!$A$2:$A$76="Deepak Nitrite")*(Raw_Financials!$B$2:$B$76="2022"),0)+1),"")="",IFERROR(INDEX(Raw_Financials!$H$2:$H$76, MATCH(1, (Raw_Financials!$A$2:$A$76="Deepak Nitrite")*(Raw_Financials!$B$2:$B$76="2022"),0)+1),"")=""),"",(IFERROR(INDEX(Raw_Financials!$G$2:$G$76, MATCH(1, (Raw_Financials!$A$2:$A$76="Deepak Nitrite")*(Raw_Financials!$B$2:$B$76="2022"),0)+1),""))-(IFERROR(INDEX(Raw_Financials!$H$2:$H$76, MATCH(1, (Raw_Financials!$A$2:$A$76="Deepak Nitrite")*(Raw_Financials!$B$2:$B$76="2022"),0)+1),"")))))} -> 50.12499 | G9: {=IF(OR(IFERROR(INDEX(Raw_Financials!$O$2:$O$76, MATCH(1, (Raw_Financials!$A$2:$A$76="Deepak Nitrite")*(Raw_Financials!$B$2:$B$76="2022"),0)+1),"")="",IFERROR(INDEX(Raw_Financials!$M$2:$M$76, MATCH(1, (Raw_Financials!$A$2:$A$76="Deepak Nitrite")*(Raw_Financials!$B$2:$B$76="2022"),0)+1),"")=""),"",(IFERROR(INDEX(Raw_Financials!$O$2:$O$76, MATCH(1, (Raw_Financials!$A$2:$A$76="Deepak Nitrite")*(Raw_Financials!$B$2:$B$76="2022"),0)+1),""))/(IFERROR(INDEX(Raw_Financials!$M$2:$M$76, MATCH(1, (Raw_Financials!$A$2:$A$76="Deepak Nitrite")*(Raw_Financials!$B$2:$B$76="2022"),0)+1),"")))} -> 1.6891704 | H9: {=IF(OR(IFERROR(INDEX(Raw_Financials!$M$2:$M$76, MATCH(1, (Raw_Financials!$A$2:$A$76="Deepak Nitrite")*(Raw_Financials!$B$2:$B$76="2022"),0)+1),"")="",IFERROR(INDEX(Raw_Financials!$L$2:$L$76, MATCH(1, (Raw_Financials!$A$2:$A$76="Deepak Nitrite")*(Raw_Financials!$B$2:$B$76="2022"),0)+1),"")=""),"",(IFERROR(INDEX(Raw_Financials!$M$2:$M$76, MATCH(1, (Raw_Financials!$A$2:$A$76="Deepak Nitrite")*(Raw_Financials!$B$2:$B$76="2022"),0)+1),""))/(IFERROR(INDEX(Raw_Financials!$L$2:$L$76, MATCH(1, (Raw_Financials!$A$2:$A$76="Deepak Nitrite")*(Raw_Financials!$B$2:$B$76="2022"),0)+1),"")))} -> 3.6306221 | I9: {=IF(OR(IFERROR(INDEX(Raw_Financials!$N$2:$N$76, MATCH(1, (Raw_Financials!$A$2:$A$76="Deepak Nitrite")*(Raw_Financials!$B$2:$B$76="2022"),0)+1),"")="",IFERROR(INDEX(Raw_Financials!$J$2:$J$76, MATCH(1, (Raw_Financials!$A$2:$A$76="Deepak Nitrite")*(Raw_Financials!$B$2:$B$76="2022"),0)+1),"")=""),"",(IFERROR(INDEX(Raw_Financials!$N$2:$N$76, MATCH(1, (Raw_Financials!$A$2:$A$76="Deepak Nitrite")*(Raw_Financials!$B$2:$B$76="2022"),0)+1),""))-(IFERROR(INDEX(Raw_Financials!$J$2:$J$76, MATCH(1, (Raw_Financials!$A$2:$A$76="Deepak Nitrite")*(Raw_Financials!$B$2:$B$76="2022"),0)+1),"")))} -> 4445.39 | J9: {=IF(OR(IFERROR(INDEX(Raw_Financials!$M$2:$M$76, MATCH(1, (Raw_Financials!$A$2:$A$76="Deepak Nitrite")*(Raw_Financials!$B$2:$B$76="2022"),0)+1),"")="",IFERROR(INDEX(Raw_Financials!$C$2:$C$76, MATCH(1, (Raw_Financials!$A$2:$A$76="Deepak Nitrite")*(Raw_Financials!$B$2:$B$76="2022"),0)+1),"")=""),"",(IFERROR(INDEX(Raw_Financials!$M$2:$M$76, MATCH(1, (Raw_Financials!$A$2:$A$76="Deepak Nitrite")*(Raw_Financials!$B$2:$B$76="2022"),0)+1),""))/(IFERROR(INDEX(Raw_Financials!$C$2:$C$76, MATCH(1, (Raw_Financials!$A$2:$A$76="Deepak Nitrite")*(Raw_Financials!$B$2:$B$76="2022"),0)+1),"")))} -> 0.28067395 | K9: {=IF(OR(IFERROR(INDEX(Raw_ESG!$C$2:$C$76, MATCH(1, (Raw_ESG!$A$2:$A$76="Deepak Nitrite")*(Raw_ESG!$B$2:$B$76="2022"),0)+1),"")="",IFERROR(INDEX(Raw_Financials!$J$2:$J$76, MATCH(1, (Raw_Financials!$A$2:$A$76="Deepak Nitrite")*(Raw_Financials!$B$2:$B$76="2022"),0)+1),"")=""),"",(IFERROR(INDEX(Raw_ESG!$C$2:$C$76, MATCH(1, (Raw_ESG!$A$2:$A$76="Deepak Nitrite")*(Raw_ESG!$B$2:$B$76="2022"),0)+1),""))/(IFERROR(INDEX(Raw_Financials!$J$2:$J$76, MATCH(1, (Raw_Financials!$A$2:$A$76="Deepak Nitrite")*(Raw_Financials!$B$2:$B$76="2022"),0)+1),"")))} -> 0.40460458 | L9: {=IF(OR(IFERROR(INDEX(Raw_ESG!$D$2:$D$76, MATCH(1, (Raw_ESG!$A$2:$A$76="Deepak Nitrite")*(Raw_ESG!$B$2:$B$76="2022"),0)+1),"")="",IFERROR(INDEX(Raw_Financials!$E$2:$E$76, MATCH(1, (Raw_Financials!$A$2:$A$76="Deepak Nitrite")*(Raw_Financials!$B$2:$B$76="2022"),0)+1),"")=""),"",(IFERROR(INDEX(Raw_ESG!$D$2:$D$76, MATCH(1, (Raw_ESG!$A$2:$A$76="Deepak Nitrite")*(Raw_ESG!$B$2:$B$76="2022"),0)+1),""))/(IFERROR(INDEX(Raw_Financials!$E$2:$E$76, MATCH(1, (Raw_Financials!$A$2:$A$76="Deepak Nitrite")*(Raw_Financials!$B$2:$B$76="2022"),0)+1),"")))} -> 0.091859187 | M9: {=IF(OR(IFERROR(INDEX(Raw_ESG!$E$2:$E$76, MATCH(1, (Raw_ESG!$A$2:$A$76="Deepak Nitrite")*(Raw_ESG!$B$2:$B$76="2022"),0)+1),"")="",IFERROR(INDEX(Raw_ESG!$F$2:$F$76, MATCH(1, (Raw_ESG!$A$2:$A$76="Deepak Nitrite")*(Raw_ESG!$B$2:$B$76="2022"),0)+1),"")=""),"",(IFERROR(INDEX(Raw_ESG!$E$2:$E$76, MATCH(1, (Raw_ESG!$A$2:$A$76="Deepak Nitrite")*(Raw_ESG!$B$2:$B$76="2022"),0)+1),""))+(IFERROR(INDEX(Raw_ESG!$F$2:$F$76, MATCH(1, (Raw_ESG!$A$2:$A$76="Deepak Nitrite")*(Raw_ESG!$B$2:$B$76="2022"),0)+1),"")))} -> 123389.63 | N9: {=IFERROR(INDEX(Raw_ESG!$G$2:$G$76, MATCH(1, (Raw_ESG!$A$2:$A$76="Deepak Nitrite")*(Raw_ESG!$B$2:$B$76="2022"),0)+1),"")} -> 79.76
A10: Deepak Nitrite | B10: 2023 | C10: {=IF(OR(IFERROR(INDEX(Raw_Financials!$E$2:$E$76, MATCH(1, (Raw_Financials!$A$2:$A$76="Deepak Nitrite")*(Raw_Financials!$B$2:$B$76="2023"),0)+1),"")="",IFERROR(INDEX(Raw_Financials!$D$2:$D$76, MATCH(1, (Raw_Financials!$A$2:$A$76="Deepak Nitrite")*(Raw_Financials!$B$2:$B$76="2023"),0)+1),"")=""),"",(IFERROR(INDEX(Raw_Financials!$D$2:$D$76, MATCH(1, (Raw_Financials!$A$2:$A$76="Deepak Nitrite")*(Raw_Financials!$B$2:$B$76="2023"),0)+1),""))/(IFERROR(INDEX(Raw_Financials!$E$2:$E$76, MATCH(1, (Raw_Financials!$A$2:$A$76="Deepak Nitrite")*(Raw_Financials!$B$2:$B$76="2023"),0)+1),"")))} -> 0.045165928 | D10: {=IF(OR(IFERROR(INDEX(Raw_Financials!$E$2:$E$76, MATCH(1, (Raw_Financials!$A$2:$A$76="Deepak Nitrite")*(Raw_Financials!$B$2:$B$76="2023"),0)+1),"")="",IFERROR(INDEX(Raw_Financials!$C$2:$C$76, MATCH(1, (Raw_Financials!$A$2:$A$76="Deepak Nitrite")*(Raw_Financials!$B$2:$B$76="2023"),0)+1),"")=""),"",(IFERROR(INDEX(Raw_Financials!$C$2:$C$76, MATCH(1, (Raw_Financials!$A$2:$A$76="Deepak Nitrite")*(Raw_Financials!$B$2:$B$76="2023"),0)+1),""))/(IFERROR(INDEX(Raw_Financials!$E$2:$E$76, MATCH(1, (Raw_Financials!$A$2:$A$76="Deepak Nitrite")*(Raw_Financials!$B$2:$B$76="2023"),0)+1),"")))} -> 0.22809367 | E10: {=IF(OR(IFERROR(INDEX(Raw_Financials!$G$2:$G$76, MATCH(1, (Raw_Financials!$A$2:$A$76="Deepak Nitrite")*(Raw_Financials!$B$2:$B$76="2023"),0)+1),"")="",IFERROR(INDEX(Raw_Financials!$H$2:$H$76, MATCH(1, (Raw_Financials!$A$2:$A$76="Deepak Nitrite")*(Raw_Financials!$B$2:$B$76="2023"),0)+1),"")=""),"",(IFERROR(INDEX(Raw_Financials!$G$2:$G$76, MATCH(1, (Raw_Financials!$A$2:$A$76="Deepak Nitrite")*(Raw_Financials!$B$2:$B$76="2023"),0)+1),""))-(IFERROR(INDEX(Raw_Financials!$H$2:$H$76, MATCH(1, (Raw_Financials!$A$2:$A$76="Deepak Nitrite")*(Raw_Financials!$B$2:$B$76="2023"),0)+1),"")))} -> 14997.86 | F10: {=IF(OR(IFERROR(INDEX(Raw_Financials!$C$2:$C$76, MATCH(1, (Raw_Financials!$A$2:$A$76="Deepak Nitrite")*(Raw_Financials!$B$2:$B$76="2023"),0)+1),"")="",IF(OR(IFERROR(INDEX(Raw_Financials!$G$2:$G$76, MATCH(1, (Raw_Financials!$A$2:$A$76="Deepak Nitrite")*(Raw_Financials!$B$2:$B$76="2023"),0)+1),"")="",IFERROR(INDEX(Raw_Financials!$H$2:$H$76, MATCH(1, (Raw_Financials!$A$2:$A$76="Deepak Nitrite")*(Raw_Financials!$B$2:$B$76="2023"),0)+1),"")=""),"",(IFERROR(INDEX(Raw_Financials!$G$2:$G$76, MATCH(1, (Raw_Financials!$A$2:$A$76="Deepak Nitrite")*(Raw_Financials!$B$2:$B$76="2023"),0)+1),""))-(IFERROR(INDEX(Raw_Financials!$H$2:$H$76, MATCH(1, (Raw_Financials!$A$2:$A$76="Deepak Nitrite")*(Raw_Financials!$B$2:$B$76="2023"),0)+1),"")))=""),"",(IFERROR(INDEX(Raw_Financials!$C$2:$C$76, MATCH(1, (Raw_Financials!$A$2:$A$76="Deepak Nitrite")*(Raw_Financials!$B$2:$B$76="2023"),0)+1),""))/(IF(OR(IFERROR(INDEX(Raw_Financials!$G$2:$G$76, MATCH(1, (Raw_Financials!$A$2:$A$76="Deepak Nitrite")*(Raw_Financials!$B$2:$B$76="2023"),0)+1),"")="",IFERROR(INDEX(Raw_Financials!$H$2:$H$76, MATCH(1, (Raw_Financials!$A$2:$A$76="Deepak Nitrite")*(Raw_Financials!$B$2:$B$76="2023"),0)+1),"")=""),"",(IFERROR(INDEX(Raw_Financials!$G$2:$G$76, MATCH(1, (Raw_Financials!$A$2:$A$76="Deepak Nitrite")*(Raw_Financials!$B$2:$B$76="2023"),0)+1),""))-(IFERROR(INDEX(Raw_Financials!$H$2:$H$76, MATCH(1, (Raw_Financials!$A$2:$A$76="Deepak Nitrite")*(Raw_Financials!$B$2:$B$76="2023"),0)+1),"")))))} -> 2.7444015 | G10: {=IF(OR(IFERROR(INDEX(Raw_Financials!$O$2:$O$76, MATCH(1, (Raw_Financials!$A$2:$A$76="Deepak Nitrite")*(Raw_Financials!$B$2:$B$76="2023"),0)+1),"")="",IFERROR(INDEX(Raw_Financials!$M$2:$M$76, MATCH(1, (Raw_Financials!$A$2:$A$76="Deepak Nitrite")*(Raw_Financials!$B$2:$B$76="2023"),0)+1),"")=""),"",(IFERROR(INDEX(Raw_Financials!$O$2:$O$76, MATCH(1, (Raw_Financials!$A$2:$A$76="Deepak Nitrite")*(Raw_Financials!$B$2:$B$76="2023"),0)+1),""))/(IFERROR(INDEX(Raw_Financials!$M$2:$M$76, MATCH(1, (Raw_Financials!$A$2:$A$76="Deepak Nitrite")*(Raw_Financials!$B$2:$B$76="2023"),0)+1),"")))} -> 4.668948 | H10: {=IF(OR(IFERROR(INDEX(Raw_Financials!$M$2:$M$76, MATCH(1, (Raw_Financials!$A$2:$A$76="Deepak Nitrite")*(Raw_Financials!$B$2:$B$76="2023"),0)+1),"")="",IFERROR(INDEX(Raw_Financials!$L$2:$L$76, MATCH(1, (Raw_Financials!$A$2:$A$76="Deepak Nitrite")*(Raw_Financials!$B$2:$B$76="2023"),0)+1),"")=""),"",(IFERROR(INDEX(Raw_Financials!$M$2:$M$76, MATCH(1, (Raw_Financials!$A$2:$A$76="Deepak Nitrite")*(Raw_Financials!$B$2:$B$76="2023"),0)+1),""))/(IFERROR(INDEX(Raw_Financials!$L$2:$L$76, MATCH(1, (Raw_Financials!$A$2:$A$76="Deepak Nitrite")*(Raw_Financials!$B$2:$B$76="2023"),0)+1),"")))} -> 2.7362877 | I10: {=IF(OR(IFERROR(INDEX(Raw_Financials!$N$2:$N$76, MATCH(1, (Raw_Financials!$A$2:$A$76="Deepak Nitrite")*(Raw_Financials!$B$2:$B$76="2023"),0)+1),"")="",IFERROR(INDEX(Raw_Financials!$J$2:$J$76, MATCH(1, (Raw_Financials!$A$2:$A$76="Deepak Nitrite")*(Raw_Financials!$B$2:$B$76="2023"),0)+1),"")=""),"",(IFERROR(INDEX(Raw_Financials!$N$2:$N$76, MATCH(1, (Raw_Financials!$A$2:$A$76="Deepak Nitrite")*(Raw_Financials!$B$2:$B$76="2023"),0)+1),""))-(IFERROR(INDEX(Raw_Financials!$J$2:$J$76, MATCH(1, (Raw_Financials!$A$2:$A$76="Deepak Nitrite")*(Raw_Financials!$B$2:$B$76="2023"),0)+1),"")))} -> 17766.62 | J10: {=IF(OR(IFERROR(INDEX(Raw_Financials!$M$2:$M$76, MATCH(1, (Raw_Financials!$A$2:$A$76="Deepak Nitrite")*(Raw_Financials!$B$2:$B$76="2023"),0)+1),"")="",IFERROR(INDEX(Raw_Financials!$C$2:$C$76, MATCH(1, (Raw_Financials!$A$2:$A$76="Deepak Nitrite")*(Raw_Financials!$B$2:$B$76="2023"),0)+1),"")=""),"",(IFERROR(INDEX(Raw_Financials!$M$2:$M$76, MATCH(1, (Raw_Financials!$A$2:$A$76="Deepak Nitrite")*(Raw_Financials!$B$2:$B$76="2023"),0)+1),""))/(IFERROR(INDEX(Raw_Financials!$C$2:$C$76, MATCH(1, (Raw_Financials!$A$2:$A$76="Deepak Nitrite")*(Raw_Financials!$B$2:$B$76="2023"),0)+1),"")))} -> 0.26087709 | K10: {=IF(OR(IFERROR(INDEX(Raw_ESG!$C$2:$C$76, MATCH(1, (Raw_ESG!$A$2:$A$76="Deepak Nitrite")*(Raw_ESG!$B$2:$B$76="2023"),0)+1),"")="",IFERROR(INDEX(Raw_Financials!$J$2:$J$76, MATCH(1, (Raw_Financials!$A$2:$A$76="Deepak Nitrite")*(Raw_Financials!$B$2:$B$76="2023"),0)+1),"")=""),"",(IFERROR(INDEX(Raw_ESG!$C$2:$C$76, MATCH(1, (Raw_ESG!$A$2:$A$76="Deepak Nitrite")*(Raw_ESG!$B$2:$B$76="2023"),0)+1),""))/(IFERROR(INDEX(Raw_Financials!$J$2:$J$76, MATCH(1, (Raw_Financials!$A$2:$A$76="Deepak Nitrite")*(Raw_Financials!$B$2:$B$76="2023"),0)+1),"")))} -> 0.60570229 | L10: {=IF(OR(IFERROR(INDEX(Raw_ESG!$D$2:$D$76, MATCH(1, (Raw_ESG!$A$2:$A$76="Deepak Nitrite")*(Raw_ESG!$B$2:$B$76="2023"),0)+1),"")="",IFERROR(INDEX(Raw_Financials!$E$2:$E$76, MATCH(1, (Raw_Financials!$A$2:$A$76="Deepak Nitrite")*(Raw_Financials!$B$2:$B$76="2023"),0)+1),"")=""),"",(IFERROR(INDEX(Raw_ESG!$D$2:$D$76, MATCH(1, (Raw_ESG!$A$2:$A$76="Deepak Nitrite")*(Raw_ESG!$B$2:$B$76="2023"),0)+1),""))/(IFERROR(INDEX(Raw_Financials!$E$2:$E$76, MATCH(1, (Raw_Financials!$A$2:$A$76="Deepak Nitrite")*(Raw_Financials!$B$2:$B$76="2023"),0)+1),"")))} -> 0.089883041 | M10: {=IF(OR(IFERROR(INDEX(Raw_ESG!$E$2:$E$76, MATCH(1, (Raw_ESG!$A$2:$A$76="Deepak Nitrite")*(Raw_ESG!$B$2:$B$76="2023"),0)+1),"")="",IFERROR(INDEX(Raw_ESG!$F$2:$F$76, MATCH(1, (Raw_ESG!$A$2:$A$76="Deepak Nitrite")*(Raw_ESG!$B$2:$B$76="2023"),0)+1),"")=""),"",(IFERROR(INDEX(Raw_ESG!$E$2:$E$76, MATCH(1, (Raw_ESG!$A$2:$A$76="Deepak Nitrite")*(Raw_ESG!$B$2:$B$76="2023"),0)+1),""))+(IFERROR(INDEX(Raw_ESG!$F$2:$F$76, MATCH(1, (Raw_ESG!$A$2:$A$76="Deepak Nitrite")*(Raw_ESG!$B$2:$B$76="2023"),0)+1),"")))} -> 157583.78 | N10: {=IFERROR(INDEX(Raw_ESG!$G$2:$G$76, MATCH(1, (Raw_ESG!$A$2:$A$76="Deepak Nitrite")*(Raw_ESG!$B$2:$B$76="2023"),0)+1),"")} -> 53.54
A11: Deepak Nitrite | B11: 2024 | C11: {=IF(OR(IFERROR(INDEX(Raw_Financials!$E$2:$E$76, MATCH(1, (Raw_Financials!$A$2:$A$76="Deepak Nitrite")*(Raw_Financials!$B$2:$B$76="2024"),0)+1),"")="",IFERROR(INDEX(Raw_Financials!$D$2:$D$76, MATCH(1, (Raw_Financials!$A$2:$A$76="Deepak Nitrite")*(Raw_Financials!$B$2:$B$76="2024"),0)+1),"")=""),"",(IFERROR(INDEX(Raw_Financials!$D$2:$D$76, MATCH(1, (Raw_Financials!$A$2:$A$76="Deepak Nitrite")*(Raw_Financials!$B$2:$B$76="2024"),0)+1),""))/(IFERROR(INDEX(Raw_Financials!$E$2:$E$76, MATCH(1, (Raw_Financials!$A$2:$A$76="Deepak Nitrite")*(Raw_Financials!$B$2:$B$76="2024"),0)+1),"")))} -> 0.061162424 | D11: {=IF(OR(IFERROR(INDEX(Raw_Financials!$E$2:$E$76, MATCH(1, (Raw_Financials!$A$2:$A$76="Deepak Nitrite")*(Raw_Financials!$B$2:$B$76="2024"),0)+1),"")="",IFERROR(INDEX(Raw_Financials!$C$2:$C$76, MATCH(1, (Raw_Financials!$A$2:$A$76="Deepak Nitrite")*(Raw_Financials!$B$2:$B$76="2024"),0)+1),"")=""),"",(IFERROR(INDEX(Raw_Financials!$C$2:$C$76, MATCH(1, (Raw_Financials!$A$2:$A$76="Deepak Nitrite")*(Raw_Financials!$B$2:$B$76="2024"),0)+1),""))/(IFERROR(INDEX(Raw_Financials!$E$2:$E$76, MATCH(1, (Raw_Financials!$A$2:$A$76="Deepak Nitrite")*(Raw_Financials!$B$2:$B$76="2024"),0)+1),"")))} -> 0.72790459 | E11: {=IF(OR(IFERROR(INDEX(Raw_Financials!$G$2:$G$76, MATCH(1, (Raw_Financials!$A$2:$A$76="Deepak Nitrite")*(Raw_Financials!$B$2:$B$76="2024"),0)+1),"")="",IFERROR(INDEX(Raw_Financials!$H$2:$H$76, MATCH(1, (Raw_Financials!$A$2:$A$76="Deepak Nitrite")*(Raw_Financials!$B$2:$B$76="2024"),0)+1),"")=""),"",(IFERROR(INDEX(Raw_Financials!$G$2:$G$76, MATCH(1, (Raw_Financials!$A$2:$A$76="Deepak Nitrite")*(Raw_Financials!$B$2:$B$76="2024"),0)+1),""))-(IFERROR(INDEX(Raw_Financials!$H$2:$H$76, MATCH(1, (Raw_Financials!$A$2:$A$76="Deepak Nitrite")*(Raw_Financials!$B$2:$B$76="2024"),0)+1),"")))} -> 37164.36 | F11: {=IF(OR(IFERROR(INDEX(Raw_Financials!$C$2:$C$76, MATCH(1, (Raw_Financials!$A$2:$A$76="Deepak Nitrite")*(Raw_Financials!$B$2:$B$76="2024"),0)+1),"")="",IF(OR(IFERROR(INDEX(Raw_Financials!$G$2:$G$76, MATCH(1, (Raw_Financials!$A$2:$A$76="Deepak Nitrite")*(Raw_Financials!$B$2:$B$76="2024"),0)+1),"")="",IFERROR(INDEX(Raw_Financials!$H$2:$H$76, MATCH(1, (Raw_Financials!$A$2:$A$76="Deepak Nitrite")*(Raw_Financials!$B$2:$B$76="2024"),0)+1),"")=""),"",(IFERROR(INDEX(Raw_Financials!$G$2:$G$76, MATCH(1, (Raw_Financials!$A$2:$A$76="Deepak Nitrite")*(Raw_Financials!$B$2:$B$76="2024"),0)+1),""))-(IFERROR(INDEX(Raw_Financials!$H$2:$H$76, MATCH(1, (Raw_Financials!$A$2:$A$76="Deepak Nitrite")*(Raw_Financials!$B$2:$B$76="2024"),0)+1),"")))=""),"",(IFERROR(INDEX(Raw_Financials!$C$2:$C$76, MATCH(1, (Raw_Financials!$A$2:$A$76="Deepak Nitrite")*(Raw_Financials!$B$2:$B$76="2024"),0)+1),""))/(IF(OR(IFERROR(INDEX(Raw_Financials!$G$2:$G$76, MATCH(1, (Raw_Financials!$A$2:$A$76="Deepak Nitrite")*(Raw_Financials!$B$2:$B$76="2024"),0)+1),"")="",IFERROR(INDEX(Raw_Financials!$H$2:$H$76, MATCH(1, (Raw_Financials!$A$2:$A$76="Deepak Nitrite")*(Raw_Financials!$B$2:$B$76="2024"),0)+1),"")=""),"",(IFERROR(INDEX(Raw_Financials!$G$2:$G$76, MATCH(1, (Raw_Financials!$A$2:$A$76="Deepak Nitrite")*(Raw_Financials!$B$2:$B$76="2024"),0)+1),""))-(IFERROR(INDEX(Raw_Financials!$H$2:$H$76, MATCH(1, (Raw_Financials!$A$2:$A$76="Deepak Nitrite")*(Raw_Financials!$B$2:$B$76="2024"),0)+1),"")))))} -> 1.8946456 | G11: {=IF(OR(IFERROR(INDEX(Raw_Financials!$O$2:$O$76, MATCH(1, (Raw_Financials!$A$2:$A$76="Deepak Nitrite")*(Raw_Financials!$B$2:$B$76="2024"),0)+1),"")="",IFERROR(INDEX(Raw_Financials!$M$2:$M$76, MATCH(1, (Raw_Financials!$A$2:$A$76="Deepak Nitrite")*(Raw_Financials!$B$2:$B$76="2024"),0)+1),"")=""),"",(IFERROR(INDEX(Raw_Financials!$O$2:$O$76, MATCH(1, (Raw_Financials!$A$2:$A$76="Deepak Nitrite")*(Raw_Financials!$B$2:$B$76="2024"),0)+1),""))/(IFERROR(INDEX(Raw_Financials!$M$2:$M$76, MATCH(1, (Raw_Financials!$A$2:$A$76="Deepak Nitrite")*(Raw_Financials!$B$2:$B$76="2024"),0)+1),"")))} -> 3.2655912 | H11: {=IF(OR(IFERROR(INDEX(Raw_Financials!$M$2:$M$76, MATCH(1, (Raw_Financials!$A$2:$A$76="Deepak Nitrite")*(Raw_Financials!$B$2:$B$76="2024"),0)+1),"")="",IFERROR(INDEX(Raw_Financials!$L$2:$L$76, MATCH(1, (Raw_Financials!$A$2:$A$76="Deepak Nitrite")*(Raw_Financials!$B$2:$B$76="2024"),0)+1),"")=""),"",(IFERROR(INDEX(Raw_Financials!$M$2:$M$76, MATCH(1, (Raw_Financials!$A$2:$A$76="Deepak Nitrite")*(Raw_Financials!$B$2:$B$76="2024"),0)+1),""))/(IFERROR(INDEX(Raw_Financials!$L$2:$L$76, MATCH(1, (Raw_Financials!$A$2:$A$76="Deepak Nitrite")*(Raw_Financials!$B$2:$B$76="2024"),0)+1),"")))} -> 2.8261576 | I11: {=IF(OR(IFERROR(INDEX(Raw_Financials!$N$2:$N$76, MATCH(1, (Raw_Financials!$A$2:$A$76="Deepak Nitrite")*(Raw_Financials!$B$2:$B$76="2024"),0)+1),"")="",IFERROR(INDEX(Raw_Financials!$J$2:$J$76, MATCH(1, (Raw_Financials!$A$2:$A$76="Deepak Nitrite")*(Raw_Financials!$B$2:$B$76="2024"),0)+1),"")=""),"",(IFERROR(INDEX(Raw_Financials!$N$2:$N$76, MATCH(1, (Raw_Financials!$A$2:$A$76="Deepak Nitrite")*(Raw_Financials!$B$2:$B$76="2024"),0)+1),""))-(IFERROR(INDEX(Raw_Financials!$J$2:$J$76, MATCH(1, (Raw_Financials!$A$2:$A$76="Deepak Nitrite")*(Raw_Financials!$B$2:$B$76="2024"),0)+1),"")))} -> 15691.45 | J11: {=IF(OR(IFERROR(INDEX(Raw_Financials!$M$2:$M$76, MATCH(1, (Raw_Financials!$A$2:$A$76="Deepak Nitrite")*(Raw_Financials!$B$2:$B$76="2024"),0)+1),"")="",IFERROR(INDEX(Raw_Financials!$C$2:$C$76, MATCH(1, (Raw_Financials!$A$2:$A$76="Deepak Nitrite")*(Raw_Financials!$B$2:$B$76="2024"),0)+1),"")=""),"",(IFERROR(INDEX(Raw_Financials!$M$2:$M$76, MATCH(1, (Raw_Financials!$A$2:$A$76="Deepak Nitrite")*(Raw_Financials!$B$2:$B$76="2024"),0)+1),""))/(IFERROR(INDEX(Raw_Financials!$C$2:$C$76, MATCH(1, (Raw_Financials!$A$2:$A$76="Deepak Nitrite")*(Raw_Financials!$B$2:$B$76="2024"),0)+1),"")))} -> 0.24648273 | K11: {=IF(OR(IFERROR(INDEX(Raw_ESG!$C$2:$C$76, MATCH(1, (Raw_ESG!$A$2:$A$76="Deepak Nitrite")*(Raw_ESG!$B$2:$B$76="2024"),0)+1),"")="",IFERROR(INDEX(Raw_Financials!$J$2:$J$76, MATCH(1, (Raw_Financials!$A$2:$A$76="Deepak Nitrite")*(Raw_Financials!$B$2:$B$76="2024"),0)+1),"")=""),"",(IFERROR(INDEX(Raw_ESG!$C$2:$C$76, MATCH(1, (Raw_ESG!$A$2:$A$76="Deepak Nitrite")*(Raw_ESG!$B$2:$B$76="2024"),0)+1),""))/(IFERROR(INDEX(Raw_Financials!$J$2:$J$76, MATCH(1, (Raw_Financials!$A$2:$A$76="Deepak Nitrite")*(Raw_Financials!$B$2:$B$76="2024"),0)+1),"")))} -> 0.20631569 | L11: {=IF(OR(IFERROR(INDEX(Raw_ESG!$D$2:$D$76, MATCH(1, (Raw_ESG!$A$2:$A$76="Deepak Nitrite")*(Raw_ESG!$B$2:$B$76="2024"),0)+1),"")="",IFERROR(INDEX(Raw_Financials!$E$2:$E$76, MATCH(1, (Raw_Financials!$A$2:$A$76="Deepak Nitrite")*(Raw_Financials!$B$2:$B$76="2024"),0)+1),"")=""),"",(IFERROR(INDEX(Raw_ESG!$D$2:$D$76, MATCH(1, (Raw_ESG!$A$2:$A$76="Deepak Nitrite")*(Raw_ESG!$B$2:$B$76="2024"),0)+1),""))/(IFERROR(INDEX(Raw_Financials!$E$2:$E$76, MATCH(1, (Raw_Financials!$A$2:$A$76="Deepak Nitrite")*(Raw_Financials!$B$2:$B$76="2024"),0)+1),"")))} -> 0.17060838 | M11: {=IF(OR(IFERROR(INDEX(Raw_ESG!$E$2:$E$76, MATCH(1, (Raw_ESG!$A$2:$A$76="Deepak Nitrite")*(Raw_ESG!$B$2:$B$76="2024"),0)+1),"")="",IFERROR(INDEX(Raw_ESG!$F$2:$F$76, MATCH(1, (Raw_ESG!$A$2:$A$76="Deepak Nitrite")*(Raw_ESG!$B$2:$B$76="2024"),0)+1),"")=""),"",(IFERROR(INDEX(Raw_ESG!$E$2:$E$76, MATCH(1, (Raw_ESG!$A$2:$A$76="Deepak Nitrite")*(Raw_ESG!$B$2:$B$76="2024"),0)+1),""))+(IFERROR(INDEX(Raw_ESG!$F$2:$F$76, MATCH(1, (Raw_ESG!$A$2:$A$76="Deepak Nitrite")*(Raw_ESG!$B$2:$B$76="2024"),0)+1),"")))} -> 147900.92 | N11: {=IFERROR(INDEX(Raw_ESG!$G$2:$G$76, MATCH(1, (Raw_ESG!$A$2:$A$76="Deepak Nitrite")*(Raw_ESG!$B$2:$B$76="2024"),0)+1),"")} -> 61.95
A12: Linde India | B12: 2020 | C12: {=IF(OR(IFERROR(INDEX(Raw_Financials!$E$2:$E$76, MATCH(1, (Raw_Financials!$A$2:$A$76="Linde India")*(Raw_Financials!$B$2:$B$76="2020"),0)+1),"")="",IFERROR(INDEX(Raw_Financials!$D$2:$D$76, MATCH(1, (Raw_Financials!$A$2:$A$76="Linde India")*(Raw_Financials!$B$2:$B$76="2020"),0)+1),"")=""),"",(IFERROR(INDEX(Raw_Financials!$D$2:$D$76, MATCH(1, (Raw_Financials!$A$2:$A$76="Linde India")*(Raw_Financials!$B$2:$B$76="2020"),0)+1),""))/(IFERROR(INDEX(Raw_Financials!$E$2:$E$76, MATCH(1, (Raw_Financials!$A$2:$A$76="Linde India")*(Raw_Financials!$B$2:$B$76="2020"),0)+1),"")))} -> 0.063763659 | D12: {=IF(OR(IFERROR(INDEX(Raw_Financials!$E$2:$E$76, MATCH(1, (Raw_Financials!$A$2:$A$76="Linde India")*(Raw_Financials!$B$2:$B$76="2020"),0)+1),"")="",IFERROR(INDEX(Raw_Financials!$C$2:$C$76, MATCH(1, (Raw_Financials!$A$2:$A$76="Linde India")*(Raw_Financials!$B$2:$B$76="2020"),0)+1),"")=""),"",(IFERROR(INDEX(Raw_Financials!$C$2:$C$76, MATCH(1, (Raw_Financials!$A$2:$A$76="Linde India")*(Raw_Financials!$B$2:$B$76="2020"),0)+1),""))/(IFERROR(INDEX(Raw_Financials!$E$2:$E$76, MATCH(1, (Raw_Financials!$A$2:$A$76="Linde India")*(Raw_Financials!$B$2:$B$76="2020"),0)+1),"")))} -> 0.64834491 | E12: {=IF(OR(IFERROR(INDEX(Raw_Financials!$G$2:$G$76, MATCH(1, (Raw_Financials!$A$2:$A$76="Linde India")*(Raw_Financials!$B$2:$B$76="2020"),0)+1),"")="",IFERROR(INDEX(Raw_Financials!$H$2:$H$76, MATCH(1, (Raw_Financials!$A$2:$A$76="Linde India")*(Raw_Financials!$B$2:$B$76="2020"),0)+1),"")=""),"",(IFERROR(INDEX(Raw_Financials!$G$2:$G$76, MATCH(1, (Raw_Financials!$A$2:$A$76="Linde India")*(Raw_Financials!$B$2:$B$76="2020"),0)+1),""))-(IFERROR(INDEX(Raw_Financials!$H$2:$H$76, MATCH(1, (Raw_Financials!$A$2:$A$76="Linde India")*(Raw_Financials!$B$2:$B$76="2020"),0)+1),"")))} -> 8308.79 | F12: {=IF(OR(IFERROR(INDEX(Raw_Financials!$C$2:$C$76, MATCH(1, (Raw_Financials!$A$2:$A$76="Linde India")*(Raw_Financials!$B$2:$B$76="2020"),0)+1),"")="",IF(OR(IFERROR(INDEX(Raw_Financials!$G$2:$G$76, MATCH(1, (Raw_Financials!$A$2:$A$76="Linde India")*(Raw_Financials!$B$2:$B$76="2020"),0)+1),"")="",IFERROR(INDEX(Raw_Financials!$H$2:$H$76, MATCH(1, (Raw_Financials!$A$2:$A$76="Linde India")*(Raw_Financials!$B$2:$B$76="2020"),0)+1),"")=""),"",(IFERROR(INDEX(Raw_Financials!$G$2:$G$76, MATCH(1, (Raw_Financials!$A$2:$A$76="Linde India")*(Raw_Financials!$B$2:$B$76="2020"),0)+1),""))-(IFERROR(INDEX(Raw_Financials!$H$2:$H$76, MATCH(1, (Raw_Financials!$A$2:$A$76="Linde India")*(Raw_Financials!$B$2:$B$76="2020"),0)+1),"")))=""),"",(IFERROR(INDEX(Raw_Financials!$C$2:$C$76, MATCH(1, (Raw_Financials!$A$2:$A$76="Linde India")*(Raw_Financials!$B$2:$B$76="2020"),0)+1),""))/(IF(OR(IFERROR(INDEX(Raw_Financials!$G$2:$G$76, MATCH(1, (Raw_Financials!$A$2:$A$76="Linde India")*(Raw_Financials!$B$2:$B$76="2020"),0)+1),"")="",IFERROR(INDEX(Raw_Financials!$H$2:$H$76, MATCH(1, (Raw_Financials!$A$2:$A$76="Linde India")*(Raw_Financials!$B$2:$B$76="2020"),0)+1),"")=""),"",(IFERROR(INDEX(Raw_Financials!$G$2:$G$76, MATCH(1, (Raw_Financials!$A$2:$A$76="Linde India")*(Raw_Financials!$B$2:$B$76="2020"),0)+1),""))-(IFERROR(INDEX(Raw_Financials!$H$2:$H$76, MATCH(1, (Raw_Financials!$A$2:$A$76="Linde India")*(Raw_Financials!$B$2:$B$76="2020"),0)+1),"")))))} -> 8.0354805 | G12: {=IF(OR(IFERROR(INDEX(Raw_Financials!$O$2:$O$76, MATCH(1, (Raw_Financials!$A$2:$A$76="Linde India")*(Raw_Financials!$B$2:$B$76="2020"),0)+1),"")="",IFERROR(INDEX(Raw_Financials!$M$2:$M$76, MATCH(1, (Raw_Financials!$A$2:$A$76="Linde India")*(Raw_Financials!$B$2:$B$76="2020"),0)+1),"")=""),"",(IFERROR(INDEX(Raw_Financials!$O$2:$O$76, MATCH(1, (Raw_Financials!$A$2:$A$76="Linde India")*(Raw_Financials!$B$2:$B$76="2020"),0)+1),""))/(IFERROR(INDEX(Raw_Financials!$M$2:$M$76, MATCH(1, (Raw_Financials!$A$2:$A$76="Linde India")*(Raw_Financials!$B$2:$B$76="2020"),0)+1),"")))} -> 3.2872904 | H12: {=IF(OR(IFERROR(INDEX(Raw_Financials!$M$2:$M$76, MATCH(1, (Raw_Financials!$A$2:$A$76="Linde India")*(Raw_Financials!$B$2:$B$76="2020"),0)+1),"")="",IFERROR(INDEX(Raw_Financials!$L$2:$L$76, MATCH(1, (Raw_Financials!$A$2:$A$76="Linde India")*(Raw_Financials!$B$2:$B$76="2020"),0)+1),"")=""),"",(IFERROR(INDEX(Raw_Financials!$M$2:$M$76, MATCH(1, (Raw_Financials!$A$2:$A$76="Linde India")*(Raw_Financials!$B$2:$B$76="2020"),0)+1),""))/(IFERROR(INDEX(Raw_Financials!$L$2:$L$76, MATCH(1, (Raw_Financials!$A$2:$A$76="Linde India")*(Raw_Financials!$B$2:$B$76="2020"),0)+1),"")))} -> 2.3555117 | I12: {=IF(OR(IFERROR(INDEX(Raw_Financials!$N$2:$N$76, MATCH(1, (Raw_Financials!$A$2:$A$76="Linde India")*(Raw_Financials!$B$2:$B$76="2020"),0)+1),"")="",IFERROR(INDEX(Raw_Financials!$J$2:$J$76, MATCH(1, (Raw_Financials!$A$2:$A$76="Linde India")*(Raw_Financials!$B$2:$B$76="2020"),0)+1),"")=""),"",(IFERROR(INDEX(Raw_Financials!$N$2:$N$76, MATCH(1, (Raw_Financials!$A$2:$A$76="Linde India")*(Raw_Financials!$B$2:$B$76="2020"),0)+1),""))-(IFERROR(INDEX(Raw_Financials!$J$2:$J$76, MATCH(1, (Raw_Financials!$A$2:$A$76="Linde India")*(Raw_Financials!$B$2:$B$76="2020"),0)+1),"")))} -> 19652.51 | J12: {=IF(OR(IFERROR(INDEX(Raw_Financials!$M$2:$M$76, MATCH(1, (Raw_Financials!$A$2:$A$76="Linde India")*(Raw_Financials!$B$2:$B$76="2020"),0)+1),"")="",IFERROR(INDEX(Raw_Financials!$C$2:$C$76, MATCH(1, (Raw_Financials!$A$2:$A$76="Linde India")*(Raw_Financials!$B$2:$B$76="2020"),0)+1),"")=""),"",(IFERROR(INDEX(Raw_Financials!$M$2:$M$76, MATCH(1, (Raw_Financials!$A$2:$A$76="Linde India")*(Raw_Financials!$B$2:$B$76="2020"),0)+1),""))/(IFERROR(INDEX(Raw_Financials!$C$2:$C$76, MATCH(1, (Raw_Financials!$A$2:$A$76="Linde India")*(Raw_Financials!$B$2:$B$76="2020"),0)+1),"")))} -> 0.20201162 | K12: {=IF(OR(IFERROR(INDEX(Raw_ESG!$C$2:$C$76, MATCH(1, (Raw_ESG!$A$2:$A$76="Linde India")*(Raw_ESG!$B$2:$B$76="2020"),0)+1),"")="",IFERROR(INDEX(Raw_Financials!$J$2:$J$76, MATCH(1, (Raw_Financials!$A$2:$A$76="Linde India")*(Raw_Financials!$B$2:$B$76="2020"),0)+1),"")=""),"",(IFERROR(INDEX(Raw_ESG!$C$2:$C$76, MATCH(1, (Raw_ESG!$A$2:$A$76="Linde India")*(Raw_ESG!$B$2:$B$76="2020"),0)+1),""))/(IFERROR(INDEX(Raw_Financials!$J$2:$J$76, MATCH(1, (Raw_Financials!$A$2:$A$76="Linde India")*(Raw_Financials!$B$2:$B$76="2020"),0)+1),"")))} -> 0.72617339 | L12: {=IF(OR(IFERROR(INDEX(Raw_ESG!$D$2:$D$76, MATCH(1, (Raw_ESG!$A$2:$A$76="Linde India")*(Raw_ESG!$B$2:$B$76="2020"),0)+1),"")="",IFERROR(INDEX(Raw_Financials!$E$2:$E$76, MATCH(1, (Raw_Financials!$A$2:$A$76="Linde India")*(Raw_Financials!$B$2:$B$76="2020"),0)+1),"")=""),"",(IFERROR(INDEX(Raw_ESG!$D$2:$D$76, MATCH(1, (Raw_ESG!$A$2:$A$76="Linde India")*(Raw_ESG!$B$2:$B$76="2020"),0)+1),""))/(IFERROR(INDEX(Raw_Financials!$E$2:$E$76, MATCH(1, (Raw_Financials!$A$2:$A$76="Linde India")*(Raw_Financials!$B$2:$B$76="2020"),0)+1),"")))} -> 0.23880996 | M12: {=IF(OR(IFERROR(INDEX(Raw_ESG!$E$2:$E$76, MATCH(1, (Raw_ESG!$A$2:$A$76="Linde India")*(Raw_ESG!$B$2:$B$76="2020"),0)+1),"")="",IFERROR(INDEX(Raw_ESG!$F$2:$F$76, MATCH(1, (Raw_ESG!$A$2:$A$76="Linde India")*(Raw_ESG!$B$2:$B$76="2020"),0)+1),"")=""),"",(IFERROR(INDEX(Raw_ESG!$E$2:$E$76, MATCH(1, (Raw_ESG!$A$2:$A$76="Linde India")*(Raw_ESG!$B$2:$B$76="2020"),0)+1),""))+(IFERROR(INDEX(Raw_ESG!$F$2:$F$76, MATCH(1, (Raw_ESG!$A$2:$A$76="Linde India")*(Raw_ESG!$B$2:$B$76="2020"),0)+1),"")))} -> 152269.2 | N12: {=IFERROR(INDEX(Raw_ESG!$G$2:$G$76, MATCH(1, (Raw_ESG!$A$2:$A$76="Linde India")*(Raw_ESG!$B$2:$B$76="2020"),0)+1),"")} -> 43.92
A13: Linde India | B13: 2021 | C13: {=IF(OR(IFERROR(INDEX(Raw_Financials!$E$2:$E$76, MATCH(1, (Raw_Financials!$A$2:$A$76="Linde India")*(Raw_Financials!$B$2:$B$76="2021"),0)+1),"")="",IFERROR(INDEX(Raw_Financials!$D$2:$D$76, MATCH(1, (Raw_Financials!$A$2:$A$76="Linde India")*(Raw_Financials!$B$2:$B$76="2021"),0)+1),"")=""),"",(IFERROR(INDEX(Raw_Financials!$D$2:$D$76, MATCH(1, (Raw_Financials!$A$2:$A$76="Linde India")*(Raw_Financials!$B$2:$B$76="2021"),0)+1),""))/(IFERROR(INDEX(Raw_Financials!$E$2:$E$76, MATCH(1, (Raw_Financials!$A$2:$A$76="Linde India")*(Raw_Financials!$B$2:$B$76="2021"),0)+1),"")))} -> 0.022965359 | D13: {=IF(OR(IFERROR(INDEX(Raw_Financials!$E$2:$E$76, MATCH(1, (Raw_Financials!$A$2:$A$76="Linde India")*(Raw_Financials!$B$2:$B$76="2021"),0)+1),"")="",IFERROR(INDEX(Raw_Financials!$C$2:$C$76, MATCH(1, (Raw_Financials!$A$2:$A$76="Linde India")*(Raw_Financials!$B$2:$B$76="2021"),0)+1),"")=""),"",(IFERROR(INDEX(Raw_Financials!$C$2:$C$76, MATCH(1, (Raw_Financials!$A$2:$A$76="Linde India")*(Raw_Financials!$B$2:$B$76="2021"),0)+1),""))/(IFERROR(INDEX(Raw_Financials!$E$2:$E$76, MATCH(1, (Raw_Financials!$A$2:$A$76="Linde India")*(Raw_Financials!$B$2:$B$76="2021"),0)+1),"")))} -> 0.19678299 | E13: {=IF(OR(IFERROR(INDEX(Raw_Financials!$G$2:$G$76, MATCH(1, (Raw_Financials!$A$2:$A$76="Linde India")*(Raw_Financials!$B$2:$B$76="2021"),0)+1),"")="",IFERROR(INDEX(Raw_Financials!$H$2:$H$76, MATCH(1, (Raw_Financials!$A$2:$A$76="Linde India")*(Raw_Financials!$B$2:$B$76="2021"),0)+1),"")=""),"",(IFERROR(INDEX(Raw_Financials!$G$2:$G$76, MATCH(1, (Raw_Financials!$A$2:$A$76="Linde India")*(Raw_Financials!$B$2:$B$76="2021"),0)+1),""))-(IFERROR(INDEX(Raw_Financials!$H$2:$H$76, MATCH(1, (Raw_Financials!$A$2:$A$76="Linde India")*(Raw_Financials!$B$2:$B$76="2021"),0)+1),"")))} -> -4481.85 | F13: {=IF(OR(IFERROR(INDEX(Raw_Financials!$C$2:$C$76, MATCH(1, (Raw_Financials!$A$2:$A$76="Linde India")*(Raw_Financials!$B$2:$B$76="2021"),0)+1),"")="",IF(OR(IFERROR(INDEX(Raw_Financials!$G$2:$G$76, MATCH(1, (Raw_Financials!$A$2:$A$76="Linde India")*(Raw_Financials!$B$2:$B$76="2021"),0)+1),"")="",IFERROR(INDEX(Raw_Financials!$H$2:$H$76, MATCH(1, (Raw_Financials!$A$2:$A$76="Linde India")*(Raw_Financials!$B$2:$B$76="2021"),0)+1),"")=""),"",(IFERROR(INDEX(Raw_Financials!$G$2:$G$76, MATCH(1, (Raw_Financials!$A$2:$A$76="Linde India")*(Raw_Financials!$B$2:$B$76="2021"),0)+1),""))-(IFERROR(INDEX(Raw_Financials!$H$2:$H$76, MATCH(1, (Raw_Financials!$A$2:$A$76="Linde India")*(Raw_Financials!$B$2:$B$76="2021"),0)+1),"")))=""),"",(IFERROR(INDEX(Raw_Financials!$C$2:$C$76, MATCH(1, (Raw_Financials!$A$2:$A$76="Linde India")*(Raw_Financials!$B$2:$B$76="2021"),0)+1),""))/(IF(OR(IFERROR(INDEX(Raw_Financials!$G$2:$G$76, MATCH(1, (Raw_Financials!$A$2:$A$76="Linde India")*(Raw_Financials!$B$2:$B$76="2021"),0)+1),"")="",IFERROR(INDEX(Raw_Financials!$H$2:$H$76, MATCH(1, (Raw_Financials!$A$2:$A$76="Linde India")*(Raw_Financials!$B$2:$B$76="2021"),0)+1),"")=""),"",(IFERROR(INDEX(Raw_Financials!$G$2:$G$76, MATCH(1, (Raw_Financials!$A$2:$A$76="Linde India")*(Raw_Financials!$B$2:$B$76="2021"),0)+1),""))-(IFERROR(INDEX(Raw_Financials!$H$2:$H$76, MATCH(1, (Raw_Financials!$A$2:$A$76="Linde India")*(Raw_Financials!$B$2:$B$76="2021"),0)+1),"")))))} -> -9.3830271 | G13: {=IF(OR(IFERROR(INDEX(Raw_Financials!$O$2:$O$76, MATCH(1, (Raw_Financials!$A$2:$A$76="Linde India")*(Raw_Financials!$B$2:$B$76="2021"),0)+1),"")="",IFERROR(INDEX(Raw_Financials!$M$2:$M$76, MATCH(1, (Raw_Financials!$A$2:$A$76="Linde India")*(Raw_Financials!$B$2:$B$76="2021"),0)+1),"")=""),"",(IFERROR(INDEX(Raw_Financials!$O$2:$O$76, MATCH(1, (Raw_Financials!$A$2:$A$76="Linde India")*(Raw_Financials!$B$2:$B$76="2021"),0)+1),""))/(IFERROR(INDEX(Raw_Financials!$M$2:$M$76, MATCH(1, (Raw_Financials!$A$2:$A$76="Linde India")*(Raw_Financials!$B$2:$B$76="2021"),0)+1),"")))} -> 5.9029292 | H13: {=IF(OR(IFERROR(INDEX(Raw_Financials!$M$2:$M$76, MATCH(1, (Raw_Financials!$A$2:$A$76="Linde India")*(Raw_Financials!$B$2:$B$76="2021"),0)+1),"")="",IFERROR(INDEX(Raw_Financials!$L$2:$L$76, MATCH(1, (Raw_Financials!$A$2:$A$76="Linde India")*(Raw_Financials!$B$2:$B$76="2021"),0)+1),"")=""),"",(IFERROR(INDEX(Raw_Financials!$M$2:$M$76, MATCH(1, (Raw_Financials!$A$2:$A$76="Linde India")*(Raw_Financials!$B$2:$B$76="2021"),0)+1),""))/(IFERROR(INDEX(Raw_Financials!$L$2:$L$76, MATCH(1, (Raw_Financials!$A$2:$A$76="Linde India")*(Raw_Financials!$B$2:$B$76="2021"),0)+1),"")))} -> 3.1979586 | I13: {=IF(OR(IFERROR(INDEX(Raw_Financials!$N$2:$N$76, MATCH(1, (Raw_Financials!$A$2:$A$76="Linde India")*(Raw_Financials!$B$2:$B$76="2021"),0)+1),"")="",IFERROR(INDEX(Raw_Financials!$J$2:$J$76, MATCH(1, (Raw_Financials!$A$2:$A$76="Linde India")*(Raw_Financials!$B$2:$B$76="2021"),0)+1),"")=""),"",(IFERROR(INDEX(Raw_Financials!$N$2:$N$76, MATCH(1, (Raw_Financials!$A$2:$A$76="Linde India")*(Raw_Financials!$B$2:$B$76="2021"),0)+1),""))-(IFERROR(INDEX(Raw_Financials!$J$2:$J$76, MATCH(1, (Raw_Financials!$A$2:$A$76="Linde India")*(Raw_Financials!$B$2:$B$76="2021"),0)+1),"")))} -> 24378.38 | J13: {=IF(OR(IFERROR(INDEX(Raw_Financials!$M$2:$M$76, MATCH(1, (Raw_Financials!$A$2:$A$76="Linde India")*(Raw_Financials!$B$2:$B$76="2021"),0)+1),"")="",IFERROR(INDEX(Raw_Financials!$C$2:$C$76, MATCH(1, (Raw_Financials!$A$2:$A$76="Linde India")*(Raw_Financials!$B$2:$B$76="2021"),0)+1),"")=""),"",(IFERROR(INDEX(Raw_Financials!$M$2:$M$76, MATCH(1, (Raw_Financials!$A$2:$A$76="Linde India")*(Raw_Financials!$B$2:$B$76="2021"),0)+1),""))/(IFERROR(INDEX(Raw_Financials!$C$2:$C$76, MATCH(1, (Raw_Financials!$A$2:$A$76="Linde India")*(Raw_Financials!$B$2:$B$76="2021"),0)+1),"")))} -> 0.2820719 | K13: {=IF(OR(IFERROR(INDEX(Raw_ESG!$C$2:$C$76, MATCH(1, (Raw_ESG!$A$2:$A$76="Linde India")*(Raw_ESG!$B$2:$B$76="2021"),0)+1),"")="",IFERROR(INDEX(Raw_Financials!$J$2:$J$76, MATCH(1, (Raw_Financials!$A$2:$A$76="Linde India")*(Raw_Financials!$B$2:$B$76="2021"),0)+1),"")=""),"",(IFERROR(INDEX(Raw_ESG!$C$2:$C$76, MATCH(1, (Raw_ESG!$A$2:$A$76="Linde India")*(Raw_ESG!$B$2:$B$76="2021"),0)+1),""))/(IFERROR(INDEX(Raw_Financials!$J$2:$J$76, MATCH(1, (Raw_Financials!$A$2:$A$76="Linde India")*(Raw_Financials!$B$2:$B$76="2021"),0)+1),"")))} -> 0.63136881 | L13: {=IF(OR(IFERROR(INDEX(Raw_ESG!$D$2:$D$76, MATCH(1, (Raw_ESG!$A$2:$A$76="Linde India")*(Raw_ESG!$B$2:$B$76="2021"),0)+1),"")="",IFERROR(INDEX(Raw_Financials!$E$2:$E$76, MATCH(1, (Raw_Financials!$A$2:$A$76="Linde India")*(Raw_Financials!$B$2:$B$76="2021"),0)+1),"")=""),"",(IFERROR(INDEX(Raw_ESG!$D$2:$D$76, MATCH(1, (Raw_ESG!$A$2:$A$76="Linde India")*(Raw_ESG!$B$2:$B$76="2021"),0)+1),""))/(IFERROR(INDEX(Raw_Financials!$E$2:$E$76, MATCH(1, (Raw_Financials!$A$2:$A$76="Linde India")*(Raw_Financials!$B$2:$B$76="2021"),0)+1),"")))} -> 0.10646102 | M13: {=IF(OR(IFERROR(INDEX(Raw_ESG!$E$2:$E$76, MATCH(1, (Raw_ESG!$A$2:$A$76="Linde India")*(Raw_ESG!$B$2:$B$76="2021"),0)+1),"")="",IFERROR(INDEX(Raw_ESG!$F$2:$F$76, MATCH(1, (Raw_ESG!$A$2:$A$76="Linde India")*(Raw_ESG!$B$2:$B$76="2021"),0)+1),"")=""),"",(IFERROR(INDEX(Raw_ESG!$E$2:$E$76, MATCH(1, (Raw_ESG!$A$2:$A$76="Linde India")*(Raw_ESG!$B$2:$B$76="2021"),0)+1),""))+(IFERROR(INDEX(Raw_ESG!$F$2:$F$76, MATCH(1, (Raw_ESG!$A$2:$A$76="Linde India")*(Raw_ESG!$B$2:$B$76="2021"),0)+1),"")))} -> 139568.77 | N13: {=IFERROR(INDEX(Raw_ESG!$G$2:$G$76, MATCH(1, (Raw_ESG!$A$2:$A$76="Linde India")*(Raw_ESG!$B$2:$B$76="2021"),0)+1),"")} -> 41.27
A14: Linde India | B14: 2022 | C14: {=IF(OR(IFERROR(INDEX(Raw_Financials!$E$2:$E$76, MATCH(1, (Raw_Financials!$A$2:$A$76="Linde India")*(Raw_Financials!$B$2:$B$76="2022"),0)+1),"")="",IFERROR(INDEX(Raw_Financials!$D$2:$D$76, MATCH(1, (Raw_Financials!$A$2:$A$76="Linde India")*(Raw_Financials!$B$2:$B$76="2022"),0)+1),"")=""),"",(IFERROR(INDEX(Raw_Financials!$D$2:$D$76, MATCH(1, (Raw_Financials!$A$2:$A$76="Linde India")*(Raw_Financials!$B$2:$B$76="2022"),0)+1),""))/(IFERROR(INDEX(Raw_Financials!$E$2:$E$76, MATCH(1, (Raw_Financials!$A$2:$A$76="Linde India")*(Raw_Financials!$B$2:$B$76="2022"),0)+1),"")))} -> 0.046799694 | D14: {=IF(OR(IFERROR(INDEX(Raw_Financials!$E$2:$E$76, MATCH(1, (Raw_Financials!$A$2:$A$76="Linde India")*(Raw_Financials!$B$2:$B$76="2022"),0)+1),"")="",IFERROR(INDEX(Raw_Financials!$C$2:$C$76, MATCH(1, (Raw_Financials!$A$2:$A$76="Linde India")*(Raw_Financials!$B$2:$B$76="2022"),0)+1),"")=""),"",(IFERROR(INDEX(Raw_Financials!$C$2:$C$76, MATCH(1, (Raw_Financials!$A$2:$A$76="Linde India")*(Raw_Financials!$B$2:$B$76="2022"),0)+1),""))/(IFERROR(INDEX(Raw_Financials!$E$2:$E$76, MATCH(1, (Raw_Financials!$A$2:$A$76="Linde India")*(Raw_Financials!$B$2:$B$76="2022"),0)+1),"")))} -> 0.20261097 | E14: {=IF(OR(IFERROR(INDEX(Raw_Financials!$G$2:$G$76, MATCH(1, (Raw_Financials!$A$2:$A$76="Linde India")*(Raw_Financials!$B$2:$B$76="2022"),0)+1),"")="",IFERROR(INDEX(Raw_Financials!$H$2:$H$76, MATCH(1, (Raw_Financials!$A$2:$A$76="Linde India")*(Raw_Financials!$B$2:$B$76="2022"),0)+1),"")=""),"",(IFERROR(INDEX(Raw_Financials!$G$2:$G$76, MATCH(1, (Raw_Financials!$A$2:$A$76="Linde India")*(Raw_Financials!$B$2:$B$76="2022"),0)+1),""))-(IFERROR(INDEX(Raw_Financials!$H$2:$H$76, MATCH(1, (Raw_Financials!$A$2:$A$76="Linde India")*(Raw_Financials!$B$2:$B$76="2022"),0)+1),"")))} -> 16934.07 | F14: {=IF(OR(IFERROR(INDEX(Raw_Financials!$C$2:$C$76, MATCH(1, (Raw_Financials!$A$2:$A$76="Linde India")*(Raw_Financials!$B$2:$B$76="2022"),0)+1),"")="",IF(OR(IFERROR(INDEX(Raw_Financials!$G$2:$G$76, MATCH(1, (Raw_Financials!$A$2:$A$76="Linde India")*(Raw_Financials!$B$2:$B$76="2022"),0)+1),"")="",IFERROR(INDEX(Raw_Financials!$H$2:$H$76, MATCH(1, (Raw_Financials!$A$2:$A$76="Linde India")*(Raw_Financials!$B$2:$B$76="2022"),0)+1),"")=""),"",(IFERROR(INDEX(Raw_Financials!$G$2:$G$76, MATCH(1, (Raw_Financials!$A$2:$A$76="Linde India")*(Raw_Financials!$B$2:$B$76="2022"),0)+1),""))-(IFERROR(INDEX(Raw_Financials!$H$2:$H$76, MATCH(1, (Raw_Financials!$A$2:$A$76="Linde India")*(Raw_Financials!$B$2:$B$76="2022"),0)+1),"")))=""),"",(IFERROR(INDEX(Raw_Financials!$C$2:$C$76, MATCH(1, (Raw_Financials!$A$2:$A$76="Linde India")*(Raw_Financials!$B$2:$B$76="2022"),0)+1),""))/(IF(OR(IFERROR(INDEX(Raw_Financials!$G$2:$G$76, MATCH(1, (Raw_Financials!$A$2:$A$76="Linde India")*(Raw_Financials!$B$2:$B$76="2022"),0)+1),"")="",IFERROR(INDEX(Raw_Financials!$H$2:$H$76, MATCH(1, (Raw_Financials!$A$2:$A$76="Linde India")*(Raw_Financials!$B$2:$B$76="2022"),0)+1),"")=""),"",(IFERROR(INDEX(Raw_Financials!$G$2:$G$76, MATCH(1, (Raw_Financials!$A$2:$A$76="Linde India")*(Raw_Financials!$B$2:$B$76="2022"),0)+1),""))-(IFERROR(INDEX(Raw_Financials!$H$2:$H$76, MATCH(1, (Raw_Financials!$A$2:$A$76="Linde India")*(Raw_Financials!$B$2:$B$76="2022"),0)+1),"")))))} -> 2.5073996 | G14: {=IF(OR(IFERROR(INDEX(Raw_Financials!$O$2:$O$76, MATCH(1, (Raw_Financials!$A$2:$A$76="Linde India")*(Raw_Financials!$B$2:$B$76="2022"),0)+1),"")="",IFERROR(INDEX(Raw_Financials!$M$2:$M$76, MATCH(1, (Raw_Financials!$A$2:$A$76="Linde India")*(Raw_Financials!$B$2:$B$76="2022"),0)+1),"")=""),"",(IFERROR(INDEX(Raw_Financials!$O$2:$O$76, MATCH(1, (Raw_Financials!$A$2:$A$76="Linde India")*(Raw_Financials!$B$2:$B$76="2022"),0)+1),""))/(IFERROR(INDEX(Raw_Financials!$M$2:$M$76, MATCH(1, (Raw_Financials!$A$2:$A$76="Linde India")*(Raw_Financials!$B$2:$B$76="2022"),0)+1),"")))} -> 5.7124345 | H14: {=IF(OR(IFERROR(INDEX(Raw_Financials!$M$2:$M$76, MATCH(1, (Raw_Financials!$A$2:$A$76="Linde India")*(Raw_Financials!$B$2:$B$76="2022"),0)+1),"")="",IFERROR(INDEX(Raw_Financials!$L$2:$L$76, MATCH(1, (Raw_Financials!$A$2:$A$76="Linde India")*(Raw_Financials!$B$2:$B$76="2022"),0)+1),"")=""),"",(IFERROR(INDEX(Raw_Financials!$M$2:$M$76, MATCH(1, (Raw_Financials!$A$2:$A$76="Linde India")*(Raw_Financials!$B$2:$B$76="2022"),0)+1),""))/(IFERROR(INDEX(Raw_Financials!$L$2:$L$76, MATCH(1, (Raw_Financials!$A$2:$A$76="Linde India")*(Raw_Financials!$B$2:$B$76="2022"),0)+1),"")))} -> 1.8408648 | I14: {=IF(OR(IFERROR(INDEX(Raw_Financials!$N$2:$N$76, MATCH(1, (Raw_Financials!$A$2:$A$76="Linde India")*(Raw_Financials!$B$2:$B$76="2022"),0)+1),"")="",IFERROR(INDEX(Raw_Financials!$J$2:$J$76, MATCH(1, (Raw_Financials!$A$2:$A$76="Linde India")*(Raw_Financials!$B$2:$B$76="2022"),0)+1),"")=""),"",(IFERROR(INDEX(Raw_Financials!$N$2:$N$76, MATCH(1, (Raw_Financials!$A$2:$A$76="Linde India")*(Raw_Financials!$B$2:$B$76="2022"),0)+1),""))-(IFERROR(INDEX(Raw_Financials!$J$2:$J$76, MATCH(1, (Raw_Financials!$A$2:$A$76="Linde India")*(Raw_Financials!$B$2:$B$76="2022"),0)+1),"")))} -> 8420.5 | J14: {=IF(OR(IFERROR(INDEX(Raw_Financials!$M$2:$M$76, MATCH(1, (Raw_Financials!$A$2:$A$76="Linde India")*(Raw_Financials!$B$2:$B$76="2022"),0)+1),"")="",IFERROR(INDEX(Raw_Financials!$C$2:$C$76, MATCH(1, (Raw_Financials!$A$2:$A$76="Linde India")*(Raw_Financials!$B$2:$B$76="2022"),0)+1),"")=""),"",(IFERROR(INDEX(Raw_Financials!$M$2:$M$76, MATCH(1, (Raw_Financials!$A$2:$A$76="Linde India")*(Raw_Financials!$B$2:$B$76="2022"),0)+1),""))/(IFERROR(INDEX(Raw_Financials!$C$2:$C$76, MATCH(1, (Raw_Financials!$A$2:$A$76="Linde India")*(Raw_Financials!$B$2:$B$76="2022"),0)+1),"")))} -> 0.23984515 | K14: {=IF(OR(IFERROR(INDEX(Raw_ESG!$C$2:$C$76, MATCH(1, (Raw_ESG!$A$2:$A$76="Linde India")*(Raw_ESG!$B$2:$B$76="2022"),0)+1),"")="",IFERROR(INDEX(Raw_Financials!$J$2:$J$76, MATCH(1, (Raw_Financials!$A$2:$A$76="Linde India")*(Raw_Financials!$B$2:$B$76="2022"),0)+1),"")=""),"",(IFERROR(INDEX(Raw_ESG!$C$2:$C$76, MATCH(1, (Raw_ESG!$A$2:$A$76="Linde India")*(Raw_ESG!$B$2:$B$76="2022"),0)+1),""))/(IFERROR(INDEX(Raw_Financials!$J$2:$J$76, MATCH(1, (Raw_Financials!$A$2:$A$76="Linde India")*(Raw_Financials!$B$2:$B$76="2022"),0)+1),"")))} -> 0.53832284 | L14: {=IF(OR(IFERROR(INDEX(Raw_ESG!$D$2:$D$76, MATCH(1, (Raw_ESG!$A$2:$A$76="Linde India")*(Raw_ESG!$B$2:$B$76="2022"),0)+1),"")="",IFERROR(INDEX(Raw_Financials!$E$2:$E$76, MATCH(1, (Raw_Financials!$A$2:$A$76="Linde India")*(Raw_Financials!$B$2:$B$76="2022"),0)+1),"")=""),"",(IFERROR(INDEX(Raw_ESG!$D$2:$D$76, MATCH(1, (Raw_ESG!$A$2:$A$76="Linde India")*(Raw_ESG!$B$2:$B$76="2022"),0)+1),""))/(IFERROR(INDEX(Raw_Financials!$E$2:$E$76, MATCH(1, (Raw_Financials!$A$2:$A$76="Linde India")*(Raw_Financials!$B$2:$B$76="2022"),0)+1),"")))} -> 0.13238874 | M14: {=IF(OR(IFERROR(INDEX(Raw_ESG!$E$2:$E$76, MATCH(1, (Raw_ESG!$A$2:$A$76="Linde India")*(Raw_ESG!$B$2:$B$76="2022"),0)+1),"")="",IFERROR(INDEX(Raw_ESG!$F$2:$F$76, MATCH(1, (Raw_ESG!$A$2:$A$76="Linde India")*(Raw_ESG!$B$2:$B$76="2022"),0)+1),"")=""),"",(IFERROR(INDEX(Raw_ESG!$E$2:$E$76, MATCH(1, (Raw_ESG!$A$2:$A$76="Linde India")*(Raw_ESG!$B$2:$B$76="2022"),0)+1),""))+(IFERROR(INDEX(Raw_ESG!$F$2:$F$76, MATCH(1, (Raw_ESG!$A$2:$A$76="Linde India")*(Raw_ESG!$B$2:$B$76="2022"),0)+1),"")))} -> 160851.08 | N14: {=IFERROR(INDEX(Raw_ESG!$G$2:$G$76, MATCH(1, (Raw_ESG!$A$2:$A$76="Linde India")*(Raw_ESG!$B$2:$B$76="2022"),0)+1),"")} -> 88.13
A15: Linde India | B15: 2023 | C15: {=IF(OR(IFERROR(INDEX(Raw_Financials!$E$2:$E$76, MATCH(1, (Raw_Financials!$A$2:$A$76="Linde India")*(Raw_Financials!$B$2:$B$76="2023"),0)+1),"")="",IFERROR(INDEX(Raw_Financials!$D$2:$D$76, MATCH(1, (Raw_Financials!$A$2:$A$76="Linde India")*(Raw_Financials!$B$2:$B$76="2023"),0)+1),"")=""),"",(IFERROR(INDEX(Raw_Financials!$D$2:$D$76, MATCH(1, (Raw_Financials!$A$2:$A$76="Linde India")*(Raw_Financials!$B$2:$B$76="2023"),0)+1),""))/(IFERROR(INDEX(Raw_Financials!$E$2:$E$76, MATCH(1, (Raw_Financials!$A$2:$A$76="Linde India")*(Raw_Financials!$B$2:$B$76="2023"),0)+1),"")))} -> 0.055182179 | D15: {=IF(OR(IFERROR(INDEX(Raw_Financials!$E$2:$E$76, MATCH(1, (Raw_Financials!$A$2:$A$76="Linde India")*(Raw_Financials!$B$2:$B$76="2023"),0)+1),"")="",IFERROR(INDEX(Raw_Financials!$C$2:$C$76, MATCH(1, (Raw_Financials!$A$2:$A$76="Linde India")*(Raw_Financials!$B$2:$B$76="2023"),0)+1),"")=""),"",(IFERROR(INDEX(Raw_Financials!$C$2:$C$76, MATCH(1, (Raw_Financials!$A$2:$A$76="Linde India")*(Raw_Financials!$B$2:$B$76="2023"),0)+1),""))/(IFERROR(INDEX(Raw_Financials!$E$2:$E$76, MATCH(1, (Raw_Financials!$A$2:$A$76="Linde India")*(Raw_Financials!$B$2:$B$76="2023"),0)+1),"")))} -> 0.30346327 | E15: {=IF(OR(IFERROR(INDEX(Raw_Financials!$G$2:$G$76, MATCH(1, (Raw_Financials!$A$2:$A$76="Linde India")*(Raw_Financials!$B$2:$B$76="2023"),0)+1),"")="",IFERROR(INDEX(Raw_Financials!$H$2:$H$76, MATCH(1, (Raw_Financials!$A$2:$A$76="Linde India")*(Raw_Financials!$B$2:$B$76="2023"),0)+1),"")=""),"",(IFERROR(INDEX(Raw_Financials!$G$2:$G$76, MATCH(1, (Raw_Financials!$A$2:$A$76="Linde India")*(Raw_Financials!$B$2:$B$76="2023"),0)+1),""))-(IFERROR(INDEX(Raw_Financials!$H$2:$H$76, MATCH(1, (Raw_Financials!$A$2:$A$76="Linde India")*(Raw_Financials!$B$2:$B$76="2023"),0)+1),"")))} -> 26369.7 | F15: {=IF(OR(IFERROR(INDEX(Raw_Financials!$C$2:$C$76, MATCH(1, (Raw_Financials!$A$2:$A$76="Linde India")*(Raw_Financials!$B$2:$B$76="2023"),0)+1),"")="",IF(OR(IFERROR(INDEX(Raw_Financials!$G$2:$G$76, MATCH(1, (Raw_Financials!$A$2:$A$76="Linde India")*(Raw_Financials!$B$2:$B$76="2023"),0)+1),"")="",IFERROR(INDEX(Raw_Financials!$H$2:$H$76, MATCH(1, (Raw_Financials!$A$2:$A$76="Linde India")*(Raw_Financials!$B$2:$B$76="2023"),0)+1),"")=""),"",(IFERROR(INDEX(Raw_Financials!$G$2:$G$76, MATCH(1, (Raw_Financials!$A$2:$A$76="Linde India")*(Raw_Financials!$B$2:$B$76="2023"),0)+1),""))-(IFERROR(INDEX(Raw_Financials!$H$2:$H$76, MATCH(1, (Raw_Financials!$A$2:$A$76="Linde India")*(Raw_Financials!$B$2:$B$76="2023"),0)+1),"")))=""),"",(IFERROR(INDEX(Raw_Financials!$C$2:$C$76, MATCH(1, (Raw_Financials!$A$2:$A$76="Linde India")*(Raw_Financials!$B$2:$B$76="2023"),0)+1),""))/(IF(OR(IFERROR(INDEX(Raw_Financials!$G$2:$G$76, MATCH(1, (Raw_Financials!$A$2:$A$76="Linde India")*(Raw_Financials!$B$2:$B$76="2023"),0)+1),"")="",IFERROR(INDEX(Raw_Financials!$H$2:$H$76, MATCH(1, (Raw_Financials!$A$2:$A$76="Linde India")*(Raw_Financials!$B$2:$B$76="2023"),0)+1),"")=""),"",(IFERROR(INDEX(Raw_Financials!$G$2:$G$76, MATCH(1, (Raw_Financials!$A$2:$A$76="Linde India")*(Raw_Financials!$B$2:$B$76="2023"),0)+1),""))-(IFERROR(INDEX(Raw_Financials!$H$2:$H$76, MATCH(1, (Raw_Financials!$A$2:$A$76="Linde India")*(Raw_Financials!$B$2:$B$76="2023"),0)+1),"")))))} -> 1.9885205 | G15: {=IF(OR(IFERROR(INDEX(Raw_Financials!$O$2:$O$76, MATCH(1, (Raw_Financials!$A$2:$A$76="Linde India")*(Raw_Financials!$B$2:$B$76="2023"),0)+1),"")="",IFERROR(INDEX(Raw_Financials!$M$2:$M$76, MATCH(1, (Raw_Financials!$A$2:$A$76="Linde India")*(Raw_Financials!$B$2:$B$76="2023"),0)+1),"")=""),"",(IFERROR(INDEX(Raw_Financials!$O$2:$O$76, MATCH(1, (Raw_Financials!$A$2:$A$76="Linde India")*(Raw_Financials!$B$2:$B$76="2023"),0)+1),""))/(IFERROR(INDEX(Raw_Financials!$M$2:$M$76, MATCH(1, (Raw_Financials!$A$2:$A$76="Linde India")*(Raw_Financials!$B$2:$B$76="2023"),0)+1),"")))} -> 1.2821098 | H15: {=IF(OR(IFERROR(INDEX(Raw_Financials!$M$2:$M$76, MATCH(1, (Raw_Financials!$A$2:$A$76="Linde India")*(Raw_Financials!$B$2:$B$76="2023"),0)+1),"")="",IFERROR(INDEX(Raw_Financials!$L$2:$L$76, MATCH(1, (Raw_Financials!$A$2:$A$76="Linde India")*(Raw_Financials!$B$2:$B$76="2023"),0)+1),"")=""),"",(IFERROR(INDEX(Raw_Financials!$M$2:$M$76, MATCH(1, (Raw_Financials!$A$2:$A$76="Linde India")*(Raw_Financials!$B$2:$B$76="2023"),0)+1),""))/(IFERROR(INDEX(Raw_Financials!$L$2:$L$76, MATCH(1, (Raw_Financials!$A$2:$A$76="Linde India")*(Raw_Financials!$B$2:$B$76="2023"),0)+1),"")))} -> 3.4319372 | I15: {=IF(OR(IFERROR(INDEX(Raw_Financials!$N$2:$N$76, MATCH(1, (Raw_Financials!$A$2:$A$76="Linde India")*(Raw_Financials!$B$2:$B$76="2023"),0)+1),"")="",IFERROR(INDEX(Raw_Financials!$J$2:$J$76, MATCH(1, (Raw_Financials!$A$2:$A$76="Linde India")*(Raw_Financials!$B$2:$B$76="2023"),0)+1),"")=""),"",(IFERROR(INDEX(Raw_Financials!$N$2:$N$76, MATCH(1, (Raw_Financials!$A$2:$A$76="Linde India")*(Raw_Financials!$B$2:$B$76="2023"),0)+1),""))-(IFERROR(INDEX(Raw_Financials!$J$2:$J$76, MATCH(1, (Raw_Financials!$A$2:$A$76="Linde India")*(Raw_Financials!$B$2:$B$76="2023"),0)+1),"")))} -> 14242.81 | J15: {=IF(OR(IFERROR(INDEX(Raw_Financials!$M$2:$M$76, MATCH(1, (Raw_Financials!$A$2:$A$76="Linde India")*(Raw_Financials!$B$2:$B$76="2023"),0)+1),"")="",IFERROR(INDEX(Raw_Financials!$C$2:$C$76, MATCH(1, (Raw_Financials!$A$2:$A$76="Linde India")*(Raw_Financials!$B$2:$B$76="2023"),0)+1),"")=""),"",(IFERROR(INDEX(Raw_Financials!$M$2:$M$76, MATCH(1, (Raw_Financials!$A$2:$A$76="Linde India")*(Raw_Financials!$B$2:$B$76="2023"),0)+1),""))/(IFERROR(INDEX(Raw_Financials!$C$2:$C$76, MATCH(1, (Raw_Financials!$A$2:$A$76="Linde India")*(Raw_Financials!$B$2:$B$76="2023"),0)+1),"")))} -> 0.44152787 | K15: {=IF(OR(IFERROR(INDEX(Raw_ESG!$C$2:$C$76, MATCH(1, (Raw_ESG!$A$2:$A$76="Linde India")*(Raw_ESG!$B$2:$B$76="2023"),0)+1),"")="",IFERROR(INDEX(Raw_Financials!$J$2:$J$76, MATCH(1, (Raw_Financials!$A$2:$A$76="Linde India")*(Raw_Financials!$B$2:$B$76="2023"),0)+1),"")=""),"",(IFERROR(INDEX(Raw_ESG!$C$2:$C$76, MATCH(1, (Raw_ESG!$A$2:$A$76="Linde India")*(Raw_ESG!$B$2:$B$76="2023"),0)+1),""))/(IFERROR(INDEX(Raw_Financials!$J$2:$J$76, MATCH(1, (Raw_Financials!$A$2:$A$76="Linde India")*(Raw_Financials!$B$2:$B$76="2023"),0)+1),"")))} -> 0.27349736 | L15: {=IF(OR(IFERROR(INDEX(Raw_ESG!$D$2:$D$76, MATCH(1, (Raw_ESG!$A$2:$A$76="Linde India")*(Raw_ESG!$B$2:$B$76="2023"),0)+1),"")="",IFERROR(INDEX(Raw_Financials!$E$2:$E$76, MATCH(1, (Raw_Financials!$A$2:$A$76="Linde India")*(Raw_Financials!$B$2:$B$76="2023"),0)+1),"")=""),"",(IFERROR(INDEX(Raw_ESG!$D$2:$D$76, MATCH(1, (Raw_ESG!$A$2:$A$76="Linde India")*(Raw_ESG!$B$2:$B$76="2023"),0)+1),""))/(IFERROR(INDEX(Raw_Financials!$E$2:$E$76, MATCH(1, (Raw_Financials!$A$2:$A$76="Linde India")*(Raw_Financials!$B$2:$B$76="2023"),0)+1),"")))} -> 0.11252867 | M15: {=IF(OR(IFERROR(INDEX(Raw_ESG!$E$2:$E$76, MATCH(1, (Raw_ESG!$A$2:$A$76="Linde India")*(Raw_ESG!$B$2:$B$76="2023"),0)+1),"")="",IFERROR(INDEX(Raw_ESG!$F$2:$F$76, MATCH(1, (Raw_ESG!$A$2:$A$76="Linde India")*(Raw_ESG!$B$2:$B$76="2023"),0)+1),"")=""),"",(IFERROR(INDEX(Raw_ESG!$E$2:$E$76, MATCH(1, (Raw_ESG!$A$2:$A$76="Linde India")*(Raw_ESG!$B$2:$B$76="2023"),0)+1),""))+(IFERROR(INDEX(Raw_ESG!$F$2:$F$76, MATCH(1, (Raw_ESG!$A$2:$A$76="Linde India")*(Raw_ESG!$B$2:$B$76="2023"),0)+1),"")))} -> 92884.51 | N15: {=IFERROR(INDEX(Raw_ESG!$G$2:$G$76, MATCH(1, (Raw_ESG!$A$2:$A$76="Linde India")*(Raw_ESG!$B$2:$B$76="2023"),0)+1),"")} -> 81.8
A16: Linde India | B16: 2024 | C16: {=IF(OR(IFERROR(INDEX(Raw_Financials!$E$2:$E$76, MATCH(1, (Raw_Financials!$A$2:$A$76="Linde India")*(Raw_Financials!$B$2:$B$76="2024"),0)+1),"")="",IFERROR(INDEX(Raw_Financials!$D$2:$D$76, MATCH(1, (Raw_Financials!$A$2:$A$76="Linde India")*(Raw_Financials!$B$2:$B$76="2024"),0)+1),"")=""),"",(IFERROR(INDEX(Raw_Financials!$D$2:$D$76, MATCH(1, (Raw_Financials!$A$2:$A$76="Linde India")*(Raw_Financials!$B$2:$B$76="2024"),0)+1),""))/(IFERROR(INDEX(Raw_Financials!$E$2:$E$76, MATCH(1, (Raw_Financials!$A$2:$A$76="Linde India")*(Raw_Financials!$B$2:$B$76="2024"),0)+1),"")))} -> 0.087964094 | D16: {=IF(OR(IFERROR(INDEX(Raw_Financials!$E$2:$E$76, MATCH(1, (Raw_Financials!$A$2:$A$76="Linde India")*(Raw_Financials!$B$2:$B$76="2024"),0)+1),"")="",IFERROR(INDEX(Raw_Financials!$C$2:$C$76, MATCH(1, (Raw_Financials!$A$2:$A$76="Linde India")*(Raw_Financials!$B$2:$B$76="2024"),0)+1),"")=""),"",(IFERROR(INDEX(Raw_Financials!$C$2:$C$76, MATCH(1, (Raw_Financials!$A$2:$A$76="Linde India")*(Raw_Financials!$B$2:$B$76="2024"),0)+1),""))/(IFERROR(INDEX(Raw_Financials!$E$2:$E$76, MATCH(1, (Raw_Financials!$A$2:$A$76="Linde India")*(Raw_Financials!$B$2:$B$76="2024"),0)+1),"")))} -> 0.27768129 | E16: {=IF(OR(IFERROR(INDEX(Raw_Financials!$G$2:$G$76, MATCH(1, (Raw_Financials!$A$2:$A$76="Linde India")*(Raw_Financials!$B$2:$B$76="2024"),0)+1),"")="",IFERROR(INDEX(Raw_Financials!$H$2:$H$76, MATCH(1, (Raw_Financials!$A$2:$A$76="Linde India")*(Raw_Financials!$B$2:$B$76="2024"),0)+1),"")=""),"",(IFERROR(INDEX(Raw_Financials!$G$2:$G$76, MATCH(1, (Raw_Financials!$A$2:$A$76="Linde India")*(Raw_Financials!$B$2:$B$76="2024"),0)+1),""))-(IFERROR(INDEX(Raw_Financials!$H$2:$H$76, MATCH(1, (Raw_Financials!$A$2:$A$76="Linde India")*(Raw_Financials!$B$2:$B$76="2024"),0)+1),"")))} -> 6401.21 | F16: {=IF(OR(IFERROR(INDEX(Raw_Financials!$C$2:$C$76, MATCH(1, (Raw_Financials!$A$2:$A$76="Linde India")*(Raw_Financials!$B$2:$B$76="2024"),0)+1),"")="",IF(OR(IFERROR(INDEX(Raw_Financials!$G$2:$G$76, MATCH(1, (Raw_Financials!$A$2:$A$76="Linde India")*(Raw_Financials!$B$2:$B$76="2024"),0)+1),"")="",IFERROR(INDEX(Raw_Financials!$H$2:$H$76, MATCH(1, (Raw_Financials!$A$2:$A$76="Linde India")*(Raw_Financials!$B$2:$B$76="2024"),0)+1),"")=""),"",(IFERROR(INDEX(Raw_Financials!$G$2:$G$76, MATCH(1, (Raw_Financials!$A$2:$A$76="Linde India")*(Raw_Financials!$B$2:$B$76="2024"),0)+1),""))-(IFERROR(INDEX(Raw_Financials!$H$2:$H$76, MATCH(1, (Raw_Financials!$A$2:$A$76="Linde India")*(Raw_Financials!$B$2:$B$76="2024"),0)+1),"")))=""),"",(IFERROR(INDEX(Raw_Financials!$C$2:$C$76, MATCH(1, (Raw_Financials!$A$2:$A$76="Linde India")*(Raw_Financials!$B$2:$B$76="2024"),0)+1),""))/(IF(OR(IFERROR(INDEX(Raw_Financials!$G$2:$G$76, MATCH(1, (Raw_Financials!$A$2:$A$76="Linde India")*(Raw_Financials!$B$2:$B$76="2024"),0)+1),"")="",IFERROR(INDEX(Raw_Financials!$H$2:$H$76, MATCH(1, (Raw_Financials!$A$2:$A$76="Linde India")*(Raw_Financials!$B$2:$B$76="2024"),0)+1),"")=""),"",(IFERROR(INDEX(Raw_Financials!$G$2:$G$76, MATCH(1, (Raw_Financials!$A$2:$A$76="Linde India")*(Raw_Financials!$B$2:$B$76="2024"),0)+1),""))-(IFERROR(INDEX(Raw_Financials!$H$2:$H$76, MATCH(1, (Raw_Financials!$A$2:$A$76="Linde India")*(Raw_Financials!$B$2:$B$76="2024"),0)+1),"")))))} -> 5.81132 | G16: {=IF(OR(IFERROR(INDEX(Raw_Financials!$O$2:$O$76, MATCH(1, (Raw_Financials!$A$2:$A$76="Linde India")*(Raw_Financials!$B$2:$B$76="2024"),0)+1),"")="",IFERROR(INDEX(Raw_Financials!$M$2:$M$76, MATCH(1, (Raw_Financials!$A$2:$A$76="Linde India")*(Raw_Financials!$B$2:$B$76="2024"),0)+1),"")=""),"",(IFERROR(INDEX(Raw_Financials!$O$2:$O$76, MATCH(1, (Raw_Financials!$A$2:$A$76="Linde India")*(Raw_Financials!$B$2:$B$76="2024"),0)+1),""))/(IFERROR(INDEX(Raw_Financials!$M$2:$M$76, MATCH(1, (Raw_Financials!$A$2:$A$76="Linde India")*(Raw_Financials!$B$2:$B$76="2024"),0)+1),"")))} -> 1.072263 | H16: {=IF(OR(IFERROR(INDEX(Raw_Financials!$M$2:$M$76, MATCH(1, (Raw_Financials!$A$2:$A$76="Linde India")*(Raw_Financials!$B$2:$B$76="2024"),0)+1),"")="",IFERROR(INDEX(Raw_Financials!$L$2:$L$76, MATCH(1, (Raw_Financials!$A$2:$A$76="Linde India")*(Raw_Financials!$B$2:$B$76="2024"),0)+1),"")=""),"",(IFERROR(INDEX(Raw_Financials!$M$2:$M$76, MATCH(1, (Raw_Financials!$A$2:$A$76="Linde India")*(Raw_Financials!$B$2:$B$76="2024"),0)+1),""))/(IFERROR(INDEX(Raw_Financials!$L$2:$L$76, MATCH(1, (Raw_Financials!$A$2:$A$76="Linde India")*(Raw_Financials!$B$2:$B$76="2024"),0)+1),"")))} -> 7.033246 | I16: {=IF(OR(IFERROR(INDEX(Raw_Financials!$N$2:$N$76, MATCH(1, (Raw_Financials!$A$2:$A$76="Linde India")*(Raw_Financials!$B$2:$B$76="2024"),0)+1),"")="",IFERROR(INDEX(Raw_Financials!$J$2:$J$76, MATCH(1, (Raw_Financials!$A$2:$A$76="Linde India")*(Raw_Financials!$B$2:$B$76="2024"),0)+1),"")=""),"",(IFERROR(INDEX(Raw_Financials!$N$2:$N$76, MATCH(1, (Raw_Financials!$A$2:$A$76="Linde India")*(Raw_Financials!$B$2:$B$76="2024"),0)+1),""))-(IFERROR(INDEX(Raw_Financials!$J$2:$J$76, MATCH(1, (Raw_Financials!$A$2:$A$76="Linde India")*(Raw_Financials!$B$2:$B$76="2024"),0)+1),"")))} -> 8750.27 | J16: {=IF(OR(IFERROR(INDEX(Raw_Financials!$M$2:$M$76, MATCH(1, (Raw_Financials!$A$2:$A$76="Linde India")*(Raw_Financials!$B$2:$B$76="2024"),0)+1),"")="",IFERROR(INDEX(Raw_Financials!$C$2:$C$76, MATCH(1, (Raw_Financials!$A$2:$A$76="Linde India")*(Raw_Financials!$B$2:$B$76="2024"),0)+1),"")=""),"",(IFERROR(INDEX(Raw_Financials!$M$2:$M$76, MATCH(1, (Raw_Financials!$A$2:$A$76="Linde India")*(Raw_Financials!$B$2:$B$76="2024"),0)+1),""))/(IFERROR(INDEX(Raw_Financials!$C$2:$C$76, MATCH(1, (Raw_Financials!$A$2:$A$76="Linde India")*(Raw_Financials!$B$2:$B$76="2024"),0)+1),"")))} -> 0.65724145 | K16: {=IF(OR(IFERROR(INDEX(Raw_ESG!$C$2:$C$76, MATCH(1, (Raw_ESG!$A$2:$A$76="Linde India")*(Raw_ESG!$B$2:$B$76="2024"),0)+1),"")="",IFERROR(INDEX(Raw_Financials!$J$2:$J$76, MATCH(1, (Raw_Financials!$A$2:$A$76="Linde India")*(Raw_Financials!$B$2:$B$76="2024"),0)+1),"")=""),"",(IFERROR(INDEX(Raw_ESG!$C$2:$C$76, MATCH(1, (Raw_ESG!$A$2:$A$76="Linde India")*(Raw_ESG!$B$2:$B$76="2024"),0)+1),""))/(IFERROR(INDEX(Raw_Financials!$J$2:$J$76, MATCH(1, (Raw_Financials!$A$2:$A$76="Linde India")*(Raw_Financials!$B$2:$B$76="2024"),0)+1),"")))} -> 0.31730034 | L16: {=IF(OR(IFERROR(INDEX(Raw_ESG!$D$2:$D$76, MATCH(1, (Raw_ESG!$A$2:$A$76="Linde India")*(Raw_ESG!$B$2:$B$76="2024"),0)+1),"")="",IFERROR(INDEX(Raw_Financials!$E$2:$E$76, MATCH(1, (Raw_Financials!$A$2:$A$76="Linde India")*(Raw_Financials!$B$2:$B$76="2024"),0)+1),"")=""),"",(IFERROR(INDEX(Raw_ESG!$D$2:$D$76, MATCH(1, (Raw_ESG!$A$2:$A$76="Linde India")*(Raw_ESG!$B$2:$B$76="2024"),0)+1),""))/(IFERROR(INDEX(Raw_Financials!$E$2:$E$76, MATCH(1, (Raw_Financials!$A$2:$A$76="Linde India")*(Raw_Financials!$B$2:$B$76="2024"),0)+1),"")))} -> 0.092501112 | M16: {=IF(OR(IFERROR(INDEX(Raw_ESG!$E$2:$E$76, MATCH(1, (Raw_ESG!$A$2:$A$76="Linde India")*(Raw_ESG!$B$2:$B$76="2024"),0)+1),"")="",IFERROR(INDEX(Raw_ESG!$F$2:$F$76, MATCH(1, (Raw_ESG!$A$2:$A$76="Linde India")*(Raw_ESG!$B$2:$B$76="2024"),0)+1),"")=""),"",(IFERROR(INDEX(Raw_ESG!$E$2:$E$76, MATCH(1, (Raw_ESG!$A$2:$A$76="Linde India")*(Raw_ESG!$B$2:$B$76="2024"),0)+1),""))+(IFERROR(INDEX(Raw_ESG!$F$2:$F$76, MATCH(1, (Raw_ESG!$A$2:$A$76="Linde India")*(Raw_ESG!$B$2:$B$76="2024"),0)+1),"")))} -> 205553.18 | N16: {=IFERROR(INDEX(Raw_ESG!$G$2:$G$76, MATCH(1, (Raw_ESG!$A$2:$A$76="Linde India")*(Raw_ESG!$B$2:$B$76="2024"),0)+1),"")} -> 74.8
A17: SRF Ltd | B17: 2020 | C17: {=IF(OR(IFERROR(INDEX(Raw_Financials!$E$2:$E$76, MATCH(1, (Raw_Financials!$A$2:$A$76="SRF Ltd")*(Raw_Financials!$B$2:$B$76="2020"),0)+1),"")="",IFERROR(INDEX(Raw_Financials!$D$2:$D$76, MATCH(1, (Raw_Financials!$A$2:$A$76="SRF Ltd")*(Raw_Financials!$B$2:$B$76="2020"),0)+1),"")=""),"",(IFERROR(INDEX(Raw_Financials!$D$2:$D$76, MATCH(1, (Raw_Financials!$A$2:$A$76="SRF Ltd")*(Raw_Financials!$B$2:$B$76="2020"),0)+1),""))/(IFERROR(INDEX(Raw_Financials!$E$2:$E$76, MATCH(1, (Raw_Financials!$A$2:$A$76="SRF Ltd")*(Raw_Financials!$B$2:$B$76="2020"),0)+1),"")))} -> 0.054805865 | D17: {=IF(OR(IFERROR(INDEX(Raw_Financials!$E$2:$E$76, MATCH(1, (Raw_Financials!$A$2:$A$76="SRF Ltd")*(Raw_Financials!$B$2:$B$76="2020"),0)+1),"")="",IFERROR(INDEX(Raw_Financials!$C$2:$C$76, MATCH(1, (Raw_Financials!$A$2:$A$76="SRF Ltd")*(Raw_Financials!$B$2:$B$76="2020"),0)+1),"")=""),"",(IFERROR(INDEX(Raw_Financials!$C$2:$C$76, MATCH(1, (Raw_Financials!$A$2:$A$76="SRF Ltd")*(Raw_Financials!$B$2:$B$76="2020"),0)+1),""))/(IFERROR(INDEX(Raw_Financials!$E$2:$E$76, MATCH(1, (Raw_Financials!$A$2:$A$76="SRF Ltd")*(Raw_Financials!$B$2:$B$76="2020"),0)+1),"")))} -> 0.33936317 | E17: {=IF(OR(IFERROR(INDEX(Raw_Financials!$G$2:$G$76, MATCH(1, (Raw_Financials!$A$2:$A$76="SRF Ltd")*(Raw_Financials!$B$2:$B$76="2020"),0)+1),"")="",IFERROR(INDEX(Raw_Financials!$H$2:$H$76, MATCH(1, (Raw_Financials!$A$2:$A$76="SRF Ltd")*(Raw_Financials!$B$2:$B$76="2020"),0)+1),"")=""),"",(IFERROR(INDEX(Raw_Financials!$G$2:$G$76, MATCH(1, (Raw_Financials!$A$2:$A$76="SRF Ltd")*(Raw_Financials!$B$2:$B$76="2020"),0)+1),""))-(IFERROR(INDEX(Raw_Financials!$H$2:$H$76, MATCH(1, (Raw_Financials!$A$2:$A$76="SRF Ltd")*(Raw_Financials!$B$2:$B$76="2020"),0)+1),"")))} -> -22231.3 | F17: {=IF(OR(IFERROR(INDEX(Raw_Financials!$C$2:$C$76, MATCH(1, (Raw_Financials!$A$2:$A$76="SRF Ltd")*(Raw_Financials!$B$2:$B$76="2020"),0)+1),"")="",IF(OR(IFERROR(INDEX(Raw_Financials!$G$2:$G$76, MATCH(1, (Raw_Financials!$A$2:$A$76="SRF Ltd")*(Raw_Financials!$B$2:$B$76="2020"),0)+1),"")="",IFERROR(INDEX(Raw_Financials!$H$2:$H$76, MATCH(1, (Raw_Financials!$A$2:$A$76="SRF Ltd")*(Raw_Financials!$B$2:$B$76="2020"),0)+1),"")=""),"",(IFERROR(INDEX(Raw_Financials!$G$2:$G$76, MATCH(1, (Raw_Financials!$A$2:$A$76="SRF Ltd")*(Raw_Financials!$B$2:$B$76="2020"),0)+1),""))-(IFERROR(INDEX(Raw_Financials!$H$2:$H$76, MATCH(1, (Raw_Financials!$A$2:$A$76="SRF Ltd")*(Raw_Financials!$B$2:$B$76="2020"),0)+1),"")))=""),"",(IFERROR(INDEX(Raw_Financials!$C$2:$C$76, MATCH(1, (Raw_Financials!$A$2:$A$76="SRF Ltd")*(Raw_Financials!$B$2:$B$76="2020"),0)+1),""))/(IF(OR(IFERROR(INDEX(Raw_Financials!$G$2:$G$76, MATCH(1, (Raw_Financials!$A$2:$A$76="SRF Ltd")*(Raw_Financials!$B$2:$B$76="2020"),0)+1),"")="",IFERROR(INDEX(Raw_Financials!$H$2:$H$76, MATCH(1, (Raw_Financials!$A$2:$A$76="SRF Ltd")*(Raw_Financials!$B$2:$B$76="2020"),0)+1),"")=""),"",(IFERROR(INDEX(Raw_Financials!$G$2:$G$76, MATCH(1, (Raw_Financials!$A$2:$A$76="SRF Ltd")*(Raw_Financials!$B$2:$B$76="2020"),0)+1),""))-(IFERROR(INDEX(Raw_Financials!$H$2:$H$76, MATCH(1, (Raw_Financials!$A$2:$A$76="SRF Ltd")*(Raw_Financials!$B$2:$B$76="2020"),0)+1),"")))))} -> -3.2397084 | G17: {=IF(OR(IFERROR(INDEX(Raw_Financials!$O$2:$O$76, MATCH(1, (Raw_Financials!$A$2:$A$76="SRF Ltd")*(Raw_Financials!$B$2:$B$76="2020"),0)+1),"")="",IFERROR(INDEX(Raw_Financials!$M$2:$M$76, MATCH(1, (Raw_Financials!$A$2:$A$76="SRF Ltd")*(Raw_Financials!$B$2:$B$76="2020"),0)+1),"")=""),"",(IFERROR(INDEX(Raw_Financials!$O$2:$O$76, MATCH(1, (Raw_Financials!$A$2:$A$76="SRF Ltd")*(Raw_Financials!$B$2:$B$76="2020"),0)+1),""))/(IFERROR(INDEX(Raw_Financials!$M$2:$M$76, MATCH(1, (Raw_Financials!$A$2:$A$76="SRF Ltd")*(Raw_Financials!$B$2:$B$76="2020"),0)+1),"")))} -> 4.2518041 | H17: {=IF(OR(IFERROR(INDEX(Raw_Financials!$M$2:$M$76, MATCH(1, (Raw_Financials!$A$2:$A$76="SRF Ltd")*(Raw_Financials!$B$2:$B$76="2020"),0)+1),"")="",IFERROR(INDEX(Raw_Financials!$L$2:$L$76, MATCH(1, (Raw_Financials!$A$2:$A$76="SRF Ltd")*(Raw_Financials!$B$2:$B$76="2020"),0)+1),"")=""),"",(IFERROR(INDEX(Raw_Financials!$M$2:$M$76, MATCH(1, (Raw_Financials!$A$2:$A$76="SRF Ltd")*(Raw_Financials!$B$2:$B$76="2020"),0)+1),""))/(IFERROR(INDEX(Raw_Financials!$L$2:$L$76, MATCH(1, (Raw_Financials!$A$2:$A$76="SRF Ltd")*(Raw_Financials!$B$2:$B$76="2020"),0)+1),"")))} -> 2.3486863 | I17: {=IF(OR(IFERROR(INDEX(Raw_Financials!$N$2:$N$76, MATCH(1, (Raw_Financials!$A$2:$A$76="SRF Ltd")*(Raw_Financials!$B$2:$B$76="2020"),0)+1),"")="",IFERROR(INDEX(Raw_Financials!$J$2:$J$76, MATCH(1, (Raw_Financials!$A$2:$A$76="SRF Ltd")*(Raw_Financials!$B$2:$B$76="2020"),0)+1),"")=""),"",(IFERROR(INDEX(Raw_Financials!$N$2:$N$76, MATCH(1, (Raw_Financials!$A$2:$A$76="SRF Ltd")*(Raw_Financials!$B$2:$B$76="2020"),0)+1),""))-(IFERROR(INDEX(Raw_Financials!$J$2:$J$76, MATCH(1, (Raw_Financials!$A$2:$A$76="SRF Ltd")*(Raw_Financials!$B$2:$B$76="2020"),0)+1),"")))} -> 7460.89 | J17: {=IF(OR(IFERROR(INDEX(Raw_Financials!$M$2:$M$76, MATCH(1, (Raw_Financials!$A$2:$A$76="SRF Ltd")*(Raw_Financials!$B$2:$B$76="2020"),0)+1),"")="",IFERROR(INDEX(Raw_Financials!$C$2:$C$76, MATCH(1, (Raw_Financials!$A$2:$A$76="SRF Ltd")*(Raw_Financials!$B$2:$B$76="2020"),0)+1),"")=""),"",(IFERROR(INDEX(Raw_Financials!$M$2:$M$76, MATCH(1, (Raw_Financials!$A$2:$A$76="SRF Ltd")*(Raw_Financials!$B$2:$B$76="2020"),0)+1),""))/(IFERROR(INDEX(Raw_Financials!$C$2:$C$76, MATCH(1, (Raw_Financials!$A$2:$A$76="SRF Ltd")*(Raw_Financials!$B$2:$B$76="2020"),0)+1),"")))} -> 0.22061002 | K17: {=IF(OR(IFERROR(INDEX(Raw_ESG!$C$2:$C$76, MATCH(1, (Raw_ESG!$A$2:$A$76="SRF Ltd")*(Raw_ESG!$B$2:$B$76="2020"),0)+1),"")="",IFERROR(INDEX(Raw_Financials!$J$2:$J$76, MATCH(1, (Raw_Financials!$A$2:$A$76="SRF Ltd")*(Raw_Financials!$B$2:$B$76="2020"),0)+1),"")=""),"",(IFERROR(INDEX(Raw_ESG!$C$2:$C$76, MATCH(1, (Raw_ESG!$A$2:$A$76="SRF Ltd")*(Raw_ESG!$B$2:$B$76="2020"),0)+1),""))/(IFERROR(INDEX(Raw_Financials!$J$2:$J$76, MATCH(1, (Raw_Financials!$A$2:$A$76="SRF Ltd")*(Raw_Financials!$B$2:$B$76="2020"),0)+1),"")))} -> 0.27417559 | L17: {=IF(OR(IFERROR(INDEX(Raw_ESG!$D$2:$D$76, MATCH(1, (Raw_ESG!$A$2:$A$76="SRF Ltd")*(Raw_ESG!$B$2:$B$76="2020"),0)+1),"")="",IFERROR(INDEX(Raw_Financials!$E$2:$E$76, MATCH(1, (Raw_Financials!$A$2:$A$76="SRF Ltd")*(Raw_Financials!$B$2:$B$76="2020"),0)+1),"")=""),"",(IFERROR(INDEX(Raw_ESG!$D$2:$D$76, MATCH(1, (Raw_ESG!$A$2:$A$76="SRF Ltd")*(Raw_ESG!$B$2:$B$76="2020"),0)+1),""))/(IFERROR(INDEX(Raw_Financials!$E$2:$E$76, MATCH(1, (Raw_Financials!$A$2:$A$76="SRF Ltd")*(Raw_Financials!$B$2:$B$76="2020"),0)+1),"")))} -> 0.11433322 | M17: {=IF(OR(IFERROR(INDEX(Raw_ESG!$E$2:$E$76, MATCH(1, (Raw_ESG!$A$2:$A$76="SRF Ltd")*(Raw_ESG!$B$2:$B$76="2020"),0)+1),"")="",IFERROR(INDEX(Raw_ESG!$F$2:$F$76, MATCH(1, (Raw_ESG!$A$2:$A$76="SRF Ltd")*(Raw_ESG!$B$2:$B$76="2020"),0)+1),"")=""),"",(IFERROR(INDEX(Raw_ESG!$E$2:$E$76, MATCH(1, (Raw_ESG!$A$2:$A$76="SRF Ltd")*(Raw_ESG!$B$2:$B$76="2020"),0)+1),""))+(IFERROR(INDEX(Raw_ESG!$F$2:$F$76, MATCH(1, (Raw_ESG!$A$2:$A$76="SRF Ltd")*(Raw_ESG!$B$2:$B$76="2020"),0)+1),"")))} -> 154774.44 | N17: {=IFERROR(INDEX(Raw_ESG!$G$2:$G$76, MATCH(1, (Raw_ESG!$A$2:$A$76="SRF Ltd")*(Raw_ESG!$B$2:$B$76="2020"),0)+1),"")} -> 60.45
A18: SRF Ltd | B18: 2021 | C18: {=IF(OR(IFERROR(INDEX(Raw_Financials!$E$2:$E$76, MATCH(1, (Raw_Financials!$A$2:$A$76="SRF Ltd")*(Raw_Financials!$B$2:$B$76="2021"),0)+1),"")="",IFERROR(INDEX(Raw_Financials!$D$2:$D$76, MATCH(1, (Raw_Financials!$A$2:$A$76="SRF Ltd")*(Raw_Financials!$B$2:$B$76="2021"),0)+1),"")=""),"",(IFERROR(INDEX(Raw_Financials!$D$2:$D$76, MATCH(1, (Raw_Financials!$A$2:$A$76="SRF Ltd")*(Raw_Financials!$B$2:$B$76="2021"),0)+1),""))/(IFERROR(INDEX(Raw_Financials!$E$2:$E$76, MATCH(1, (Raw_Financials!$A$2:$A$76="SRF Ltd")*(Raw_Financials!$B$2:$B$76="2021"),0)+1),"")))} -> 0.064040991 | D18: {=IF(OR(IFERROR(INDEX(Raw_Financials!$E$2:$E$76, MATCH(1, (Raw_Financials!$A$2:$A$76="SRF Ltd")*(Raw_Financials!$B$2:$B$76="2021"),0)+1),"")="",IFERROR(INDEX(Raw_Financials!$C$2:$C$76, MATCH(1, (Raw_Financials!$A$2:$A$76="SRF Ltd")*(Raw_Financials!$B$2:$B$76="2021"),0)+1),"")=""),"",(IFERROR(INDEX(Raw_Financials!$C$2:$C$76, MATCH(1, (Raw_Financials!$A$2:$A$76="SRF Ltd")*(Raw_Financials!$B$2:$B$76="2021"),0)+1),""))/(IFERROR(INDEX(Raw_Financials!$E$2:$E$76, MATCH(1, (Raw_Financials!$A$2:$A$76="SRF Ltd")*(Raw_Financials!$B$2:$B$76="2021"),0)+1),"")))} -> 0.29453034 | E18: {=IF(OR(IFERROR(INDEX(Raw_Financials!$G$2:$G$76, MATCH(1, (Raw_Financials!$A$2:$A$76="SRF Ltd")*(Raw_Financials!$B$2:$B$76="2021"),0)+1),"")="",IFERROR(INDEX(Raw_Financials!$H$2:$H$76, MATCH(1, (Raw_Financials!$A$2:$A$76="SRF Ltd")*(Raw_Financials!$B$2:$B$76="2021"),0)+1),"")=""),"",(IFERROR(INDEX(Raw_Financials!$G$2:$G$76, MATCH(1, (Raw_Financials!$A$2:$A$76="SRF Ltd")*(Raw_Financials!$B$2:$B$76="2021"),0)+1),""))-(IFERROR(INDEX(Raw_Financials!$H$2:$H$76, MATCH(1, (Raw_Financials!$A$2:$A$76="SRF Ltd")*(Raw_Financials!$B$2:$B$76="2021"),0)+1),"")))} -> -9563.16 | F18: {=IF(OR(IFERROR(INDEX(Raw_Financials!$C$2:$C$76, MATCH(1, (Raw_Financials!$A$2:$A$76="SRF Ltd")*(Raw_Financials!$B$2:$B$76="2021"),0)+1),"")="",IF(OR(IFERROR(INDEX(Raw_Financials!$G$2:$G$76, MATCH(1, (Raw_Financials!$A$2:$A$76="SRF Ltd")*(Raw_Financials!$B$2:$B$76="2021"),0)+1),"")="",IFERROR(INDEX(Raw_Financials!$H$2:$H$76, MATCH(1, (Raw_Financials!$A$2:$A$76="SRF Ltd")*(Raw_Financials!$B$2:$B$76="2021"),0)+1),"")=""),"",(IFERROR(INDEX(Raw_Financials!$G$2:$G$76, MATCH(1, (Raw_Financials!$A$2:$A$76="SRF Ltd")*(Raw_Financials!$B$2:$B$76="2021"),0)+1),""))-(IFERROR(INDEX(Raw_Financials!$H$2:$H$76, MATCH(1, (Raw_Financials!$A$2:$A$76="SRF Ltd")*(Raw_Financials!$B$2:$B$76="2021"),0)+1),"")))=""),"",(IFERROR(INDEX(Raw_Financials!$C$2:$C$76, MATCH(1, (Raw_Financials!$A$2:$A$76="SRF Ltd")*(Raw_Financials!$B$2:$B$76="2021"),0)+1),""))/(IF(OR(IFERROR(INDEX(Raw_Financials!$G$2:$G$76, MATCH(1, (Raw_Financials!$A$2:$A$76="SRF Ltd")*(Raw_Financials!$B$2:$B$76="2021"),0)+1),"")="",IFERROR(INDEX(Raw_Financials!$H$2:$H$76, MATCH(1, (Raw_Financials!$A$2:$A$76="SRF Ltd")*(Raw_Financials!$B$2:$B$76="2021"),0)+1),"")=""),"",(IFERROR(INDEX(Raw_Financials!$G$2:$G$76, MATCH(1, (Raw_Financials!$A$2:$A$76="SRF Ltd")*(Raw_Financials!$B$2:$B$76="2021"),0)+1),""))-(IFERROR(INDEX(Raw_Financials!$H$2:$H$76, MATCH(1, (Raw_Financials!$A$2:$A$76="SRF Ltd")*(Raw_Financials!$B$2:$B$76="2021"),0)+1),"")))))} -> -5.5253765 | G18: {=IF(OR(IFERROR(INDEX(Raw_Financials!$O$2:$O$76, MATCH(1, (Raw_Financials!$A$2:$A$76="SRF Ltd")*(Raw_Financials!$B$2:$B$76="2021"),0)+1),"")="",IFERROR(INDEX(Raw_Financials!$M$2:$M$76, MATCH(1, (Raw_Financials!$A$2:$A$76="SRF Ltd")*(Raw_Financials!$B$2:$B$76="2021"),0)+1),"")=""),"",(IFERROR(INDEX(Raw_Financials!$O$2:$O$76, MATCH(1, (Raw_Financials!$A$2:$A$76="SRF Ltd")*(Raw_Financials!$B$2:$B$76="2021"),0)+1),""))/(IFERROR(INDEX(Raw_Financials!$M$2:$M$76, MATCH(1, (Raw_Financials!$A$2:$A$76="SRF Ltd")*(Raw_Financials!$B$2:$B$76="2021"),0)+1),"")))} -> 2.4228613 | H18: {=IF(OR(IFERROR(INDEX(Raw_Financials!$M$2:$M$76, MATCH(1, (Raw_Financials!$A$2:$A$76="SRF Ltd")*(Raw_Financials!$B$2:$B$76="2021"),0)+1),"")="",IFERROR(INDEX(Raw_Financials!$L$2:$L$76, MATCH(1, (Raw_Financials!$A$2:$A$76="SRF Ltd")*(Raw_Financials!$B$2:$B$76="2021"),0)+1),"")=""),"",(IFERROR(INDEX(Raw_Financials!$M$2:$M$76, MATCH(1, (Raw_Financials!$A$2:$A$76="SRF Ltd")*(Raw_Financials!$B$2:$B$76="2021"),0)+1),""))/(IFERROR(INDEX(Raw_Financials!$L$2:$L$76, MATCH(1, (Raw_Financials!$A$2:$A$76="SRF Ltd")*(Raw_Financials!$B$2:$B$76="2021"),0)+1),"")))} -> 3.6032871 | I18: {=IF(OR(IFERROR(INDEX(Raw_Financials!$N$2:$N$76, MATCH(1, (Raw_Financials!$A$2:$A$76="SRF Ltd")*(Raw_Financials!$B$2:$B$76="2021"),0)+1),"")="",IFERROR(INDEX(Raw_Financials!$J$2:$J$76, MATCH(1, (Raw_Financials!$A$2:$A$76="SRF Ltd")*(Raw_Financials!$B$2:$B$76="2021"),0)+1),"")=""),"",(IFERROR(INDEX(Raw_Financials!$N$2:$N$76, MATCH(1, (Raw_Financials!$A$2:$A$76="SRF Ltd")*(Raw_Financials!$B$2:$B$76="2021"),0)+1),""))-(IFERROR(INDEX(Raw_Financials!$J$2:$J$76, MATCH(1, (Raw_Financials!$A$2:$A$76="SRF Ltd")*(Raw_Financials!$B$2:$B$76="2021"),0)+1),"")))} -> 23524.55 | J18: {=IF(OR(IFERROR(INDEX(Raw_Financials!$M$2:$M$76, MATCH(1, (Raw_Financials!$A$2:$A$76="SRF Ltd")*(Raw_Financials!$B$2:$B$76="2021"),0)+1),"")="",IFERROR(INDEX(Raw_Financials!$C$2:$C$76, MATCH(1, (Raw_Financials!$A$2:$A$76="SRF Ltd")*(Raw_Financials!$B$2:$B$76="2021"),0)+1),"")=""),"",(IFERROR(INDEX(Raw_Financials!$M$2:$M$76, MATCH(1, (Raw_Financials!$A$2:$A$76="SRF Ltd")*(Raw_Financials!$B$2:$B$76="2021"),0)+1),""))/(IFERROR(INDEX(Raw_Financials!$C$2:$C$76, MATCH(1, (Raw_Financials!$A$2:$A$76="SRF Ltd")*(Raw_Financials!$B$2:$B$76="2021"),0)+1),"")))} -> 0.46963175 | K18: {=IF(OR(IFERROR(INDEX(Raw_ESG!$C$2:$C$76, MATCH(1, (Raw_ESG!$A$2:$A$76="SRF Ltd")*(Raw_ESG!$B$2:$B$76="2021"),0)+1),"")="",IFERROR(INDEX(Raw_Financials!$J$2:$J$76, MATCH(1, (Raw_Financials!$A$2:$A$76="SRF Ltd")*(Raw_Financials!$B$2:$B$76="2021"),0)+1),"")=""),"",(IFERROR(INDEX(Raw_ESG!$C$2:$C$76, MATCH(1, (Raw_ESG!$A$2:$A$76="SRF Ltd")*(Raw_ESG!$B$2:$B$76="2021"),0)+1),""))/(IFERROR(INDEX(Raw_Financials!$J$2:$J$76, MATCH(1, (Raw_Financials!$A$2:$A$76="SRF Ltd")*(Raw_Financials!$B$2:$B$76="2021"),0)+1),"")))} -> 0.80048556 | L18: {=IF(OR(IFERROR(INDEX(Raw_ESG!$D$2:$D$76, MATCH(1, (Raw_ESG!$A$2:$A$76="SRF Ltd")*(Raw_ESG!$B$2:$B$76="2021"),0)+1),"")="",IFERROR(INDEX(Raw_Financials!$E$2:$E$76, MATCH(1, (Raw_Financials!$A$2:$A$76="SRF Ltd")*(Raw_Financials!$B$2:$B$76="2021"),0)+1),"")=""),"",(IFERROR(INDEX(Raw_ESG!$D$2:$D$76, MATCH(1, (Raw_ESG!$A$2:$A$76="SRF Ltd")*(Raw_ESG!$B$2:$B$76="2021"),0)+1),""))/(IFERROR(INDEX(Raw_Financials!$E$2:$E$76, MATCH(1, (Raw_Financials!$A$2:$A$76="SRF Ltd")*(Raw_Financials!$B$2:$B$76="2021"),0)+1),"")))} -> 0.14055224 | M18: {=IF(OR(IFERROR(INDEX(Raw_ESG!$E$2:$E$76, MATCH(1, (Raw_ESG!$A$2:$A$76="SRF Ltd")*(Raw_ESG!$B$2:$B$76="2021"),0)+1),"")="",IFERROR(INDEX(Raw_ESG!$F$2:$F$76, MATCH(1, (Raw_ESG!$A$2:$A$76="SRF Ltd")*(Raw_ESG!$B$2:$B$76="2021"),0)+1),"")=""),"",(IFERROR(INDEX(Raw_ESG!$E$2:$E$76, MATCH(1, (Raw_ESG!$A$2:$A$76="SRF Ltd")*(Raw_ESG!$B$2:$B$76="2021"),0)+1),""))+(IFERROR(INDEX(Raw_ESG!$F$2:$F$76, MATCH(1, (Raw_ESG!$A$2:$A$76="SRF Ltd")*(Raw_ESG!$B$2:$B$76="2021"),0)+1),"")))} -> 139395.07 | N18: {=IFERROR(INDEX(Raw_ESG!$G$2:$G$76, MATCH(1, (Raw_ESG!$A$2:$A$76="SRF Ltd")*(Raw_ESG!$B$2:$B$76="2021"),0)+1),"")} -> 48.66
A19: SRF Ltd | B19: 2022 | C19: {=IF(OR(IFERROR(INDEX(Raw_Financials!$E$2:$E$76, MATCH(1, (Raw_Financials!$A$2:$A$76="SRF Ltd")*(Raw_Financials!$B$2:$B$76="2022"),0)+1),"")="",IFERROR(INDEX(Raw_Financials!$D$2:$D$76, MATCH(1, (Raw_Financials!$A$2:$A$76="SRF Ltd")*(Raw_Financials!$B$2:$B$76="2022"),0)+1),"")=""),"",(IFERROR(INDEX(Raw_Financials!$D$2:$D$76, MATCH(1, (Raw_Financials!$A$2:$A$76="SRF Ltd")*(Raw_Financials!$B$2:$B$76="2022"),0)+1),""))/(IFERROR(INDEX(Raw_Financials!$E$2:$E$76, MATCH(1, (Raw_Financials!$A$2:$A$76="SRF Ltd")*(Raw_Financials!$B$2:$B$76="2022"),0)+1),"")))} -> 0.051111219 | D19: {=IF(OR(IFERROR(INDEX(Raw_Financials!$E$2:$E$76, MATCH(1, (Raw_Financials!$A$2:$A$76="SRF Ltd")*(Raw_Financials!$B$2:$B$76="2022"),0)+1),"")="",IFERROR(INDEX(Raw_Financials!$C$2:$C$76, MATCH(1, (Raw_Financials!$A$2:$A$76="SRF Ltd")*(Raw_Financials!$B$2:$B$76="2022"),0)+1),"")=""),"",(IFERROR(INDEX(Raw_Financials!$C$2:$C$76, MATCH(1, (Raw_Financials!$A$2:$A$76="SRF Ltd")*(Raw_Financials!$B$2:$B$76="2022"),0)+1),""))/(IFERROR(INDEX(Raw_Financials!$E$2:$E$76, MATCH(1, (Raw_Financials!$A$2:$A$76="SRF Ltd")*(Raw_Financials!$B$2:$B$76="2022"),0)+1),"")))} -> 0.31926162 | E19: {=IF(OR(IFERROR(INDEX(Raw_Financials!$G$2:$G$76, MATCH(1, (Raw_Financials!$A$2:$A$76="SRF Ltd")*(Raw_Financials!$B$2:$B$76="2022"),0)+1),"")="",IFERROR(INDEX(Raw_Financials!$H$2:$H$76, MATCH(1, (Raw_Financials!$A$2:$A$76="SRF Ltd")*(Raw_Financials!$B$2:$B$76="2022"),0)+1),"")=""),"",(IFERROR(INDEX(Raw_Financials!$G$2:$G$76, MATCH(1, (Raw_Financials!$A$2:$A$76="SRF Ltd")*(Raw_Financials!$B$2:$B$76="2022"),0)+1),""))-(IFERROR(INDEX(Raw_Financials!$H$2:$H$76, MATCH(1, (Raw_Financials!$A$2:$A$76="SRF Ltd")*(Raw_Financials!$B$2:$B$76="2022"),0)+1),"")))} -> 10408.21 | F19: {=IF(OR(IFERROR(INDEX(Raw_Financials!$C$2:$C$76, MATCH(1, (Raw_Financials!$A$2:$A$76="SRF Ltd")*(Raw_Financials!$B$2:$B$76="2022"),0)+1),"")="",IF(OR(IFERROR(INDEX(Raw_Financials!$G$2:$G$76, MATCH(1, (Raw_Financials!$A$2:$A$76="SRF Ltd")*(Raw_Financials!$B$2:$B$76="2022"),0)+1),"")="",IFERROR(INDEX(Raw_Financials!$H$2:$H$76, MATCH(1, (Raw_Financials!$A$2:$A$76="SRF Ltd")*(Raw_Financials!$B$2:$B$76="2022"),0)+1),"")=""),"",(IFERROR(INDEX(Raw_Financials!$G$2:$G$76, MATCH(1, (Raw_Financials!$A$2:$A$76="SRF Ltd")*(Raw_Financials!$B$2:$B$76="2022"),0)+1),""))-(IFERROR(INDEX(Raw_Financials!$H$2:$H$76, MATCH(1, (Raw_Financials!$A$2:$A$76="SRF Ltd")*(Raw_Financials!$B$2:$B$76="2022"),0)+1),"")))=""),"",(IFERROR(INDEX(Raw_Financials!$C$2:$C$76, MATCH(1, (Raw_Financials!$A$2:$A$76="SRF Ltd")*(Raw_Financials!$B$2:$B$76="2022"),0)+1),""))/(IF(OR(IFERROR(INDEX(Raw_Financials!$G$2:$G$76, MATCH(1, (Raw_Financials!$A$2:$A$76="SRF Ltd")*(Raw_Financials!$B$2:$B$76="2022"),0)+1),"")="",IFERROR(INDEX(Raw_Financials!$H$2:$H$76, MATCH(1, (Raw_Financials!$A$2:$A$76="SRF Ltd")*(Raw_Financials!$B$2:$B$76="2022"),0)+1),"")=""),"",(IFERROR(INDEX(Raw_Financials!$G$2:$G$76, MATCH(1, (Raw_Financials!$A$2:$A$76="SRF Ltd")*(Raw_Financials!$B$2:$B$76="2022"),0)+1),""))-(IFERROR(INDEX(Raw_Financials!$H$2:$H$76, MATCH(1, (Raw_Financials!$A$2:$A$76="SRF Ltd")*(Raw_Financials!$B$2:$B$76="2022"),0)+1),"")))))} -> 6.2900403 | G19: {=IF(OR(IFERROR(INDEX(Raw_Financials!$O$2:$O$76, MATCH(1, (Raw_Financials!$A$2:$A$76="SRF Ltd")*(Raw_Financials!$B$2:$B$76="2022"),0)+1),"")="",IFERROR(INDEX(Raw_Financials!$M$2:$M$76, MATCH(1, (Raw_Financials!$A$2:$A$76="SRF Ltd")*(Raw_Financials!$B$2:$B$76="2022"),0)+1),"")=""),"",(IFERROR(INDEX(Raw_Financials!$O$2:$O$76, MATCH(1, (Raw_Financials!$A$2:$A$76="SRF Ltd")*(Raw_Financials!$B$2:$B$76="2022"),0)+1),""))/(IFERROR(INDEX(Raw_Financials!$M$2:$M$76, MATCH(1, (Raw_Financials!$A$2:$A$76="SRF Ltd")*(Raw_Financials!$B$2:$B$76="2022"),0)+1),"")))} -> 1.5747833 | H19: {=IF(OR(IFERROR(INDEX(Raw_Financials!$M$2:$M$76, MATCH(1, (Raw_Financials!$A$2:$A$76="SRF Ltd")*(Raw_Financials!$B$2:$B$76="2022"),0)+1),"")="",IFERROR(INDEX(Raw_Financials!$L$2:$L$76, MATCH(1, (Raw_Financials!$A$2:$A$76="SRF Ltd")*(Raw_Financials!$B$2:$B$76="2022"),0)+1),"")=""),"",(IFERROR(INDEX(Raw_Financials!$M$2:$M$76, MATCH(1, (Raw_Financials!$A$2:$A$76="SRF Ltd")*(Raw_Financials!$B$2:$B$76="2022"),0)+1),""))/(IFERROR(INDEX(Raw_Financials!$L$2:$L$76, MATCH(1, (Raw_Financials!$A$2:$A$76="SRF Ltd")*(Raw_Financials!$B$2:$B$76="2022"),0)+1),"")))} -> 4.2908291 | I19: {=IF(OR(IFERROR(INDEX(Raw_Financials!$N$2:$N$76, MATCH(1, (Raw_Financials!$A$2:$A$76="SRF Ltd")*(Raw_Financials!$B$2:$B$76="2022"),0)+1),"")="",IFERROR(INDEX(Raw_Financials!$J$2:$J$76, MATCH(1, (Raw_Financials!$A$2:$A$76="SRF Ltd")*(Raw_Financials!$B$2:$B$76="2022"),0)+1),"")=""),"",(IFERROR(INDEX(Raw_Financials!$N$2:$N$76, MATCH(1, (Raw_Financials!$A$2:$A$76="SRF Ltd")*(Raw_Financials!$B$2:$B$76="2022"),0)+1),""))-(IFERROR(INDEX(Raw_Financials!$J$2:$J$76, MATCH(1, (Raw_Financials!$A$2:$A$76="SRF Ltd")*(Raw_Financials!$B$2:$B$76="2022"),0)+1),"")))} -> 9450.24 | J19: {=IF(OR(IFERROR(INDEX(Raw_Financials!$M$2:$M$76, MATCH(1, (Raw_Financials!$A$2:$A$76="SRF Ltd")*(Raw_Financials!$B$2:$B$76="2022"),0)+1),"")="",IFERROR(INDEX(Raw_Financials!$C$2:$C$76, MATCH(1, (Raw_Financials!$A$2:$A$76="SRF Ltd")*(Raw_Financials!$B$2:$B$76="2022"),0)+1),"")=""),"",(IFERROR(INDEX(Raw_Financials!$M$2:$M$76, MATCH(1, (Raw_Financials!$A$2:$A$76="SRF Ltd")*(Raw_Financials!$B$2:$B$76="2022"),0)+1),""))/(IFERROR(INDEX(Raw_Financials!$C$2:$C$76, MATCH(1, (Raw_Financials!$A$2:$A$76="SRF Ltd")*(Raw_Financials!$B$2:$B$76="2022"),0)+1),"")))} -> 0.42463623 | K19: {=IF(OR(IFERROR(INDEX(Raw_ESG!$C$2:$C$76, MATCH(1, (Raw_ESG!$A$2:$A$76="SRF Ltd")*(Raw_ESG!$B$2:$B$76="2022"),0)+1),"")="",IFERROR(INDEX(Raw_Financials!$J$2:$J$76, MATCH(1, (Raw_Financials!$A$2:$A$76="SRF Ltd")*(Raw_Financials!$B$2:$B$76="2022"),0)+1),"")=""),"",(IFERROR(INDEX(Raw_ESG!$C$2:$C$76, MATCH(1, (Raw_ESG!$A$2:$A$76="SRF Ltd")*(Raw_ESG!$B$2:$B$76="2022"),0)+1),""))/(IFERROR(INDEX(Raw_Financials!$J$2:$J$76, MATCH(1, (Raw_Financials!$A$2:$A$76="SRF Ltd")*(Raw_Financials!$B$2:$B$76="2022"),0)+1),"")))} -> 0.4052066 | L19: {=IF(OR(IFERROR(INDEX(Raw_ESG!$D$2:$D$76, MATCH(1, (Raw_ESG!$A$2:$A$76="SRF Ltd")*(Raw_ESG!$B$2:$B$76="2022"),0)+1),"")="",IFERROR(INDEX(Raw_Financials!$E$2:$E$76, MATCH(1, (Raw_Financials!$A$2:$A$76="SRF Ltd")*(Raw_Financials!$B$2:$B$76="2022"),0)+1),"")=""),"",(IFERROR(INDEX(Raw_ESG!$D$2:$D$76, MATCH(1, (Raw_ESG!$A$2:$A$76="SRF Ltd")*(Raw_ESG!$B$2:$B$76="2022"),0)+1),""))/(IFERROR(INDEX(Raw_Financials!$E$2:$E$76, MATCH(1, (Raw_Financials!$A$2:$A$76="SRF Ltd")*(Raw_Financials!$B$2:$B$76="2022"),0)+1),"")))} -> 0.1035085 | M19: {=IF(OR(IFERROR(INDEX(Raw_ESG!$E$2:$E$76, MATCH(1, (Raw_ESG!$A$2:$A$76="SRF Ltd")*(Raw_ESG!$B$2:$B$76="2022"),0)+1),"")="",IFERROR(INDEX(Raw_ESG!$F$2:$F$76, MATCH(1, (Raw_ESG!$A$2:$A$76="SRF Ltd")*(Raw_ESG!$B$2:$B$76="2022"),0)+1),"")=""),"",(IFERROR(INDEX(Raw_ESG!$E$2:$E$76, MATCH(1, (Raw_ESG!$A$2:$A$76="SRF Ltd")*(Raw_ESG!$B$2:$B$76="2022"),0)+1),""))+(IFERROR(INDEX(Raw_ESG!$F$2:$F$76, MATCH(1, (Raw_ESG!$A$2:$A$76="SRF Ltd")*(Raw_ESG!$B$2:$B$76="2022"),0)+1),"")))} -> 97585.45 | N19: {=IFERROR(INDEX(Raw_ESG!$G$2:$G$76, MATCH(1, (Raw_ESG!$A$2:$A$76="SRF Ltd")*(Raw_ESG!$B$2:$B$76="2022"),0)+1),"")} -> 47.82
A20: SRF Ltd | B20: 2023 | C20: {=IF(OR(IFERROR(INDEX(Raw_Financials!$E$2:$E$76, MATCH(1, (Raw_Financials!$A$2:$A$76="SRF Ltd")*(Raw_Financials!$B$2:$B$76="2023"),0)+1),"")="",IFERROR(INDEX(Raw_Financials!$D$2:$D$76, MATCH(1, (Raw_Financials!$A$2:$A$76="SRF Ltd")*(Raw_Financials!$B$2:$B$76="2023"),0)+1),"")=""),"",(IFERROR(INDEX(Raw_Financials!$D$2:$D$76, MATCH(1, (Raw_Financials!$A$2:$A$76="SRF Ltd")*(Raw_Financials!$B$2:$B$76="2023"),0)+1),""))/(IFERROR(INDEX(Raw_Financials!$E$2:$E$76, MATCH(1, (Raw_Financials!$A$2:$A$76="SRF Ltd")*(Raw_Financials!$B$2:$B$76="2023"),0)+1),"")))} -> 0.049392219 | D20: {=IF(OR(IFERROR(INDEX(Raw_Financials!$E$2:$E$76, MATCH(1, (Raw_Financials!$A$2:$A$76="SRF Ltd")*(Raw_Financials!$B$2:$B$76="2023"),0)+1),"")="",IFERROR(INDEX(Raw_Financials!$C$2:$C$76, MATCH(1, (Raw_Financials!$A$2:$A$76="SRF Ltd")*(Raw_Financials!$B$2:$B$76="2023"),0)+1),"")=""),"",(IFERROR(INDEX(Raw_Financials!$C$2:$C$76, MATCH(1, (Raw_Financials!$A$2:$A$76="SRF Ltd")*(Raw_Financials!$B$2:$B$76="2023"),0)+1),""))/(IFERROR(INDEX(Raw_Financials!$E$2:$E$76, MATCH(1, (Raw_Financials!$A$2:$A$76="SRF Ltd")*(Raw_Financials!$B$2:$B$76="2023"),0)+1),"")))} -> 0.17134064 | E20: {=IF(OR(IFERROR(INDEX(Raw_Financials!$G$2:$G$76, MATCH(1, (Raw_Financials!$A$2:$A$76="SRF Ltd")*(Raw_Financials!$B$2:$B$76="2023"),0)+1),"")="",IFERROR(INDEX(Raw_Financials!$H$2:$H$76, MATCH(1, (Raw_Financials!$A$2:$A$76="SRF Ltd")*(Raw_Financials!$B$2:$B$76="2023"),0)+1),"")=""),"",(IFERROR(INDEX(Raw_Financials!$G$2:$G$76, MATCH(1, (Raw_Financials!$A$2:$A$76="SRF Ltd")*(Raw_Financials!$B$2:$B$76="2023"),0)+1),""))-(IFERROR(INDEX(Raw_Financials!$H$2:$H$76, MATCH(1, (Raw_Financials!$A$2:$A$76="SRF Ltd")*(Raw_Financials!$B$2:$B$76="2023"),0)+1),"")))} -> 27718.32 | F20: {=IF(OR(IFERROR(INDEX(Raw_Financials!$C$2:$C$76, MATCH(1, (Raw_Financials!$A$2:$A$76="SRF Ltd")*(Raw_Financials!$B$2:$B$76="2023"),0)+1),"")="",IF(OR(IFERROR(INDEX(Raw_Financials!$G$2:$G$76, MATCH(1, (Raw_Financials!$A$2:$A$76="SRF Ltd")*(Raw_Financials!$B$2:$B$76="2023"),0)+1),"")="",IFERROR(INDEX(Raw_Financials!$H$2:$H$76, MATCH(1, (Raw_Financials!$A$2:$A$76="SRF Ltd")*(Raw_Financials!$B$2:$B$76="2023"),0)+1),"")=""),"",(IFERROR(INDEX(Raw_Financials!$G$2:$G$76, MATCH(1, (Raw_Financials!$A$2:$A$76="SRF Ltd")*(Raw_Financials!$B$2:$B$76="2023"),0)+1),""))-(IFERROR(INDEX(Raw_Financials!$H$2:$H$76, MATCH(1, (Raw_Financials!$A$2:$A$76="SRF Ltd")*(Raw_Financials!$B$2:$B$76="2023"),0)+1),"")))=""),"",(IFERROR(INDEX(Raw_Financials!$C$2:$C$76, MATCH(1, (Raw_Financials!$A$2:$A$76="SRF Ltd")*(Raw_Financials!$B$2:$B$76="2023"),0)+1),""))/(IF(OR(IFERROR(INDEX(Raw_Financials!$G$2:$G$76, MATCH(1, (Raw_Financials!$A$2:$A$76="SRF Ltd")*(Raw_Financials!$B$2:$B$76="2023"),0)+1),"")="",IFERROR(INDEX(Raw_Financials!$H$2:$H$76, MATCH(1, (Raw_Financials!$A$2:$A$76="SRF Ltd")*(Raw_Financials!$B$2:$B$76="2023"),0)+1),"")=""),"",(IFERROR(INDEX(Raw_Financials!$G$2:$G$76, MATCH(1, (Raw_Financials!$A$2:$A$76="SRF Ltd")*(Raw_Financials!$B$2:$B$76="2023"),0)+1),""))-(IFERROR(INDEX(Raw_Financials!$H$2:$H$76, MATCH(1, (Raw_Financials!$A$2:$A$76="SRF Ltd")*(Raw_Financials!$B$2:$B$76="2023"),0)+1),"")))))} -> 0.9667653 | G20: {=IF(OR(IFERROR(INDEX(Raw_Financials!$O$2:$O$76, MATCH(1, (Raw_Financials!$A$2:$A$76="SRF Ltd")*(Raw_Financials!$B$2:$B$76="2023"),0)+1),"")="",IFERROR(INDEX(Raw_Financials!$M$2:$M$76, MATCH(1, (Raw_Financials!$A$2:$A$76="SRF Ltd")*(Raw_Financials!$B$2:$B$76="2023"),0)+1),"")=""),"",(IFERROR(INDEX(Raw_Financials!$O$2:$O$76, MATCH(1, (Raw_Financials!$A$2:$A$76="SRF Ltd")*(Raw_Financials!$B$2:$B$76="2023"),0)+1),""))/(IFERROR(INDEX(Raw_Financials!$M$2:$M$76, MATCH(1, (Raw_Financials!$A$2:$A$76="SRF Ltd")*(Raw_Financials!$B$2:$B$76="2023"),0)+1),"")))} -> 1.7506127 | H20: {=IF(OR(IFERROR(INDEX(Raw_Financials!$M$2:$M$76, MATCH(1, (Raw_Financials!$A$2:$A$76="SRF Ltd")*(Raw_Financials!$B$2:$B$76="2023"),0)+1),"")="",IFERROR(INDEX(Raw_Financials!$L$2:$L$76, MATCH(1, (Raw_Financials!$A$2:$A$76="SRF Ltd")*(Raw_Financials!$B$2:$B$76="2023"),0)+1),"")=""),"",(IFERROR(INDEX(Raw_Financials!$M$2:$M$76, MATCH(1, (Raw_Financials!$A$2:$A$76="SRF Ltd")*(Raw_Financials!$B$2:$B$76="2023"),0)+1),""))/(IFERROR(INDEX(Raw_Financials!$L$2:$L$76, MATCH(1, (Raw_Financials!$A$2:$A$76="SRF Ltd")*(Raw_Financials!$B$2:$B$76="2023"),0)+1),"")))} -> 6.5208656 | I20: {=IF(OR(IFERROR(INDEX(Raw_Financials!$N$2:$N$76, MATCH(1, (Raw_Financials!$A$2:$A$76="SRF Ltd")*(Raw_Financials!$B$2:$B$76="2023"),0)+1),"")="",IFERROR(INDEX(Raw_Financials!$J$2:$J$76, MATCH(1, (Raw_Financials!$A$2:$A$76="SRF Ltd")*(Raw_Financials!$B$2:$B$76="2023"),0)+1),"")=""),"",(IFERROR(INDEX(Raw_Financials!$N$2:$N$76, MATCH(1, (Raw_Financials!$A$2:$A$76="SRF Ltd")*(Raw_Financials!$B$2:$B$76="2023"),0)+1),""))-(IFERROR(INDEX(Raw_Financials!$J$2:$J$76, MATCH(1, (Raw_Financials!$A$2:$A$76="SRF Ltd")*(Raw_Financials!$B$2:$B$76="2023"),0)+1),"")))} -> 18523.83 | J20: {=IF(OR(IFERROR(INDEX(Raw_Financials!$M$2:$M$76, MATCH(1, (Raw_Financials!$A$2:$A$76="SRF Ltd")*(Raw_Financials!$B$2:$B$76="2023"),0)+1),"")="",IFERROR(INDEX(Raw_Financials!$C$2:$C$76, MATCH(1, (Raw_Financials!$A$2:$A$76="SRF Ltd")*(Raw_Financials!$B$2:$B$76="2023"),0)+1),"")=""),"",(IFERROR(INDEX(Raw_Financials!$M$2:$M$76, MATCH(1, (Raw_Financials!$A$2:$A$76="SRF Ltd")*(Raw_Financials!$B$2:$B$76="2023"),0)+1),""))/(IFERROR(INDEX(Raw_Financials!$C$2:$C$76, MATCH(1, (Raw_Financials!$A$2:$A$76="SRF Ltd")*(Raw_Financials!$B$2:$B$76="2023"),0)+1),"")))} -> 0.76295056 | K20: {=IF(OR(IFERROR(INDEX(Raw_ESG!$C$2:$C$76, MATCH(1, (Raw_ESG!$A$2:$A$76="SRF Ltd")*(Raw_ESG!$B$2:$B$76="2023"),0)+1),"")="",IFERROR(INDEX(Raw_Financials!$J$2:$J$76, MATCH(1, (Raw_Financials!$A$2:$A$76="SRF Ltd")*(Raw_Financials!$B$2:$B$76="2023"),0)+1),"")=""),"",(IFERROR(INDEX(Raw_ESG!$C$2:$C$76, MATCH(1, (Raw_ESG!$A$2:$A$76="SRF Ltd")*(Raw_ESG!$B$2:$B$76="2023"),0)+1),""))/(IFERROR(INDEX(Raw_Financials!$J$2:$J$76, MATCH(1, (Raw_Financials!$A$2:$A$76="SRF Ltd")*(Raw_Financials!$B$2:$B$76="2023"),0)+1),"")))} -> 0.29911893 | L20: {=IF(OR(IFERROR(INDEX(Raw_ESG!$D$2:$D$76, MATCH(1, (Raw_ESG!$A$2:$A$76="SRF Ltd")*(Raw_ESG!$B$2:$B$76="2023"),0)+1),"")="",IFERROR(INDEX(Raw_Financials!$E$2:$E$76, MATCH(1, (Raw_Financials!$A$2:$A$76="SRF Ltd")*(Raw_Financials!$B$2:$B$76="2023"),0)+1),"")=""),"",(IFERROR(INDEX(Raw_ESG!$D$2:$D$76, MATCH(1, (Raw_ESG!$A$2:$A$76="SRF Ltd")*(Raw_ESG!$B$2:$B$76="2023"),0)+1),""))/(IFERROR(INDEX(Raw_Financials!$E$2:$E$76, MATCH(1, (Raw_Financials!$A$2:$A$76="SRF Ltd")*(Raw_Financials!$B$2:$B$76="2023"),0)+1),"")))} -> 0.16253118 | M20: {=IF(OR(IFERROR(INDEX(Raw_ESG!$E$2:$E$76, MATCH(1, (Raw_ESG!$A$2:$A$76="SRF Ltd")*(Raw_ESG!$B$2:$B$76="2023"),0)+1),"")="",IFERROR(INDEX(Raw_ESG!$F$2:$F$76, MATCH(1, (Raw_ESG!$A$2:$A$76="SRF Ltd")*(Raw_ESG!$B$2:$B$76="2023"),0)+1),"")=""),"",(IFERROR(INDEX(Raw_ESG!$E$2:$E$76, MATCH(1, (Raw_ESG!$A$2:$A$76="SRF Ltd")*(Raw_ESG!$B$2:$B$76="2023"),0)+1),""))+(IFERROR(INDEX(Raw_ESG!$F$2:$F$76, MATCH(1, (Raw_ESG!$A$2:$A$76="SRF Ltd")*(Raw_ESG!$B$2:$B$76="2023"),0)+1),"")))} -> 134862.12 | N20: {=IFERROR(INDEX(Raw_ESG!$G$2:$G$76, MATCH(1, (Raw_ESG!$A$2:$A$76="SRF Ltd")*(Raw_ESG!$B$2:$B$76="2023"),0)+1),"")} -> 52.51
A21: SRF Ltd | B21: 2024 | C21: {=IF(OR(IFERROR(INDEX(Raw_Financials!$E$2:$E$76, MATCH(1, (Raw_Financials!$A$2:$A$76="SRF Ltd")*(Raw_Financials!$B$2:$B$76="2024"),0)+1),"")="",IFERROR(INDEX(Raw_Financials!$D$2:$D$76, MATCH(1, (Raw_Financials!$A$2:$A$76="SRF Ltd")*(Raw_Financials!$B$2:$B$76="2024"),0)+1),"")=""),"",(IFERROR(INDEX(Raw_Financials!$D$2:$D$76, MATCH(1, (Raw_Financials!$A$2:$A$76="SRF Ltd")*(Raw_Financials!$B$2:$B$76="2024"),0)+1),""))/(IFERROR(INDEX(Raw_Financials!$E$2:$E$76, MATCH(1, (Raw_Financials!$A$2:$A$76="SRF Ltd")*(Raw_Financials!$B$2:$B$76="2024"),0)+1),"")))} -> 0.05285772 | D21: {=IF(OR(IFERROR(INDEX(Raw_Financials!$E$2:$E$76, MATCH(1, (Raw_Financials!$A$2:$A$76="SRF Ltd")*(Raw_Financials!$B$2:$B$76="2024"),0)+1),"")="",IFERROR(INDEX(Raw_Financials!$C$2:$C$76, MATCH(1, (Raw_Financials!$A$2:$A$76="SRF Ltd")*(Raw_Financials!$B$2:$B$76="2024"),0)+1),"")=""),"",(IFERROR(INDEX(Raw_Financials!$C$2:$C$76, MATCH(1, (Raw_Financials!$A$2:$A$76="SRF Ltd")*(Raw_Financials!$B$2:$B$76="2024"),0)+1),""))/(IFERROR(INDEX(Raw_Financials!$E$2:$E$76, MATCH(1, (Raw_Financials!$A$2:$A$76="SRF Ltd")*(Raw_Financials!$B$2:$B$76="2024"),0)+1),"")))} -> 0.17671317 | E21: {=IF(OR(IFERROR(INDEX(Raw_Financials!$G$2:$G$76, MATCH(1, (Raw_Financials!$A$2:$A$76="SRF Ltd")*(Raw_Financials!$B$2:$B$76="2024"),0)+1),"")="",IFERROR(INDEX(Raw_Financials!$H$2:$H$76, MATCH(1, (Raw_Financials!$A$2:$A$76="SRF Ltd")*(Raw_Financials!$B$2:$B$76="2024"),0)+1),"")=""),"",(IFERROR(INDEX(Raw_Financials!$G$2:$G$76, MATCH(1, (Raw_Financials!$A$2:$A$76="SRF Ltd")*(Raw_Financials!$B$2:$B$76="2024"),0)+1),""))-(IFERROR(INDEX(Raw_Financials!$H$2:$H$76, MATCH(1, (Raw_Financials!$A$2:$A$76="SRF Ltd")*(Raw_Financials!$B$2:$B$76="2024"),0)+1),"")))} -> 4768.09 | F21: {=IF(OR(IFERROR(INDEX(Raw_Financials!$C$2:$C$76, MATCH(1, (Raw_Financials!$A$2:$A$76="SRF Ltd")*(Raw_Financials!$B$2:$B$76="2024"),0)+1),"")="",IF(OR(IFERROR(INDEX(Raw_Financials!$G$2:$G$76, MATCH(1, (Raw_Financials!$A$2:$A$76="SRF Ltd")*(Raw_Financials!$B$2:$B$76="2024"),0)+1),"")="",IFERROR(INDEX(Raw_Financials!$H$2:$H$76, MATCH(1, (Raw_Financials!$A$2:$A$76="SRF Ltd")*(Raw_Financials!$B$2:$B$76="2024"),0)+1),"")=""),"",(IFERROR(INDEX(Raw_Financials!$G$2:$G$76, MATCH(1, (Raw_Financials!$A$2:$A$76="SRF Ltd")*(Raw_Financials!$B$2:$B$76="2024"),0)+1),""))-(IFERROR(INDEX(Raw_Financials!$H$2:$H$76, MATCH(1, (Raw_Financials!$A$2:$A$76="SRF Ltd")*(Raw_Financials!$B$2:$B$76="2024"),0)+1),"")))=""),"",(IFERROR(INDEX(Raw_Financials!$C$2:$C$76, MATCH(1, (Raw_Financials!$A$2:$A$76="SRF Ltd")*(Raw_Financials!$B$2:$B$76="2024"),0)+1),""))/(IF(OR(IFERROR(INDEX(Raw_Financials!$G$2:$G$76, MATCH(1, (Raw_Financials!$A$2:$A$76="SRF Ltd")*(Raw_Financials!$B$2:$B$76="2024"),0)+1),"")="",IFERROR(INDEX(Raw_Financials!$H$2:$H$76, MATCH(1, (Raw_Financials!$A$2:$A$76="SRF Ltd")*(Raw_Financials!$B$2:$B$76="2024"),0)+1),"")=""),"",(IFERROR(INDEX(Raw_Financials!$G$2:$G$76, MATCH(1, (Raw_Financials!$A$2:$A$76="SRF Ltd")*(Raw_Financials!$B$2:$B$76="2024"),0)+1),""))-(IFERROR(INDEX(Raw_Financials!$H$2:$H$76, MATCH(1, (Raw_Financials!$A$2:$A$76="SRF Ltd")*(Raw_Financials!$B$2:$B$76="2024"),0)+1),"")))))} -> 5.7851446 | G21: {=IF(OR(IFERROR(INDEX(Raw_Financials!$O$2:$O$76, MATCH(1, (Raw_Financials!$A$2:$A$76="SRF Ltd")*(Raw_Financials!$B$2:$B$76="2024"),0)+1),"")="",IFERROR(INDEX(Raw_Financials!$M$2:$M$76, MATCH(1, (Raw_Financials!$A$2:$A$76="SRF Ltd")*(Raw_Financials!$B$2:$B$76="2024"),0)+1),"")=""),"",(IFERROR(INDEX(Raw_Financials!$O$2:$O$76, MATCH(1, (Raw_Financials!$A$2:$A$76="SRF Ltd")*(Raw_Financials!$B$2:$B$76="2024"),0)+1),""))/(IFERROR(INDEX(Raw_Financials!$M$2:$M$76, MATCH(1, (Raw_Financials!$A$2:$A$76="SRF Ltd")*(Raw_Financials!$B$2:$B$76="2024"),0)+1),"")))} -> 1.39874 | H21: {=IF(OR(IFERROR(INDEX(Raw_Financials!$M$2:$M$76, MATCH(1, (Raw_Financials!$A$2:$A$76="SRF Ltd")*(Raw_Financials!$B$2:$B$76="2024"),0)+1),"")="",IFERROR(INDEX(Raw_Financials!$L$2:$L$76, MATCH(1, (Raw_Financials!$A$2:$A$76="SRF Ltd")*(Raw_Financials!$B$2:$B$76="2024"),0)+1),"")=""),"",(IFERROR(INDEX(Raw_Financials!$M$2:$M$76, MATCH(1, (Raw_Financials!$A$2:$A$76="SRF Ltd")*(Raw_Financials!$B$2:$B$76="2024"),0)+1),""))/(IFERROR(INDEX(Raw_Financials!$L$2:$L$76, MATCH(1, (Raw_Financials!$A$2:$A$76="SRF Ltd")*(Raw_Financials!$B$2:$B$76="2024"),0)+1),"")))} -> 4.8725092 | I21: {=IF(OR(IFERROR(INDEX(Raw_Financials!$N$2:$N$76, MATCH(1, (Raw_Financials!$A$2:$A$76="SRF Ltd")*(Raw_Financials!$B$2:$B$76="2024"),0)+1),"")="",IFERROR(INDEX(Raw_Financials!$J$2:$J$76, MATCH(1, (Raw_Financials!$A$2:$A$76="SRF Ltd")*(Raw_Financials!$B$2:$B$76="2024"),0)+1),"")=""),"",(IFERROR(INDEX(Raw_Financials!$N$2:$N$76, MATCH(1, (Raw_Financials!$A$2:$A$76="SRF Ltd")*(Raw_Financials!$B$2:$B$76="2024"),0)+1),""))-(IFERROR(INDEX(Raw_Financials!$J$2:$J$76, MATCH(1, (Raw_Financials!$A$2:$A$76="SRF Ltd")*(Raw_Financials!$B$2:$B$76="2024"),0)+1),"")))} -> 6231.85 | J21: {=IF(OR(IFERROR(INDEX(Raw_Financials!$M$2:$M$76, MATCH(1, (Raw_Financials!$A$2:$A$76="SRF Ltd")*(Raw_Financials!$B$2:$B$76="2024"),0)+1),"")="",IFERROR(INDEX(Raw_Financials!$C$2:$C$76, MATCH(1, (Raw_Financials!$A$2:$A$76="SRF Ltd")*(Raw_Financials!$B$2:$B$76="2024"),0)+1),"")=""),"",(IFERROR(INDEX(Raw_Financials!$M$2:$M$76, MATCH(1, (Raw_Financials!$A$2:$A$76="SRF Ltd")*(Raw_Financials!$B$2:$B$76="2024"),0)+1),""))/(IFERROR(INDEX(Raw_Financials!$C$2:$C$76, MATCH(1, (Raw_Financials!$A$2:$A$76="SRF Ltd")*(Raw_Financials!$B$2:$B$76="2024"),0)+1),"")))} -> 0.68080658 | K21: {=IF(OR(IFERROR(INDEX(Raw_ESG!$C$2:$C$76, MATCH(1, (Raw_ESG!$A$2:$A$76="SRF Ltd")*(Raw_ESG!$B$2:$B$76="2024"),0)+1),"")="",IFERROR(INDEX(Raw_Financials!$J$2:$J$76, MATCH(1, (Raw_Financials!$A$2:$A$76="SRF Ltd")*(Raw_Financials!$B$2:$B$76="2024"),0)+1),"")=""),"",(IFERROR(INDEX(Raw_ESG!$C$2:$C$76, MATCH(1, (Raw_ESG!$A$2:$A$76="SRF Ltd")*(Raw_ESG!$B$2:$B$76="2024"),0)+1),""))/(IFERROR(INDEX(Raw_Financials!$J$2:$J$76, MATCH(1, (Raw_Financials!$A$2:$A$76="SRF Ltd")*(Raw_Financials!$B$2:$B$76="2024"),0)+1),"")))} -> 0.67552336 | L21: {=IF(OR(IFERROR(INDEX(Raw_ESG!$D$2:$D$76, MATCH(1, (Raw_ESG!$A$2:$A$76="SRF Ltd")*(Raw_ESG!$B$2:$B$76="2024"),0)+1),"")="",IFERROR(INDEX(Raw_Financials!$E$2:$E$76, MATCH(1, (Raw_Financials!$A$2:$A$76="SRF Ltd")*(Raw_Financials!$B$2:$B$76="2024"),0)+1),"")=""),"",(IFERROR(INDEX(Raw_ESG!$D$2:$D$76, MATCH(1, (Raw_ESG!$A$2:$A$76="SRF Ltd")*(Raw_ESG!$B$2:$B$76="2024"),0)+1),""))/(IFERROR(INDEX(Raw_Financials!$E$2:$E$76, MATCH(1, (Raw_Financials!$A$2:$A$76="SRF Ltd")*(Raw_Financials!$B$2:$B$76="2024"),0)+1),"")))} -> 0.12733192 | M21: {=IF(OR(IFERROR(INDEX(Raw_ESG!$E$2:$E$76, MATCH(1, (Raw_ESG!$A$2:$A$76="SRF Ltd")*(Raw_ESG!$B$2:$B$76="2024"),0)+1),"")="",IFERROR(INDEX(Raw_ESG!$F$2:$F$76, MATCH(1, (Raw_ESG!$A$2:$A$76="SRF Ltd")*(Raw_ESG!$B$2:$B$76="2024"),0)+1),"")=""),"",(IFERROR(INDEX(Raw_ESG!$E$2:$E$76, MATCH(1, (Raw_ESG!$A$2:$A$76="SRF Ltd")*(Raw_ESG!$B$2:$B$76="2024"),0)+1),""))+(IFERROR(INDEX(Raw_ESG!$F$2:$F$76, MATCH(1, (Raw_ESG!$A$2:$A$76="SRF Ltd")*(Raw_ESG!$B$2:$B$76="2024"),0)+1),"")))} -> 189172.37 | N21: {=IFERROR(INDEX(Raw_ESG!$G$2:$G$76, MATCH(1, (Raw_ESG!$A$2:$A$76="SRF Ltd")*(Raw_ESG!$B$2:$B$76="2024"),0)+1),"")} -> 67.46
A22: Gujarat Fluorochemicals | B22: 2020 | C22: {=IF(OR(IFERROR(INDEX(Raw_Financials!$E$2:$E$76, MATCH(1, (Raw_Financials!$A$2:$A$76="Gujarat Fluorochemicals")*(Raw_Financials!$B$2:$B$76="2020"),0)+1),"")="",IFERROR(INDEX(Raw_Financials!$D$2:$D$76, MATCH(1, (Raw_Financials!$A$2:$A$76="Gujarat Fluorochemicals")*(Raw_Financials!$B$2:$B$76="2020"),0)+1),"")=""),"",(IFERROR(INDEX(Raw_Financials!$D$2:$D$76, MATCH(1, (Raw_Financials!$A$2:$A$76="Gujarat Fluorochemicals")*(Raw_Financials!$B$2:$B$76="2020"),0)+1),""))/(IFERROR(INDEX(Raw_Financials!$E$2:$E$76, MATCH(1, (Raw_Financials!$A$2:$A$76="Gujarat Fluorochemicals")*(Raw_Financials!$B$2:$B$76="2020"),0)+1),"")))} -> 0.072000408 | D22: {=IF(OR(IFERROR(INDEX(Raw_Financials!$E$2:$E$76, MATCH(1, (Raw_Financials!$A$2:$A$76="Gujarat Fluorochemicals")*(Raw_Financials!$B$2:$B$76="2020"),0)+1),"")="",IFERROR(INDEX(Raw_Financials!$C$2:$C$76, MATCH(1, (Raw_Financials!$A$2:$A$76="Gujarat Fluorochemicals")*(Raw_Financials!$B$2:$B$76="2020"),0)+1),"")=""),"",(IFERROR(INDEX(Raw_Financials!$C$2:$C$76, MATCH(1, (Raw_Financials!$A$2:$A$76="Gujarat Fluorochemicals")*(Raw_Financials!$B$2:$B$76="2020"),0)+1),""))/(IFERROR(INDEX(Raw_Financials!$E$2:$E$76, MATCH(1, (Raw_Financials!$A$2:$A$76="Gujarat Fluorochemicals")*(Raw_Financials!$B$2:$B$76="2020"),0)+1),"")))} -> 0.59210073 | E22: {=IF(OR(IFERROR(INDEX(Raw_Financials!$G$2:$G$76, MATCH(1, (Raw_Financials!$A$2:$A$76="Gujarat Fluorochemicals")*(Raw_Financials!$B$2:$B$76="2020"),0)+1),"")="",IFERROR(INDEX(Raw_Financials!$H$2:$H$76, MATCH(1, (Raw_Financials!$A$2:$A$76="Gujarat Fluorochemicals")*(Raw_Financials!$B$2:$B$76="2020"),0)+1),"")=""),"",(IFERROR(INDEX(Raw_Financials!$G$2:$G$76, MATCH(1, (Raw_Financials!$A$2:$A$76="Gujarat Fluorochemicals")*(Raw_Financials!$B$2:$B$76="2020"),0)+1),""))-(IFERROR(INDEX(Raw_Financials!$H$2:$H$76, MATCH(1, (Raw_Financials!$A$2:$A$76="Gujarat Fluorochemicals")*(Raw_Financials!$B$2:$B$76="2020"),0)+1),"")))} -> -1467.08 | F22: {=IF(OR(IFERROR(INDEX(Raw_Financials!$C$2:$C$76, MATCH(1, (Raw_Financials!$A$2:$A$76="Gujarat Fluorochemicals")*(Raw_Financials!$B$2:$B$76="2020"),0)+1),"")="",IF(OR(IFERROR(INDEX(Raw_Financials!$G$2:$G$76, MATCH(1, (Raw_Financials!$A$2:$A$76="Gujarat Fluorochemicals")*(Raw_Financials!$B$2:$B$76="2020"),0)+1),"")="",IFERROR(INDEX(Raw_Financials!$H$2:$H$76, MATCH(1, (Raw_Financials!$A$2:$A$76="Gujarat Fluorochemicals")*(Raw_Financials!$B$2:$B$76="2020"),0)+1),"")=""),"",(IFERROR(INDEX(Raw_Financials!$G$2:$G$76, MATCH(1, (Raw_Financials!$A$2:$A$76="Gujarat Fluorochemicals")*(Raw_Financials!$B$2:$B$76="2020"),0)+1),""))-(IFERROR(INDEX(Raw_Financials!$H$2:$H$76, MATCH(1, (Raw_Financials!$A$2:$A$76="Gujarat Fluorochemicals")*(Raw_Financials!$B$2:$B$76="2020"),0)+1),"")))=""),"",(IFERROR(INDEX(Raw_Financials!$C$2:$C$76, MATCH(1, (Raw_Financials!$A$2:$A$76="Gujarat Fluorochemicals")*(Raw_Financials!$B$2:$B$76="2020"),0)+1),""))/(IF(OR(IFERROR(INDEX(Raw_Financials!$G$2:$G$76, MATCH(1, (Raw_Financials!$A$2:$A$76="Gujarat Fluorochemicals")*(Raw_Financials!$B$2:$B$76="2020"),0)+1),"")="",IFERROR(INDEX(Raw_Financials!$H$2:$H$76, MATCH(1, (Raw_Financials!$A$2:$A$76="Gujarat Fluorochemicals")*(Raw_Financials!$B$2:$B$76="2020"),0)+1),"")=""),"",(IFERROR(INDEX(Raw_Financials!$G$2:$G$76, MATCH(1, (Raw_Financials!$A$2:$A$76="Gujarat Fluorochemicals")*(Raw_Financials!$B$2:$B$76="2020"),0)+1),""))-(IFERROR(INDEX(Raw_Financials!$H$2:$H$76, MATCH(1, (Raw_Financials!$A$2:$A$76="Gujarat Fluorochemicals")*(Raw_Financials!$B$2:$B$76="2020"),0)+1),"")))))} -> -40.760361 | G22: {=IF(OR(IFERROR(INDEX(Raw_Financials!$O$2:$O$76, MATCH(1, (Raw_Financials!$A$2:$A$76="Gujarat Fluorochemicals")*(Raw_Financials!$B$2:$B$76="2020"),0)+1),"")="",IFERROR(INDEX(Raw_Financials!$M$2:$M$76, MATCH(1, (Raw_Financials!$A$2:$A$76="Gujarat Fluorochemicals")*(Raw_Financials!$B$2:$B$76="2020"),0)+1),"")=""),"",(IFERROR(INDEX(Raw_Financials!$O$2:$O$76, MATCH(1, (Raw_Financials!$A$2:$A$76="Gujarat Fluorochemicals")*(Raw_Financials!$B$2:$B$76="2020"),0)+1),""))/(IFERROR(INDEX(Raw_Financials!$M$2:$M$76, MATCH(1, (Raw_Financials!$A$2:$A$76="Gujarat Fluorochemicals")*(Raw_Financials!$B$2:$B$76="2020"),0)+1),"")))} -> 2.2451803 | H22: {=IF(OR(IFERROR(INDEX(Raw_Financials!$M$2:$M$76, MATCH(1, (Raw_Financials!$A$2:$A$76="Gujarat Fluorochemicals")*(Raw_Financials!$B$2:$B$76="2020"),0)+1),"")="",IFERROR(INDEX(Raw_Financials!$L$2:$L$76, MATCH(1, (Raw_Financials!$A$2:$A$76="Gujarat Fluorochemicals")*(Raw_Financials!$B$2:$B$76="2020"),0)+1),"")=""),"",(IFERROR(INDEX(Raw_Financials!$M$2:$M$76, MATCH(1, (Raw_Financials!$A$2:$A$76="Gujarat Fluorochemicals")*(Raw_Financials!$B$2:$B$76="2020"),0)+1),""))/(IFERROR(INDEX(Raw_Financials!$L$2:$L$76, MATCH(1, (Raw_Financials!$A$2:$A$76="Gujarat Fluorochemicals")*(Raw_Financials!$B$2:$B$76="2020"),0)+1),"")))} -> 3.4034667 | I22: {=IF(OR(IFERROR(INDEX(Raw_Financials!$N$2:$N$76, MATCH(1, (Raw_Financials!$A$2:$A$76="Gujarat Fluorochemicals")*(Raw_Financials!$B$2:$B$76="2020"),0)+1),"")="",IFERROR(INDEX(Raw_Financials!$J$2:$J$76, MATCH(1, (Raw_Financials!$A$2:$A$76="Gujarat Fluorochemicals")*(Raw_Financials!$B$2:$B$76="2020"),0)+1),"")=""),"",(IFERROR(INDEX(Raw_Financials!$N$2:$N$76, MATCH(1, (Raw_Financials!$A$2:$A$76="Gujarat Fluorochemicals")*(Raw_Financials!$B$2:$B$76="2020"),0)+1),""))-(IFERROR(INDEX(Raw_Financials!$J$2:$J$76, MATCH(1, (Raw_Financials!$A$2:$A$76="Gujarat Fluorochemicals")*(Raw_Financials!$B$2:$B$76="2020"),0)+1),"")))} -> 14756.88 | J22: {=IF(OR(IFERROR(INDEX(Raw_Financials!$M$2:$M$76, MATCH(1, (Raw_Financials!$A$2:$A$76="Gujarat Fluorochemicals")*(Raw_Financials!$B$2:$B$76="2020"),0)+1),"")="",IFERROR(INDEX(Raw_Financials!$C$2:$C$76, MATCH(1, (Raw_Financials!$A$2:$A$76="Gujarat Fluorochemicals")*(Raw_Financials!$B$2:$B$76="2020"),0)+1),"")=""),"",(IFERROR(INDEX(Raw_Financials!$M$2:$M$76, MATCH(1, (Raw_Financials!$A$2:$A$76="Gujarat Fluorochemicals")*(Raw_Financials!$B$2:$B$76="2020"),0)+1),""))/(IFERROR(INDEX(Raw_Financials!$C$2:$C$76, MATCH(1, (Raw_Financials!$A$2:$A$76="Gujarat Fluorochemicals")*(Raw_Financials!$B$2:$B$76="2020"),0)+1),"")))} -> 0.41402131 | K22: {=IF(OR(IFERROR(INDEX(Raw_ESG!$C$2:$C$76, MATCH(1, (Raw_ESG!$A$2:$A$76="Gujarat Fluorochemicals")*(Raw_ESG!$B$2:$B$76="2020"),0)+1),"")="",IFERROR(INDEX(Raw_Financials!$J$2:$J$76, MATCH(1, (Raw_Financials!$A$2:$A$76="Gujarat Fluorochemicals")*(Raw_Financials!$B$2:$B$76="2020"),0)+1),"")=""),"",(IFERROR(INDEX(Raw_ESG!$C$2:$C$76, MATCH(1, (Raw_ESG!$A$2:$A$76="Gujarat Fluorochemicals")*(Raw_ESG!$B$2:$B$76="2020"),0)+1),""))/(IFERROR(INDEX(Raw_Financials!$J$2:$J$76, MATCH(1, (Raw_Financials!$A$2:$A$76="Gujarat Fluorochemicals")*(Raw_Financials!$B$2:$B$76="2020"),0)+1),"")))} -> 0.27559716 | L22: {=IF(OR(IFERROR(INDEX(Raw_ESG!$D$2:$D$76, MATCH(1, (Raw_ESG!$A$2:$A$76="Gujarat Fluorochemicals")*(Raw_ESG!$B$2:$B$76="2020"),0)+1),"")="",IFERROR(INDEX(Raw_Financials!$E$2:$E$76, MATCH(1, (Raw_Financials!$A$2:$A$76="Gujarat Fluorochemicals")*(Raw_Financials!$B$2:$B$76="2020"),0)+1),"")=""),"",(IFERROR(INDEX(Raw_ESG!$D$2:$D$76, MATCH(1, (Raw_ESG!$A$2:$A$76="Gujarat Fluorochemicals")*(Raw_ESG!$B$2:$B$76="2020"),0)+1),""))/(IFERROR(INDEX(Raw_Financials!$E$2:$E$76, MATCH(1, (Raw_Financials!$A$2:$A$76="Gujarat Fluorochemicals")*(Raw_Financials!$B$2:$B$76="2020"),0)+1),"")))} -> 0.20253312 | M22: {=IF(OR(IFERROR(INDEX(Raw_ESG!$E$2:$E$76, MATCH(1, (Raw_ESG!$A$2:$A$76="Gujarat Fluorochemicals")*(Raw_ESG!$B$2:$B$76="2020"),0)+1),"")="",IFERROR(INDEX(Raw_ESG!$F$2:$F$76, MATCH(1, (Raw_ESG!$A$2:$A$76="Gujarat Fluorochemicals")*(Raw_ESG!$B$2:$B$76="2020"),0)+1),"")=""),"",(IFERROR(INDEX(Raw_ESG!$E$2:$E$76, MATCH(1, (Raw_ESG!$A$2:$A$76="Gujarat Fluorochemicals")*(Raw_ESG!$B$2:$B$76="2020"),0)+1),""))+(IFERROR(INDEX(Raw_ESG!$F$2:$F$76, MATCH(1, (Raw_ESG!$A$2:$A$76="Gujarat Fluorochemicals")*(Raw_ESG!$B$2:$B$76="2020"),0)+1),"")))} -> 98067.99 | N22: {=IFERROR(INDEX(Raw_ESG!$G$2:$G$76, MATCH(1, (Raw_ESG!$A$2:$A$76="Gujarat Fluorochemicals")*(Raw_ESG!$B$2:$B$76="2020"),0)+1),"")} -> 75.73
A23: Gujarat Fluorochemicals | B23: 2021 | C23: {=IF(OR(IFERROR(INDEX(Raw_Financials!$E$2:$E$76, MATCH(1, (Raw_Financials!$A$2:$A$76="Gujarat Fluorochemicals")*(Raw_Financials!$B$2:$B$76="2021"),0)+1),"")="",IFERROR(INDEX(Raw_Financials!$D$2:$D$76, MATCH(1, (Raw_Financials!$A$2:$A$76="Gujarat Fluorochemicals")*(Raw_Financials!$B$2:$B$76="2021"),0)+1),"")=""),"",(IFERROR(INDEX(Raw_Financials!$D$2:$D$76, MATCH(1, (Raw_Financials!$A$2:$A$76="Gujarat Fluorochemicals")*(Raw_Financials!$B$2:$B$76="2021"),0)+1),""))/(IFERROR(INDEX(Raw_Financials!$E$2:$E$76, MATCH(1, (Raw_Financials!$A$2:$A$76="Gujarat Fluorochemicals")*(Raw_Financials!$B$2:$B$76="2021"),0)+1),"")))} -> 0.13041599 | D23: {=IF(OR(IFERROR(INDEX(Raw_Financials!$E$2:$E$76, MATCH(1, (Raw_Financials!$A$2:$A$76="Gujarat Fluorochemicals")*(Raw_Financials!$B$2:$B$76="2021"),0)+1),"")="",IFERROR(INDEX(Raw_Financials!$C$2:$C$76, MATCH(1, (Raw_Financials!$A$2:$A$76="Gujarat Fluorochemicals")*(Raw_Financials!$B$2:$B$76="2021"),0)+1),"")=""),"",(IFERROR(INDEX(Raw_Financials!$C$2:$C$76, MATCH(1, (Raw_Financials!$A$2:$A$76="Gujarat Fluorochemicals")*(Raw_Financials!$B$2:$B$76="2021"),0)+1),""))/(IFERROR(INDEX(Raw_Financials!$E$2:$E$76, MATCH(1, (Raw_Financials!$A$2:$A$76="Gujarat Fluorochemicals")*(Raw_Financials!$B$2:$B$76="2021"),0)+1),"")))} -> 0.55468084 | E23: {=IF(OR(IFERROR(INDEX(Raw_Financials!$G$2:$G$76, MATCH(1, (Raw_Financials!$A$2:$A$76="Gujarat Fluorochemicals")*(Raw_Financials!$B$2:$B$76="2021"),0)+1),"")="",IFERROR(INDEX(Raw_Financials!$H$2:$H$76, MATCH(1, (Raw_Financials!$A$2:$A$76="Gujarat Fluorochemicals")*(Raw_Financials!$B$2:$B$76="2021"),0)+1),"")=""),"",(IFERROR(INDEX(Raw_Financials!$G$2:$G$76, MATCH(1, (Raw_Financials!$A$2:$A$76="Gujarat Fluorochemicals")*(Raw_Financials!$B$2:$B$76="2021"),0)+1),""))-(IFERROR(INDEX(Raw_Financials!$H$2:$H$76, MATCH(1, (Raw_Financials!$A$2:$A$76="Gujarat Fluorochemicals")*(Raw_Financials!$B$2:$B$76="2021"),0)+1),"")))} -> 5618.25 | F23: {=IF(OR(IFERROR(INDEX(Raw_Financials!$C$2:$C$76, MATCH(1, (Raw_Financials!$A$2:$A$76="Gujarat Fluorochemicals")*(Raw_Financials!$B$2:$B$76="2021"),0)+1),"")="",IF(OR(IFERROR(INDEX(Raw_Financials!$G$2:$G$76, MATCH(1, (Raw_Financials!$A$2:$A$76="Gujarat Fluorochemicals")*(Raw_Financials!$B$2:$B$76="2021"),0)+1),"")="",IFERROR(INDEX(Raw_Financials!$H$2:$H$76, MATCH(1, (Raw_Financials!$A$2:$A$76="Gujarat Fluorochemicals")*(Raw_Financials!$B$2:$B$76="2021"),0)+1),"")=""),"",(IFERROR(INDEX(Raw_Financials!$G$2:$G$76, MATCH(1, (Raw_Financials!$A$2:$A$76="Gujarat Fluorochemicals")*(Raw_Financials!$B$2:$B$76="2021"),0)+1),""))-(IFERROR(INDEX(Raw_Financials!$H$2:$H$76, MATCH(1, (Raw_Financials!$A$2:$A$76="Gujarat Fluorochemicals")*(Raw_Financials!$B$2:$B$76="2021"),0)+1),"")))=""),"",(IFERROR(INDEX(Raw_Financials!$C$2:$C$76, MATCH(1, (Raw_Financials!$A$2:$A$76="Gujarat Fluorochemicals")*(Raw_Financials!$B$2:$B$76="2021"),0)+1),""))/(IF(OR(IFERROR(INDEX(Raw_Financials!$G$2:$G$76, MATCH(1, (Raw_Financials!$A$2:$A$76="Gujarat Fluorochemicals")*(Raw_Financials!$B$2:$B$76="2021"),0)+1),"")="",IFERROR(INDEX(Raw_Financials!$H$2:$H$76, MATCH(1, (Raw_Financials!$A$2:$A$76="Gujarat Fluorochemicals")*(Raw_Financials!$B$2:$B$76="2021"),0)+1),"")=""),"",(IFERROR(INDEX(Raw_Financials!$G$2:$G$76, MATCH(1, (Raw_Financials!$A$2:$A$76="Gujarat Fluorochemicals")*(Raw_Financials!$B$2:$B$76="2021"),0)+1),""))-(IFERROR(INDEX(Raw_Financials!$H$2:$H$76, MATCH(1, (Raw_Financials!$A$2:$A$76="Gujarat Fluorochemicals")*(Raw_Financials!$B$2:$B$76="2021"),0)+1),"")))))} -> 7.6177867 | G23: {=IF(OR(IFERROR(INDEX(Raw_Financials!$O$2:$O$76, MATCH(1, (Raw_Financials!$A$2:$A$76="Gujarat Fluorochemicals")*(Raw_Financials!$B$2:$B$76="2021"),0)+1),"")="",IFERROR(INDEX(Raw_Financials!$M$2:$M$76, MATCH(1, (Raw_Financials!$A$2:$A$76="Gujarat Fluorochemicals")*(Raw_Financials!$B$2:$B$76="2021"),0)+1),"")=""),"",(IFERROR(INDEX(Raw_Financials!$O$2:$O$76, MATCH(1, (Raw_Financials!$A$2:$A$76="Gujarat Fluorochemicals")*(Raw_Financials!$B$2:$B$76="2021"),0)+1),""))/(IFERROR(INDEX(Raw_Financials!$M$2:$M$76, MATCH(1, (Raw_Financials!$A$2:$A$76="Gujarat Fluorochemicals")*(Raw_Financials!$B$2:$B$76="2021"),0)+1),"")))} -> 1.6972341 | H23: {=IF(OR(IFERROR(INDEX(Raw_Financials!$M$2:$M$76, MATCH(1, (Raw_Financials!$A$2:$A$76="Gujarat Fluorochemicals")*(Raw_Financials!$B$2:$B$76="2021"),0)+1),"")="",IFERROR(INDEX(Raw_Financials!$L$2:$L$76, MATCH(1, (Raw_Financials!$A$2:$A$76="Gujarat Fluorochemicals")*(Raw_Financials!$B$2:$B$76="2021"),0)+1),"")=""),"",(IFERROR(INDEX(Raw_Financials!$M$2:$M$76, MATCH(1, (Raw_Financials!$A$2:$A$76="Gujarat Fluorochemicals")*(Raw_Financials!$B$2:$B$76="2021"),0)+1),""))/(IFERROR(INDEX(Raw_Financials!$L$2:$L$76, MATCH(1, (Raw_Financials!$A$2:$A$76="Gujarat Fluorochemicals")*(Raw_Financials!$B$2:$B$76="2021"),0)+1),"")))} -> 6.6347247 | I23: {=IF(OR(IFERROR(INDEX(Raw_Financials!$N$2:$N$76, MATCH(1, (Raw_Financials!$A$2:$A$76="Gujarat Fluorochemicals")*(Raw_Financials!$B$2:$B$76="2021"),0)+1),"")="",IFERROR(INDEX(Raw_Financials!$J$2:$J$76, MATCH(1, (Raw_Financials!$A$2:$A$76="Gujarat Fluorochemicals")*(Raw_Financials!$B$2:$B$76="2021"),0)+1),"")=""),"",(IFERROR(INDEX(Raw_Financials!$N$2:$N$76, MATCH(1, (Raw_Financials!$A$2:$A$76="Gujarat Fluorochemicals")*(Raw_Financials!$B$2:$B$76="2021"),0)+1),""))-(IFERROR(INDEX(Raw_Financials!$J$2:$J$76, MATCH(1, (Raw_Financials!$A$2:$A$76="Gujarat Fluorochemicals")*(Raw_Financials!$B$2:$B$76="2021"),0)+1),"")))} -> 12300.21 | J23: {=IF(OR(IFERROR(INDEX(Raw_Financials!$M$2:$M$76, MATCH(1, (Raw_Financials!$A$2:$A$76="Gujarat Fluorochemicals")*(Raw_Financials!$B$2:$B$76="2021"),0)+1),"")="",IFERROR(INDEX(Raw_Financials!$C$2:$C$76, MATCH(1, (Raw_Financials!$A$2:$A$76="Gujarat Fluorochemicals")*(Raw_Financials!$B$2:$B$76="2021"),0)+1),"")=""),"",(IFERROR(INDEX(Raw_Financials!$M$2:$M$76, MATCH(1, (Raw_Financials!$A$2:$A$76="Gujarat Fluorochemicals")*(Raw_Financials!$B$2:$B$76="2021"),0)+1),""))/(IFERROR(INDEX(Raw_Financials!$C$2:$C$76, MATCH(1, (Raw_Financials!$A$2:$A$76="Gujarat Fluorochemicals")*(Raw_Financials!$B$2:$B$76="2021"),0)+1),"")))} -> 0.4633868 | K23: {=IF(OR(IFERROR(INDEX(Raw_ESG!$C$2:$C$76, MATCH(1, (Raw_ESG!$A$2:$A$76="Gujarat Fluorochemicals")*(Raw_ESG!$B$2:$B$76="2021"),0)+1),"")="",IFERROR(INDEX(Raw_Financials!$J$2:$J$76, MATCH(1, (Raw_Financials!$A$2:$A$76="Gujarat Fluorochemicals")*(Raw_Financials!$B$2:$B$76="2021"),0)+1),"")=""),"",(IFERROR(INDEX(Raw_ESG!$C$2:$C$76, MATCH(1, (Raw_ESG!$A$2:$A$76="Gujarat Fluorochemicals")*(Raw_ESG!$B$2:$B$76="2021"),0)+1),""))/(IFERROR(INDEX(Raw_Financials!$J$2:$J$76, MATCH(1, (Raw_Financials!$A$2:$A$76="Gujarat Fluorochemicals")*(Raw_Financials!$B$2:$B$76="2021"),0)+1),"")))} -> 0.32905692 | L23: {=IF(OR(IFERROR(INDEX(Raw_ESG!$D$2:$D$76, MATCH(1, (Raw_ESG!$A$2:$A$76="Gujarat Fluorochemicals")*(Raw_ESG!$B$2:$B$76="2021"),0)+1),"")="",IFERROR(INDEX(Raw_Financials!$E$2:$E$76, MATCH(1, (Raw_Financials!$A$2:$A$76="Gujarat Fluorochemicals")*(Raw_Financials!$B$2:$B$76="2021"),0)+1),"")=""),"",(IFERROR(INDEX(Raw_ESG!$D$2:$D$76, MATCH(1, (Raw_ESG!$A$2:$A$76="Gujarat Fluorochemicals")*(Raw_ESG!$B$2:$B$76="2021"),0)+1),""))/(IFERROR(INDEX(Raw_Financials!$E$2:$E$76, MATCH(1, (Raw_Financials!$A$2:$A$76="Gujarat Fluorochemicals")*(Raw_Financials!$B$2:$B$76="2021"),0)+1),"")))} -> 0.24042322 | M23: {=IF(OR(IFERROR(INDEX(Raw_ESG!$E$2:$E$76, MATCH(1, (Raw_ESG!$A$2:$A$76="Gujarat Fluorochemicals")*(Raw_ESG!$B$2:$B$76="2021"),0)+1),"")="",IFERROR(INDEX(Raw_ESG!$F$2:$F$76, MATCH(1, (Raw_ESG!$A$2:$A$76="Gujarat Fluorochemicals")*(Raw_ESG!$B$2:$B$76="2021"),0)+1),"")=""),"",(IFERROR(INDEX(Raw_ESG!$E$2:$E$76, MATCH(1, (Raw_ESG!$A$2:$A$76="Gujarat Fluorochemicals")*(Raw_ESG!$B$2:$B$76="2021"),0)+1),""))+(IFERROR(INDEX(Raw_ESG!$F$2:$F$76, MATCH(1, (Raw_ESG!$A$2:$A$76="Gujarat Fluorochemicals")*(Raw_ESG!$B$2:$B$76="2021"),0)+1),"")))} -> 174542.05 | N23: {=IFERROR(INDEX(Raw_ESG!$G$2:$G$76, MATCH(1, (Raw_ESG!$A$2:$A$76="Gujarat Fluorochemicals")*(Raw_ESG!$B$2:$B$76="2021"),0)+1),"")} -> 73.01
A24: Gujarat Fluorochemicals | B24: 2022 | C24: {=IF(OR(IFERROR(INDEX(Raw_Financials!$E$2:$E$76, MATCH(1, (Raw_Financials!$A$2:$A$76="Gujarat Fluorochemicals")*(Raw_Financials!$B$2:$B$76="2022"),0)+1),"")="",IFERROR(INDEX(Raw_Financials!$D$2:$D$76, MATCH(1, (Raw_Financials!$A$2:$A$76="Gujarat Fluorochemicals")*(Raw_Financials!$B$2:$B$76="2022"),0)+1),"")=""),"",(IFERROR(INDEX(Raw_Financials!$D$2:$D$76, MATCH(1, (Raw_Financials!$A$2:$A$76="Gujarat Fluorochemicals")*(Raw_Financials!$B$2:$B$76="2022"),0)+1),""))/(IFERROR(INDEX(Raw_Financials!$E$2:$E$76, MATCH(1, (Raw_Financials!$A$2:$A$76="Gujarat Fluorochemicals")*(Raw_Financials!$B$2:$B$76="2022"),0)+1),"")))} -> 0.11101759 | D24: {=IF(OR(IFERROR(INDEX(Raw_Financials!$E$2:$E$76, MATCH(1, (Raw_Financials!$A$2:$A$76="Gujarat Fluorochemicals")*(Raw_Financials!$B$2:$B$76="2022"),0)+1),"")="",IFERROR(INDEX(Raw_Financials!$C$2:$C$76, MATCH(1, (Raw_Financials!$A$2:$A$76="Gujarat Fluorochemicals")*(Raw_Financials!$B$2:$B$76="2022"),0)+1),"")=""),"",(IFERROR(INDEX(Raw_Financials!$C$2:$C$76, MATCH(1, (Raw_Financials!$A$2:$A$76="Gujarat Fluorochemicals")*(Raw_Financials!$B$2:$B$76="2022"),0)+1),""))/(IFERROR(INDEX(Raw_Financials!$E$2:$E$76, MATCH(1, (Raw_Financials!$A$2:$A$76="Gujarat Fluorochemicals")*(Raw_Financials!$B$2:$B$76="2022"),0)+1),"")))} -> 0.68209659 | E24: {=IF(OR(IFERROR(INDEX(Raw_Financials!$G$2:$G$76, MATCH(1, (Raw_Financials!$A$2:$A$76="Gujarat Fluorochemicals")*(Raw_Financials!$B$2:$B$76="2022"),0)+1),"")="",IFERROR(INDEX(Raw_Financials!$H$2:$H$76, MATCH(1, (Raw_Financials!$A$2:$A$76="Gujarat Fluorochemicals")*(Raw_Financials!$B$2:$B$76="2022"),0)+1),"")=""),"",(IFERROR(INDEX(Raw_Financials!$G$2:$G$76, MATCH(1, (Raw_Financials!$A$2:$A$76="Gujarat Fluorochemicals")*(Raw_Financials!$B$2:$B$76="2022"),0)+1),""))-(IFERROR(INDEX(Raw_Financials!$H$2:$H$76, MATCH(1, (Raw_Financials!$A$2:$A$76="Gujarat Fluorochemicals")*(Raw_Financials!$B$2:$B$76="2022"),0)+1),"")))} -> 14940.31 | F24: {=IF(OR(IFERROR(INDEX(Raw_Financials!$C$2:$C$76, MATCH(1, (Raw_Financials!$A$2:$A$76="Gujarat Fluorochemicals")*(Raw_Financials!$B$2:$B$76="2022"),0)+1),"")="",IF(OR(IFERROR(INDEX(Raw_Financials!$G$2:$G$76, MATCH(1, (Raw_Financials!$A$2:$A$76="Gujarat Fluorochemicals")*(Raw_Financials!$B$2:$B$76="2022"),0)+1),"")="",IFERROR(INDEX(Raw_Financials!$H$2:$H$76, MATCH(1, (Raw_Financials!$A$2:$A$76="Gujarat Fluorochemicals")*(Raw_Financials!$B$2:$B$76="2022"),0)+1),"")=""),"",(IFERROR(INDEX(Raw_Financials!$G$2:$G$76, MATCH(1, (Raw_Financials!$A$2:$A$76="Gujarat Fluorochemicals")*(Raw_Financials!$B$2:$B$76="2022"),0)+1),""))-(IFERROR(INDEX(Raw_Financials!$H$2:$H$76, MATCH(1, (Raw_Financials!$A$2:$A$76="Gujarat Fluorochemicals")*(Raw_Financials!$B$2:$B$76="2022"),0)+1),"")))=""),"",(IFERROR(INDEX(Raw_Financials!$C$2:$C$76, MATCH(1, (Raw_Financials!$A$2:$A$76="Gujarat Fluorochemicals")*(Raw_Financials!$B$2:$B$76="2022"),0)+1),""))/(IF(OR(IFERROR(INDEX(Raw_Financials!$G$2:$G$76, MATCH(1, (Raw_Financials!$A$2:$A$76="Gujarat Fluorochemicals")*(Raw_Financials!$B$2:$B$76="2022"),0)+1),"")="",IFERROR(INDEX(Raw_Financials!$H$2:$H$76, MATCH(1, (Raw_Financials!$A$2:$A$76="Gujarat Fluorochemicals")*(Raw_Financials!$B$2:$B$76="2022"),0)+1),"")=""),"",(IFERROR(INDEX(Raw_Financials!$G$2:$G$76, MATCH(1, (Raw_Financials!$A$2:$A$76="Gujarat Fluorochemicals")*(Raw_Financials!$B$2:$B$76="2022"),0)+1),""))-(IFERROR(INDEX(Raw_Financials!$H$2:$H$76, MATCH(1, (Raw_Financials!$A$2:$A$76="Gujarat Fluorochemicals")*(Raw_Financials!$B$2:$B$76="2022"),0)+1),"")))))} -> 3.7343603 | G24: {=IF(OR(IFERROR(INDEX(Raw_Financials!$O$2:$O$76, MATCH(1, (Raw_Financials!$A$2:$A$76="Gujarat Fluorochemicals")*(Raw_Financials!$B$2:$B$76="2022"),0)+1),"")="",IFERROR(INDEX(Raw_Financials!$M$2:$M$76, MATCH(1, (Raw_Financials!$A$2:$A$76="Gujarat Fluorochemicals")*(Raw_Financials!$B$2:$B$76="2022"),0)+1),"")=""),"",(IFERROR(INDEX(Raw_Financials!$O$2:$O$76, MATCH(1, (Raw_Financials!$A$2:$A$76="Gujarat Fluorochemicals")*(Raw_Financials!$B$2:$B$76="2022"),0)+1),""))/(IFERROR(INDEX(Raw_Financials!$M$2:$M$76, MATCH(1, (Raw_Financials!$A$2:$A$76="Gujarat Fluorochemicals")*(Raw_Financials!$B$2:$B$76="2022"),0)+1),"")))} -> 2.376044 | H24: {=IF(OR(IFERROR(INDEX(Raw_Financials!$M$2:$M$76, MATCH(1, (Raw_Financials!$A$2:$A$76="Gujarat Fluorochemicals")*(Raw_Financials!$B$2:$B$76="2022"),0)+1),"")="",IFERROR(INDEX(Raw_Financials!$L$2:$L$76, MATCH(1, (Raw_Financials!$A$2:$A$76="Gujarat Fluorochemicals")*(Raw_Financials!$B$2:$B$76="2022"),0)+1),"")=""),"",(IFERROR(INDEX(Raw_Financials!$M$2:$M$76, MATCH(1, (Raw_Financials!$A$2:$A$76="Gujarat Fluorochemicals")*(Raw_Financials!$B$2:$B$76="2022"),0)+1),""))/(IFERROR(INDEX(Raw_Financials!$L$2:$L$76, MATCH(1, (Raw_Financials!$A$2:$A$76="Gujarat Fluorochemicals")*(Raw_Financials!$B$2:$B$76="2022"),0)+1),"")))} -> 8.0089981 | I24: {=IF(OR(IFERROR(INDEX(Raw_Financials!$N$2:$N$76, MATCH(1, (Raw_Financials!$A$2:$A$76="Gujarat Fluorochemicals")*(Raw_Financials!$B$2:$B$76="2022"),0)+1),"")="",IFERROR(INDEX(Raw_Financials!$J$2:$J$76, MATCH(1, (Raw_Financials!$A$2:$A$76="Gujarat Fluorochemicals")*(Raw_Financials!$B$2:$B$76="2022"),0)+1),"")=""),"",(IFERROR(INDEX(Raw_Financials!$N$2:$N$76, MATCH(1, (Raw_Financials!$A$2:$A$76="Gujarat Fluorochemicals")*(Raw_Financials!$B$2:$B$76="2022"),0)+1),""))-(IFERROR(INDEX(Raw_Financials!$J$2:$J$76, MATCH(1, (Raw_Financials!$A$2:$A$76="Gujarat Fluorochemicals")*(Raw_Financials!$B$2:$B$76="2022"),0)+1),"")))} -> 1575.84 | J24: {=IF(OR(IFERROR(INDEX(Raw_Financials!$M$2:$M$76, MATCH(1, (Raw_Financials!$A$2:$A$76="Gujarat Fluorochemicals")*(Raw_Financials!$B$2:$B$76="2022"),0)+1),"")="",IFERROR(INDEX(Raw_Financials!$C$2:$C$76, MATCH(1, (Raw_Financials!$A$2:$A$76="Gujarat Fluorochemicals")*(Raw_Financials!$B$2:$B$76="2022"),0)+1),"")=""),"",(IFERROR(INDEX(Raw_Financials!$M$2:$M$76, MATCH(1, (Raw_Financials!$A$2:$A$76="Gujarat Fluorochemicals")*(Raw_Financials!$B$2:$B$76="2022"),0)+1),""))/(IFERROR(INDEX(Raw_Financials!$C$2:$C$76, MATCH(1, (Raw_Financials!$A$2:$A$76="Gujarat Fluorochemicals")*(Raw_Financials!$B$2:$B$76="2022"),0)+1),"")))} -> 0.4095244 | K24: {=IF(OR(IFERROR(INDEX(Raw_ESG!$C$2:$C$76, MATCH(1, (Raw_ESG!$A$2:$A$76="Gujarat Fluorochemicals")*(Raw_ESG!$B$2:$B$76="2022"),0)+1),"")="",IFERROR(INDEX(Raw_Financials!$J$2:$J$76, MATCH(1, (Raw_Financials!$A$2:$A$76="Gujarat Fluorochemicals")*(Raw_Financials!$B$2:$B$76="2022"),0)+1),"")=""),"",(IFERROR(INDEX(Raw_ESG!$C$2:$C$76, MATCH(1, (Raw_ESG!$A$2:$A$76="Gujarat Fluorochemicals")*(Raw_ESG!$B$2:$B$76="2022"),0)+1),""))/(IFERROR(INDEX(Raw_Financials!$J$2:$J$76, MATCH(1, (Raw_Financials!$A$2:$A$76="Gujarat Fluorochemicals")*(Raw_Financials!$B$2:$B$76="2022"),0)+1),"")))} -> 0.3738528 | L24: {=IF(OR(IFERROR(INDEX(Raw_ESG!$D$2:$D$76, MATCH(1, (Raw_ESG!$A$2:$A$76="Gujarat Fluorochemicals")*(Raw_ESG!$B$2:$B$76="2022"),0)+1),"")="",IFERROR(INDEX(Raw_Financials!$E$2:$E$76, MATCH(1, (Raw_Financials!$A$2:$A$76="Gujarat Fluorochemicals")*(Raw_Financials!$B$2:$B$76="2022"),0)+1),"")=""),"",(IFERROR(INDEX(Raw_ESG!$D$2:$D$76, MATCH(1, (Raw_ESG!$A$2:$A$76="Gujarat Fluorochemicals")*(Raw_ESG!$B$2:$B$76="2022"),0)+1),""))/(IFERROR(INDEX(Raw_Financials!$E$2:$E$76, MATCH(1, (Raw_Financials!$A$2:$A$76="Gujarat Fluorochemicals")*(Raw_Financials!$B$2:$B$76="2022"),0)+1),"")))} -> 0.12847121 | M24: {=IF(OR(IFERROR(INDEX(Raw_ESG!$E$2:$E$76, MATCH(1, (Raw_ESG!$A$2:$A$76="Gujarat Fluorochemicals")*(Raw_ESG!$B$2:$B$76="2022"),0)+1),"")="",IFERROR(INDEX(Raw_ESG!$F$2:$F$76, MATCH(1, (Raw_ESG!$A$2:$A$76="Gujarat Fluorochemicals")*(Raw_ESG!$B$2:$B$76="2022"),0)+1),"")=""),"",(IFERROR(INDEX(Raw_ESG!$E$2:$E$76, MATCH(1, (Raw_ESG!$A$2:$A$76="Gujarat Fluorochemicals")*(Raw_ESG!$B$2:$B$76="2022"),0)+1),""))+(IFERROR(INDEX(Raw_ESG!$F$2:$F$76, MATCH(1, (Raw_ESG!$A$2:$A$76="Gujarat Fluorochemicals")*(Raw_ESG!$B$2:$B$76="2022"),0)+1),"")))} -> 145830.58 | N24: {=IFERROR(INDEX(Raw_ESG!$G$2:$G$76, MATCH(1, (Raw_ESG!$A$2:$A$76="Gujarat Fluorochemicals")*(Raw_ESG!$B$2:$B$76="2022"),0)+1),"")} -> 54
A25: Gujarat Fluorochemicals | B25: 2023 | C25: {=IF(OR(IFERROR(INDEX(Raw_Financials!$E$2:$E$76, MATCH(1, (Raw_Financials!$A$2:$A$76="Gujarat Fluorochemicals")*(Raw_Financials!$B$2:$B$76="2023"),0)+1),"")="",IFERROR(INDEX(Raw_Financials!$D$2:$D$76, MATCH(1, (Raw_Financials!$A$2:$A$76="Gujarat Fluorochemicals")*(Raw_Financials!$B$2:$B$76="2023"),0)+1),"")=""),"",(IFERROR(INDEX(Raw_Financials!$D$2:$D$76, MATCH(1, (Raw_Financials!$A$2:$A$76="Gujarat Fluorochemicals")*(Raw_Financials!$B$2:$B$76="2023"),0)+1),""))/(IFERROR(INDEX(Raw_Financials!$E$2:$E$76, MATCH(1, (Raw_Financials!$A$2:$A$76="Gujarat Fluorochemicals")*(Raw_Financials!$B$2:$B$76="2023"),0)+1),"")))} -> 0.063631847 | D25: {=IF(OR(IFERROR(INDEX(Raw_Financials!$E$2:$E$76, MATCH(1, (Raw_Financials!$A$2:$A$76="Gujarat Fluorochemicals")*(Raw_Financials!$B$2:$B$76="2023"),0)+1),"")="",IFERROR(INDEX(Raw_Financials!$C$2:$C$76, MATCH(1, (Raw_Financials!$A$2:$A$76="Gujarat Fluorochemicals")*(Raw_Financials!$B$2:$B$76="2023"),0)+1),"")=""),"",(IFERROR(INDEX(Raw_Financials!$C$2:$C$76, MATCH(1, (Raw_Financials!$A$2:$A$76="Gujarat Fluorochemicals")*(Raw_Financials!$B$2:$B$76="2023"),0)+1),""))/(IFERROR(INDEX(Raw_Financials!$E$2:$E$76, MATCH(1, (Raw_Financials!$A$2:$A$76="Gujarat Fluorochemicals")*(Raw_Financials!$B$2:$B$76="2023"),0)+1),"")))} -> 0.30895464 | E25: {=IF(OR(IFERROR(INDEX(Raw_Financials!$G$2:$G$76, MATCH(1, (Raw_Financials!$A$2:$A$76="Gujarat Fluorochemicals")*(Raw_Financials!$B$2:$B$76="2023"),0)+1),"")="",IFERROR(INDEX(Raw_Financials!$H$2:$H$76, MATCH(1, (Raw_Financials!$A$2:$A$76="Gujarat Fluorochemicals")*(Raw_Financials!$B$2:$B$76="2023"),0)+1),"")=""),"",(IFERROR(INDEX(Raw_Financials!$G$2:$G$76, MATCH(1, (Raw_Financials!$A$2:$A$76="Gujarat Fluorochemicals")*(Raw_Financials!$B$2:$B$76="2023"),0)+1),""))-(IFERROR(INDEX(Raw_Financials!$H$2:$H$76, MATCH(1, (Raw_Financials!$A$2:$A$76="Gujarat Fluorochemicals")*(Raw_Financials!$B$2:$B$76="2023"),0)+1),"")))} -> 31075.51 | F25: {=IF(OR(IFERROR(INDEX(Raw_Financials!$C$2:$C$76, MATCH(1, (Raw_Financials!$A$2:$A$76="Gujarat Fluorochemicals")*(Raw_Financials!$B$2:$B$76="2023"),0)+1),"")="",IF(OR(IFERROR(INDEX(Raw_Financials!$G$2:$G$76, MATCH(1, (Raw_Financials!$A$2:$A$76="Gujarat Fluorochemicals")*(Raw_Financials!$B$2:$B$76="2023"),0)+1),"")="",IFERROR(INDEX(Raw_Financials!$H$2:$H$76, MATCH(1, (Raw_Financials!$A$2:$A$76="Gujarat Fluorochemicals")*(Raw_Financials!$B$2:$B$76="2023"),0)+1),"")=""),"",(IFERROR(INDEX(Raw_Financials!$G$2:$G$76, MATCH(1, (Raw_Financials!$A$2:$A$76="Gujarat Fluorochemicals")*(Raw_Financials!$B$2:$B$76="2023"),0)+1),""))-(IFERROR(INDEX(Raw_Financials!$H$2:$H$76, MATCH(1, (Raw_Financials!$A$2:$A$76="Gujarat Fluorochemicals")*(Raw_Financials!$B$2:$B$76="2023"),0)+1),"")))=""),"",(IFERROR(INDEX(Raw_Financials!$C$2:$C$76, MATCH(1, (Raw_Financials!$A$2:$A$76="Gujarat Fluorochemicals")*(Raw_Financials!$B$2:$B$76="2023"),0)+1),""))/(IF(OR(IFERROR(INDEX(Raw_Financials!$G$2:$G$76, MATCH(1, (Raw_Financials!$A$2:$A$76="Gujarat Fluorochemicals")*(Raw_Financials!$B$2:$B$76="2023"),0)+1),"")="",IFERROR(INDEX(Raw_Financials!$H$2:$H$76, MATCH(1, (Raw_Financials!$A$2:$A$76="Gujarat Fluorochemicals")*(Raw_Financials!$B$2:$B$76="2023"),0)+1),"")=""),"",(IFERROR(INDEX(Raw_Financials!$G$2:$G$76, MATCH(1, (Raw_Financials!$A$2:$A$76="Gujarat Fluorochemicals")*(Raw_Financials!$B$2:$B$76="2023"),0)+1),""))-(IFERROR(INDEX(Raw_Financials!$H$2:$H$76, MATCH(1, (Raw_Financials!$A$2:$A$76="Gujarat Fluorochemicals")*(Raw_Financials!$B$2:$B$76="2023"),0)+1),"")))))} -> 1.4290514 | G25: {=IF(OR(IFERROR(INDEX(Raw_Financials!$O$2:$O$76, MATCH(1, (Raw_Financials!$A$2:$A$76="Gujarat Fluorochemicals")*(Raw_Financials!$B$2:$B$76="2023"),0)+1),"")="",IFERROR(INDEX(Raw_Financials!$M$2:$M$76, MATCH(1, (Raw_Financials!$A$2:$A$76="Gujarat Fluorochemicals")*(Raw_Financials!$B$2:$B$76="2023"),0)+1),"")=""),"",(IFERROR(INDEX(Raw_Financials!$O$2:$O$76, MATCH(1, (Raw_Financials!$A$2:$A$76="Gujarat Fluorochemicals")*(Raw_Financials!$B$2:$B$76="2023"),0)+1),""))/(IFERROR(INDEX(Raw_Financials!$M$2:$M$76, MATCH(1, (Raw_Financials!$A$2:$A$76="Gujarat Fluorochemicals")*(Raw_Financials!$B$2:$B$76="2023"),0)+1),"")))} -> 2.4736383 | H25: {=IF(OR(IFERROR(INDEX(Raw_Financials!$M$2:$M$76, MATCH(1, (Raw_Financials!$A$2:$A$76="Gujarat Fluorochemicals")*(Raw_Financials!$B$2:$B$76="2023"),0)+1),"")="",IFERROR(INDEX(Raw_Financials!$L$2:$L$76, MATCH(1, (Raw_Financials!$A$2:$A$76="Gujarat Fluorochemicals")*(Raw_Financials!$B$2:$B$76="2023"),0)+1),"")=""),"",(IFERROR(INDEX(Raw_Financials!$M$2:$M$76, MATCH(1, (Raw_Financials!$A$2:$A$76="Gujarat Fluorochemicals")*(Raw_Financials!$B$2:$B$76="2023"),0)+1),""))/(IFERROR(INDEX(Raw_Financials!$L$2:$L$76, MATCH(1, (Raw_Financials!$A$2:$A$76="Gujarat Fluorochemicals")*(Raw_Financials!$B$2:$B$76="2023"),0)+1),"")))} -> 4.2207102 | I25: {=IF(OR(IFERROR(INDEX(Raw_Financials!$N$2:$N$76, MATCH(1, (Raw_Financials!$A$2:$A$76="Gujarat Fluorochemicals")*(Raw_Financials!$B$2:$B$76="2023"),0)+1),"")="",IFERROR(INDEX(Raw_Financials!$J$2:$J$76, MATCH(1, (Raw_Financials!$A$2:$A$76="Gujarat Fluorochemicals")*(Raw_Financials!$B$2:$B$76="2023"),0)+1),"")=""),"",(IFERROR(INDEX(Raw_Financials!$N$2:$N$76, MATCH(1, (Raw_Financials!$A$2:$A$76="Gujarat Fluorochemicals")*(Raw_Financials!$B$2:$B$76="2023"),0)+1),""))-(IFERROR(INDEX(Raw_Financials!$J$2:$J$76, MATCH(1, (Raw_Financials!$A$2:$A$76="Gujarat Fluorochemicals")*(Raw_Financials!$B$2:$B$76="2023"),0)+1),"")))} -> -1097.96 | J25: {=IF(OR(IFERROR(INDEX(Raw_Financials!$M$2:$M$76, MATCH(1, (Raw_Financials!$A$2:$A$76="Gujarat Fluorochemicals")*(Raw_Financials!$B$2:$B$76="2023"),0)+1),"")="",IFERROR(INDEX(Raw_Financials!$C$2:$C$76, MATCH(1, (Raw_Financials!$A$2:$A$76="Gujarat Fluorochemicals")*(Raw_Financials!$B$2:$B$76="2023"),0)+1),"")=""),"",(IFERROR(INDEX(Raw_Financials!$M$2:$M$76, MATCH(1, (Raw_Financials!$A$2:$A$76="Gujarat Fluorochemicals")*(Raw_Financials!$B$2:$B$76="2023"),0)+1),""))/(IFERROR(INDEX(Raw_Financials!$C$2:$C$76, MATCH(1, (Raw_Financials!$A$2:$A$76="Gujarat Fluorochemicals")*(Raw_Financials!$B$2:$B$76="2023"),0)+1),"")))} -> 0.27056892 | K25: {=IF(OR(IFERROR(INDEX(Raw_ESG!$C$2:$C$76, MATCH(1, (Raw_ESG!$A$2:$A$76="Gujarat Fluorochemicals")*(Raw_ESG!$B$2:$B$76="2023"),0)+1),"")="",IFERROR(INDEX(Raw_Financials!$J$2:$J$76, MATCH(1, (Raw_Financials!$A$2:$A$76="Gujarat Fluorochemicals")*(Raw_Financials!$B$2:$B$76="2023"),0)+1),"")=""),"",(IFERROR(INDEX(Raw_ESG!$C$2:$C$76, MATCH(1, (Raw_ESG!$A$2:$A$76="Gujarat Fluorochemicals")*(Raw_ESG!$B$2:$B$76="2023"),0)+1),""))/(IFERROR(INDEX(Raw_Financials!$J$2:$J$76, MATCH(1, (Raw_Financials!$A$2:$A$76="Gujarat Fluorochemicals")*(Raw_Financials!$B$2:$B$76="2023"),0)+1),"")))} -> 0.34015346 | L25: {=IF(OR(IFERROR(INDEX(Raw_ESG!$D$2:$D$76, MATCH(1, (Raw_ESG!$A$2:$A$76="Gujarat Fluorochemicals")*(Raw_ESG!$B$2:$B$76="2023"),0)+1),"")="",IFERROR(INDEX(Raw_Financials!$E$2:$E$76, MATCH(1, (Raw_Financials!$A$2:$A$76="Gujarat Fluorochemicals")*(Raw_Financials!$B$2:$B$76="2023"),0)+1),"")=""),"",(IFERROR(INDEX(Raw_ESG!$D$2:$D$76, MATCH(1, (Raw_ESG!$A$2:$A$76="Gujarat Fluorochemicals")*(Raw_ESG!$B$2:$B$76="2023"),0)+1),""))/(IFERROR(INDEX(Raw_Financials!$E$2:$E$76, MATCH(1, (Raw_Financials!$A$2:$A$76="Gujarat Fluorochemicals")*(Raw_Financials!$B$2:$B$76="2023"),0)+1),"")))} -> 0.084583311 | M25: {=IF(OR(IFERROR(INDEX(Raw_ESG!$E$2:$E$76, MATCH(1, (Raw_ESG!$A$2:$A$76="Gujarat Fluorochemicals")*(Raw_ESG!$B$2:$B$76="2023"),0)+1),"")="",IFERROR(INDEX(Raw_ESG!$F$2:$F$76, MATCH(1, (Raw_ESG!$A$2:$A$76="Gujarat Fluorochemicals")*(Raw_ESG!$B$2:$B$76="2023"),0)+1),"")=""),"",(IFERROR(INDEX(Raw_ESG!$E$2:$E$76, MATCH(1, (Raw_ESG!$A$2:$A$76="Gujarat Fluorochemicals")*(Raw_ESG!$B$2:$B$76="2023"),0)+1),""))+(IFERROR(INDEX(Raw_ESG!$F$2:$F$76, MATCH(1, (Raw_ESG!$A$2:$A$76="Gujarat Fluorochemicals")*(Raw_ESG!$B$2:$B$76="2023"),0)+1),"")))} -> 182167.75 | N25: {=IFERROR(INDEX(Raw_ESG!$G$2:$G$76, MATCH(1, (Raw_ESG!$A$2:$A$76="Gujarat Fluorochemicals")*(Raw_ESG!$B$2:$B$76="2023"),0)+1),"")} -> 87.74
A26: Gujarat Fluorochemicals | B26: 2024 | C26: {=IF(OR(IFERROR(INDEX(Raw_Financials!$E$2:$E$76, MATCH(1, (Raw_Financials!$A$2:$A$76="Gujarat Fluorochemicals")*(Raw_Financials!$B$2:$B$76="2024"),0)+1),"")="",IFERROR(INDEX(Raw_Financials!$D$2:$D$76, MATCH(1, (Raw_Financials!$A$2:$A$76="Gujarat Fluorochemicals")*(Raw_Financials!$B$2:$B$76="2024"),0)+1),"")=""),"",(IFERROR(INDEX(Raw_Financials!$D$2:$D$76, MATCH(1, (Raw_Financials!$A$2:$A$76="Gujarat Fluorochemicals")*(Raw_Financials!$B$2:$B$76="2024"),0)+1),""))/(IFERROR(INDEX(Raw_Financials!$E$2:$E$76, MATCH(1, (Raw_Financials!$A$2:$A$76="Gujarat Fluorochemicals")*(Raw_Financials!$B$2:$B$76="2024"),0)+1),"")))} -> 0.13707341 | D26: {=IF(OR(IFERROR(INDEX(Raw_Financials!$E$2:$E$76, MATCH(1, (Raw_Financials!$A$2:$A$76="Gujarat Fluorochemicals")*(Raw_Financials!$B$2:$B$76="2024"),0)+1),"")="",IFERROR(INDEX(Raw_Financials!$C$2:$C$76, MATCH(1, (Raw_Financials!$A$2:$A$76="Gujarat Fluorochemicals")*(Raw_Financials!$B$2:$B$76="2024"),0)+1),"")=""),"",(IFERROR(INDEX(Raw_Financials!$C$2:$C$76, MATCH(1, (Raw_Financials!$A$2:$A$76="Gujarat Fluorochemicals")*(Raw_Financials!$B$2:$B$76="2024"),0)+1),""))/(IFERROR(INDEX(Raw_Financials!$E$2:$E$76, MATCH(1, (Raw_Financials!$A$2:$A$76="Gujarat Fluorochemicals")*(Raw_Financials!$B$2:$B$76="2024"),0)+1),"")))} -> 0.52170172 | E26: {=IF(OR(IFERROR(INDEX(Raw_Financials!$G$2:$G$76, MATCH(1, (Raw_Financials!$A$2:$A$76="Gujarat Fluorochemicals")*(Raw_Financials!$B$2:$B$76="2024"),0)+1),"")="",IFERROR(INDEX(Raw_Financials!$H$2:$H$76, MATCH(1, (Raw_Financials!$A$2:$A$76="Gujarat Fluorochemicals")*(Raw_Financials!$B$2:$B$76="2024"),0)+1),"")=""),"",(IFERROR(INDEX(Raw_Financials!$G$2:$G$76, MATCH(1, (Raw_Financials!$A$2:$A$76="Gujarat Fluorochemicals")*(Raw_Financials!$B$2:$B$76="2024"),0)+1),""))-(IFERROR(INDEX(Raw_Financials!$H$2:$H$76, MATCH(1, (Raw_Financials!$A$2:$A$76="Gujarat Fluorochemicals")*(Raw_Financials!$B$2:$B$76="2024"),0)+1),"")))} -> 12729.25 | F26: {=IF(OR(IFERROR(INDEX(Raw_Financials!$C$2:$C$76, MATCH(1, (Raw_Financials!$A$2:$A$76="Gujarat Fluorochemicals")*(Raw_Financials!$B$2:$B$76="2024"),0)+1),"")="",IF(OR(IFERROR(INDEX(Raw_Financials!$G$2:$G$76, MATCH(1, (Raw_Financials!$A$2:$A$76="Gujarat Fluorochemicals")*(Raw_Financials!$B$2:$B$76="2024"),0)+1),"")="",IFERROR(INDEX(Raw_Financials!$H$2:$H$76, MATCH(1, (Raw_Financials!$A$2:$A$76="Gujarat Fluorochemicals")*(Raw_Financials!$B$2:$B$76="2024"),0)+1),"")=""),"",(IFERROR(INDEX(Raw_Financials!$G$2:$G$76, MATCH(1, (Raw_Financials!$A$2:$A$76="Gujarat Fluorochemicals")*(Raw_Financials!$B$2:$B$76="2024"),0)+1),""))-(IFERROR(INDEX(Raw_Financials!$H$2:$H$76, MATCH(1, (Raw_Financials!$A$2:$A$76="Gujarat Fluorochemicals")*(Raw_Financials!$B$2:$B$76="2024"),0)+1),"")))=""),"",(IFERROR(INDEX(Raw_Financials!$C$2:$C$76, MATCH(1, (Raw_Financials!$A$2:$A$76="Gujarat Fluorochemicals")*(Raw_Financials!$B$2:$B$76="2024"),0)+1),""))/(IF(OR(IFERROR(INDEX(Raw_Financials!$G$2:$G$76, MATCH(1, (Raw_Financials!$A$2:$A$76="Gujarat Fluorochemicals")*(Raw_Financials!$B$2:$B$76="2024"),0)+1),"")="",IFERROR(INDEX(Raw_Financials!$H$2:$H$76, MATCH(1, (Raw_Financials!$A$2:$A$76="Gujarat Fluorochemicals")*(Raw_Financials!$B$2:$B$76="2024"),0)+1),"")=""),"",(IFERROR(INDEX(Raw_Financials!$G$2:$G$76, MATCH(1, (Raw_Financials!$A$2:$A$76="Gujarat Fluorochemicals")*(Raw_Financials!$B$2:$B$76="2024"),0)+1),""))-(IFERROR(INDEX(Raw_Financials!$H$2:$H$76, MATCH(1, (Raw_Financials!$A$2:$A$76="Gujarat Fluorochemicals")*(Raw_Financials!$B$2:$B$76="2024"),0)+1),"")))))} -> 3.2169044 | G26: {=IF(OR(IFERROR(INDEX(Raw_Financials!$O$2:$O$76, MATCH(1, (Raw_Financials!$A$2:$A$76="Gujarat Fluorochemicals")*(Raw_Financials!$B$2:$B$76="2024"),0)+1),"")="",IFERROR(INDEX(Raw_Financials!$M$2:$M$76, MATCH(1, (Raw_Financials!$A$2:$A$76="Gujarat Fluorochemicals")*(Raw_Financials!$B$2:$B$76="2024"),0)+1),"")=""),"",(IFERROR(INDEX(Raw_Financials!$O$2:$O$76, MATCH(1, (Raw_Financials!$A$2:$A$76="Gujarat Fluorochemicals")*(Raw_Financials!$B$2:$B$76="2024"),0)+1),""))/(IFERROR(INDEX(Raw_Financials!$M$2:$M$76, MATCH(1, (Raw_Financials!$A$2:$A$76="Gujarat Fluorochemicals")*(Raw_Financials!$B$2:$B$76="2024"),0)+1),"")))} -> 1.2992894 | H26: {=IF(OR(IFERROR(INDEX(Raw_Financials!$M$2:$M$76, MATCH(1, (Raw_Financials!$A$2:$A$76="Gujarat Fluorochemicals")*(Raw_Financials!$B$2:$B$76="2024"),0)+1),"")="",IFERROR(INDEX(Raw_Financials!$L$2:$L$76, MATCH(1, (Raw_Financials!$A$2:$A$76="Gujarat Fluorochemicals")*(Raw_Financials!$B$2:$B$76="2024"),0)+1),"")=""),"",(IFERROR(INDEX(Raw_Financials!$M$2:$M$76, MATCH(1, (Raw_Financials!$A$2:$A$76="Gujarat Fluorochemicals")*(Raw_Financials!$B$2:$B$76="2024"),0)+1),""))/(IFERROR(INDEX(Raw_Financials!$L$2:$L$76, MATCH(1, (Raw_Financials!$A$2:$A$76="Gujarat Fluorochemicals")*(Raw_Financials!$B$2:$B$76="2024"),0)+1),"")))} -> 4.2215547 | I26: {=IF(OR(IFERROR(INDEX(Raw_Financials!$N$2:$N$76, MATCH(1, (Raw_Financials!$A$2:$A$76="Gujarat Fluorochemicals")*(Raw_Financials!$B$2:$B$76="2024"),0)+1),"")="",IFERROR(INDEX(Raw_Financials!$J$2:$J$76, MATCH(1, (Raw_Financials!$A$2:$A$76="Gujarat Fluorochemicals")*(Raw_Financials!$B$2:$B$76="2024"),0)+1),"")=""),"",(IFERROR(INDEX(Raw_Financials!$N$2:$N$76, MATCH(1, (Raw_Financials!$A$2:$A$76="Gujarat Fluorochemicals")*(Raw_Financials!$B$2:$B$76="2024"),0)+1),""))-(IFERROR(INDEX(Raw_Financials!$J$2:$J$76, MATCH(1, (Raw_Financials!$A$2:$A$76="Gujarat Fluorochemicals")*(Raw_Financials!$B$2:$B$76="2024"),0)+1),"")))} -> 8261.43 | J26: {=IF(OR(IFERROR(INDEX(Raw_Financials!$M$2:$M$76, MATCH(1, (Raw_Financials!$A$2:$A$76="Gujarat Fluorochemicals")*(Raw_Financials!$B$2:$B$76="2024"),0)+1),"")="",IFERROR(INDEX(Raw_Financials!$C$2:$C$76, MATCH(1, (Raw_Financials!$A$2:$A$76="Gujarat Fluorochemicals")*(Raw_Financials!$B$2:$B$76="2024"),0)+1),"")=""),"",(IFERROR(INDEX(Raw_Financials!$M$2:$M$76, MATCH(1, (Raw_Financials!$A$2:$A$76="Gujarat Fluorochemicals")*(Raw_Financials!$B$2:$B$76="2024"),0)+1),""))/(IFERROR(INDEX(Raw_Financials!$C$2:$C$76, MATCH(1, (Raw_Financials!$A$2:$A$76="Gujarat Fluorochemicals")*(Raw_Financials!$B$2:$B$76="2024"),0)+1),"")))} -> 0.63663972 | K26: {=IF(OR(IFERROR(INDEX(Raw_ESG!$C$2:$C$76, MATCH(1, (Raw_ESG!$A$2:$A$76="Gujarat Fluorochemicals")*(Raw_ESG!$B$2:$B$76="2024"),0)+1),"")="",IFERROR(INDEX(Raw_Financials!$J$2:$J$76, MATCH(1, (Raw_Financials!$A$2:$A$76="Gujarat Fluorochemicals")*(Raw_Financials!$B$2:$B$76="2024"),0)+1),"")=""),"",(IFERROR(INDEX(Raw_ESG!$C$2:$C$76, MATCH(1, (Raw_ESG!$A$2:$A$76="Gujarat Fluorochemicals")*(Raw_ESG!$B$2:$B$76="2024"),0)+1),""))/(IFERROR(INDEX(Raw_Financials!$J$2:$J$76, MATCH(1, (Raw_Financials!$A$2:$A$76="Gujarat Fluorochemicals")*(Raw_Financials!$B$2:$B$76="2024"),0)+1),"")))} -> 0.56919437 | L26: {=IF(OR(IFERROR(INDEX(Raw_ESG!$D$2:$D$76, MATCH(1, (Raw_ESG!$A$2:$A$76="Gujarat Fluorochemicals")*(Raw_ESG!$B$2:$B$76="2024"),0)+1),"")="",IFERROR(INDEX(Raw_Financials!$E$2:$E$76, MATCH(1, (Raw_Financials!$A$2:$A$76="Gujarat Fluorochemicals")*(Raw_Financials!$B$2:$B$76="2024"),0)+1),"")=""),"",(IFERROR(INDEX(Raw_ESG!$D$2:$D$76, MATCH(1, (Raw_ESG!$A$2:$A$76="Gujarat Fluorochemicals")*(Raw_ESG!$B$2:$B$76="2024"),0)+1),""))/(IFERROR(INDEX(Raw_Financials!$E$2:$E$76, MATCH(1, (Raw_Financials!$A$2:$A$76="Gujarat Fluorochemicals")*(Raw_Financials!$B$2:$B$76="2024"),0)+1),"")))} -> 0.13541181 | M26: {=IF(OR(IFERROR(INDEX(Raw_ESG!$E$2:$E$76, MATCH(1, (Raw_ESG!$A$2:$A$76="Gujarat Fluorochemicals")*(Raw_ESG!$B$2:$B$76="2024"),0)+1),"")="",IFERROR(INDEX(Raw_ESG!$F$2:$F$76, MATCH(1, (Raw_ESG!$A$2:$A$76="Gujarat Fluorochemicals")*(Raw_ESG!$B$2:$B$76="2024"),0)+1),"")=""),"",(IFERROR(INDEX(Raw_ESG!$E$2:$E$76, MATCH(1, (Raw_ESG!$A$2:$A$76="Gujarat Fluorochemicals")*(Raw_ESG!$B$2:$B$76="2024"),0)+1),""))+(IFERROR(INDEX(Raw_ESG!$F$2:$F$76, MATCH(1, (Raw_ESG!$A$2:$A$76="Gujarat Fluorochemicals")*(Raw_ESG!$B$2:$B$76="2024"),0)+1),"")))} -> 107159.08 | N26: {=IFERROR(INDEX(Raw_ESG!$G$2:$G$76, MATCH(1, (Raw_ESG!$A$2:$A$76="Gujarat Fluorochemicals")*(Raw_ESG!$B$2:$B$76="2024"),0)+1),"")} -> 76.89
